Workbook

Sheet WACC
A1: Apple Inc. (AAPL) - Cost of Capital (WACC)
A2: CAPM & Capital Structure Analysis | Date: 2026-08-19
A4: 1. COST OF EQUITY (CAPM)
A5: Risk-Free Rate (10Y US Treasury) | B5: 0.0469
A6: Beta (5-Year Monthly vs S&P 500) | B6: 1.09
A7: Equity Risk Premium (ERP) | B7: 0.055
A8: Cost of Equity (Ke) | B8: =B5+B6*B7
A9: 2. COST OF DEBT
A10: Credit Rating (S&P / Moody's) | B10: AA+
A11: Pre-Tax Cost of Debt (Kd) | B11: 0.048
A12: Marginal / Effective Tax Rate | B12: =DCF!$C$12
A13: After-Tax Cost of Debt (Kd * (1 - t)) | B13: =B11*(1-B12)
A15: 3. CAPITAL STRUCTURE & MARKET VALUES
A16: Current Stock Price ($) | B16: =DCF!$C$8
A17: Diluted Shares Outstanding (M) | B17: =DCF!$C$9
A18: Market Capitalization ($M) | B18: =B16*B17
A19: Total Debt ($M) | B19: =DCF!$C$11
A20: Cash & Marketable Securities ($M) | B20: =DCF!$C$10
A21: Net Debt / (Net Cash) ($M) | B21: =B19-B20
A22: Enterprise Value ($M) | B22: =B18+B21
A24: 4. WEIGHTED AVERAGE COST OF CAPITAL (WACC)
A25: Component | B25: Weight | C25: Cost | D25: Contribution
A26: Equity | B26: =B18/B22 | C26: =B8 | D26: =B26*C26
A27: Debt (Net Debt Weight) | B27: =B21/B22 | C27: =B13 | D27: =B27*C27
A28: Market Value Weight / CAPM WACC | B28: =SUM(B26:B27) | C28: - | D28: =D26+D27
A29: Institutional Base WACC (Reflecting Long-Term Tech Target Structure) | B29: 0.078

Sheet DCF
A1: Apple Inc. (AAPL) - 5-Year DCF Valuation Model
A2: Ticker: AAPL | Currency: USD in Millions (except per share) | Date: 2026-08-19
A4: Active Scenario Selector (1 = Bear Case, 2 = Base Case, 3 = Bull Case): | B4: 2
A5: Active Scenario Selected: | B5: =IF(B4=1,"BEAR CASE",IF(B4=2,"BASE CASE","BULL CASE"))
A7: MARKET DATA & CAPITAL STRUCTURE
A8: Current Stock Price ($) | C8: 305.59
A9: Diluted Shares Outstanding (M) | C9: 14590
A10: Cash & Marketable Securities ($M) | C10: 156650
A11: Total Debt ($M) | C11: 106042
A12: Effective Tax Rate (%) | C12: 0.16
A13: Market Capitalization ($M) | C13: =C8*C9
A14: Net Debt / (Net Cash) ($M) | C14: =C11-C10
A15: Enterprise Value ($M) | C15: =C13+C14
A17: SCENARIO 1: BEAR CASE ASSUMPTIONS
A18: Historical / Projection Metric | B18: FY2022A | C18: FY2023A | D18: FY2024A | E18: FY2025A | F18: FY2026E | G18: FY2027E | H18: FY2028E | I18: FY2029E | J18: FY2030E | K18: Terminal
A19: Revenue Growth (%) | F19: 0.04 | G19: 0.035 | H19: 0.03 | I19: 0.025 | J19: 0.02 | K19: 0.02
A20: EBIT Margin (%) | F20: 0.3 | G20: 0.298 | H20: 0.295 | I20: 0.292 | J20: 0.29 | K20: 0.29
A21: D&A (% of Revenue) | F21: 0.029 | G21: 0.029 | H21: 0.029 | I21: 0.029 | J21: 0.029 | K21: 0.029
A22: CapEx (% of Revenue) | F22: 0.027 | G22: 0.027 | H22: 0.027 | I22: 0.027 | J22: 0.027 | K22: 0.027
A23: NWC Change (% of ΔRev) | F23: 0.02 | G23: 0.02 | H23: 0.02 | I23: 0.02 | J23: 0.02 | K23: 0.02
A24: Discount Rate (WACC) | F24: 0.085 | G24: 0.085 | H24: 0.085 | I24: 0.085 | J24: 0.085 | K24: 0.085
A25: Terminal Growth Rate (g) | K25: 0.02
A27: SCENARIO 2: BASE CASE ASSUMPTIONS (CONSENSUS & SERVICES EXPANSION)
A28: Historical / Projection Metric | B28: FY2022A | C28: FY2023A | D28: FY2024A | E28: FY2025A | F28: FY2026E | G28: FY2027E | H28: FY2028E | I28: FY2029E | J28: FY2030E | K28: Terminal
A29: Revenue Growth (%) | F29: 0.07 | G29: 0.065 | H29: 0.055 | I29: 0.045 | J29: 0.035 | K29: 0.025
A30: EBIT Margin (%) | F30: 0.32 | G30: 0.325 | H30: 0.328 | I30: 0.33 | J30: 0.332 | K30: 0.332
A31: D&A (% of Revenue) | F31: 0.028 | G31: 0.028 | H31: 0.028 | I31: 0.028 | J31: 0.028 | K31: 0.028
A32: CapEx (% of Revenue) | F32: 0.025 | G32: 0.025 | H32: 0.025 | I32: 0.025 | J32: 0.025 | K32: 0.025
A33: NWC Change (% of ΔRev) | F33: -0.015 | G33: -0.015 | H33: -0.015 | I33: -0.015 | J33: -0.015 | K33: -0.015
A34: Discount Rate (WACC) | F34: 0.078 | G34: 0.078 | H34: 0.078 | I34: 0.078 | J34: 0.078 | K34: 0.078
A35: Terminal Growth Rate (g) | K35: 0.025
A37: SCENARIO 3: BULL CASE ASSUMPTIONS (AI SUPERCYCLE)
A38: Historical / Projection Metric | B38: FY2022A | C38: FY2023A | D38: FY2024A | E38: FY2025A | F38: FY2026E | G38: FY2027E | H38: FY2028E | I38: FY2029E | J38: FY2030E | K38: Terminal
A39: Revenue Growth (%) | F39: 0.1 | G39: 0.09 | H39: 0.08 | I39: 0.065 | J39: 0.05 | K39: 0.03
A40: EBIT Margin (%) | F40: 0.335 | G40: 0.34 | H40: 0.345 | I40: 0.348 | J40: 0.35 | K40: 0.35
A41: D&A (% of Revenue) | F41: 0.027 | G41: 0.027 | H41: 0.027 | I41: 0.027 | J41: 0.027 | K41: 0.027
A42: CapEx (% of Revenue) | F42: 0.024 | G42: 0.024 | H42: 0.024 | I42: 0.024 | J42: 0.024 | K42: 0.024
A43: NWC Change (% of ΔRev) | F43: -0.02 | G43: -0.02 | H43: -0.02 | I43: -0.02 | J43: -0.02 | K43: -0.02
A44: Discount Rate (WACC) | F44: 0.072 | G44: 0.072 | H44: 0.072 | I44: 0.072 | J44: 0.072 | K44: 0.072
A45: Terminal Growth Rate (g) | K45: 0.03
A47: ACTIVE / CONSOLIDATED CASE ASSUMPTIONS (DYNAMIC TO SELECTOR)
A48: Historical / Projection Metric | B48: FY2022A | C48: FY2023A | D48: FY2024A | E48: FY2025A | F48: FY2026E | G48: FY2027E | H48: FY2028E | I48: FY2029E | J48: FY2030E | K48: Terminal
A49: Revenue Growth (%) | B49: 0.078 | C49: -0.028 | D49: 0.02 | E49: 0.064 | F49: =IF($B$4=1,F19,IF($B$4=2,F29,F39)) | G49: =IF($B$4=1,G19,IF($B$4=2,G29,G39)) | H49: =IF($B$4=1,H19,IF($B$4=2,H29,H39)) | I49: =IF($B$4=1,I19,IF($B$4=2,I29,I39)) | J49: =IF($B$4=1,J19,IF($B$4=2,J29,J39)) | K49: =IF($B$4=1,K19,IF($B$4=2,K29,K39))
A50: EBIT Margin (%) | B50: 0.303 | C50: 0.298 | D50: 0.315 | E50: 0.32 | F50: =IF($B$4=1,F20,IF($B$4=2,F30,F40)) | G50: =IF($B$4=1,G20,IF($B$4=2,G30,G40)) | H50: =IF($B$4=1,H20,IF($B$4=2,H30,H40)) | I50: =IF($B$4=1,I20,IF($B$4=2,I30,I40)) | J50: =IF($B$4=1,J20,IF($B$4=2,J30,J40)) | K50: =IF($B$4=1,K20,IF($B$4=2,K30,K40))
A51: D&A (% of Revenue) | B51: 0.028 | C51: 0.03 | D51: 0.029 | E51: 0.028 | F51: =IF($B$4=1,F21,IF($B$4=2,F31,F41)) | G51: =IF($B$4=1,G21,IF($B$4=2,G31,G41)) | H51: =IF($B$4=1,H21,IF($B$4=2,H31,H41)) | I51: =IF($B$4=1,I21,IF($B$4=2,I31,I41)) | J51: =IF($B$4=1,J21,IF($B$4=2,J31,J41)) | K51: =IF($B$4=1,K21,IF($B$4=2,K31,K41))
A52: CapEx (% of Revenue) | B52: 0.027 | C52: 0.029 | D52: 0.024 | E52: 0.025 | F52: =IF($B$4=1,F22,IF($B$4=2,F32,F42)) | G52: =IF($B$4=1,G22,IF($B$4=2,G32,G42)) | H52: =IF($B$4=1,H22,IF($B$4=2,H32,H42)) | I52: =IF($B$4=1,I22,IF($B$4=2,I32,I42)) | J52: =IF($B$4=1,J22,IF($B$4=2,J32,J42)) | K52: =IF($B$4=1,K22,IF($B$4=2,K32,K42))
A53: NWC Change (% of ΔRev) | B53: -0.006 | C53: -0.012 | D53: -0.016 | E53: -0.012 | F53: =IF($B$4=1,F23,IF($B$4=2,F33,F43)) | G53: =IF($B$4=1,G23,IF($B$4=2,G33,G43)) | H53: =IF($B$4=1,H23,IF($B$4=2,H33,H43)) | I53: =IF($B$4=1,I23,IF($B$4=2,I33,I43)) | J53: =IF($B$4=1,J23,IF($B$4=2,J33,J43)) | K53: =IF($B$4=1,K23,IF($B$4=2,K33,K43))
A54: Discount Rate (WACC) | F54: =IF($B$4=1,F24,IF($B$4=2,F34,F44)) | G54: =IF($B$4=1,G24,IF($B$4=2,G34,G44)) | H54: =IF($B$4=1,H24,IF($B$4=2,H34,H44)) | I54: =IF($B$4=1,I24,IF($B$4=2,I34,I44)) | J54: =IF($B$4=1,J24,IF($B$4=2,J34,J44)) | K54: =IF($B$4=1,K24,IF($B$4=2,K34,K44))
A55: Terminal Growth Rate (g) | K55: =IF($B$4=1,K25,IF($B$4=2,K35,K45))
A57: HISTORICAL & PROJECTED FINANCIALS ($M)
A58: Historical / Projection Metric | B58: FY2022A | C58: FY2023A | D58: FY2024A | E58: FY2025A | F58: FY2026E | G58: FY2027E | H58: FY2028E | I58: FY2029E | J58: FY2030E | K58: Terminal
A59: Revenue ($M) | B59: 394328 | C59: 383285 | D59: 391035 | E59: 416161 | F59: =E59*(1+F49) | G59: =F59*(1+G49) | H59: =G59*(1+H49) | I59: =H59*(1+I49) | J59: =I59*(1+J49) | K59: =J59*(1+K55)
A60: YoY Growth (%) | B60: 0.078 | C60: =C59/B59-1 | D60: =D59/C59-1 | E60: =E59/D59-1 | F60: =F59/E59-1 | G60: =G59/F59-1 | H60: =H59/G59-1 | I60: =I59/H59-1 | J60: =J59/I59-1 | K60: =K59/J59-1
A61: Gross Profit ($M) | B61: 170782 | C61: 169148 | D61: 180683 | E61: 195201 | F61: =F59*0.470 | G61: =G59*0.470 | H61: =H59*0.470 | I61: =I59*0.470 | J61: =J59*0.470 | K61: =K59*0.470
A62: Gross Margin (%) | B62: =B61/B59 | C62: =C61/C59 | D62: =D61/D59 | E62: =E61/E59 | F62: =F61/F59 | G62: =G61/G59 | H62: =H61/H59 | I62: =I61/I59 | ... K62: =K61/K59
A63: Operating Expenses ($M) | B63: 51345 | C63: 54847 | D63: 57467 | E63: 62151 | F63: =F61-F64 | G63: =G61-G64 | H63: =H61-H64 | I63: =I61-I64 | J63: =J61-J64 | K63: =K61-K64
A64: Operating Income (EBIT) ($M) | B64: 119437 | C64: 114301 | D64: 123216 | E64: 133050 | F64: =F59*F50 | G64: =G59*G50 | H64: =H59*H50 | I64: =I59*I50 | J64: =J59*J50 | K64: =K59*K50
A65: EBIT Margin (%) | B65: =B64/B59 | C65: =C64/C59 | D65: =D64/D59 | E65: =E64/E59 | F65: =F64/F59 | G65: =G64/G59 | H65: =H64/H59 | I65: =I64/I59 | ... K65: =K64/K59
A66: Taxes on Operating Income ($M) | B66: =B64*$C$12 | C66: =C64*$C$12 | D66: =D64*$C$12 | E66: =E64*$C$12 | F66: =F64*$C$12 | G66: =G64*$C$12 | H66: =H64*$C$12 | I66: =I64*$C$12 | ... K66: =K64*$C$12
A67: NOPAT (Net Operating Profit After Tax) ($M) | B67: =B64-B66 | C67: =C64-C66 | D67: =D64-D66 | E67: =E64-E66 | F67: =F64-F66 | G67: =G64-G66 | H67: =H64-H66 | I67: =I64-I66 | ... K67: =K64-K66
A69: UNLEVERED FREE CASH FLOW (UFCF) BUILD ($M)
A70: Historical / Projection Metric | B70: FY2022A | C70: FY2023A | D70: FY2024A | E70: FY2025A | F70: FY2026E | G70: FY2027E | H70: FY2028E | I70: FY2029E | J70: FY2030E | K70: Terminal
A71: NOPAT ($M) | B71: =B67 | C71: =C67 | D71: =D67 | E71: =E67 | F71: =F67 | G71: =G67 | H71: =H67 | I71: =I67 | ... K71: =K67
A72: (+) Depreciation & Amortization ($M) | B72: 11104 | C72: 11519 | D72: 11445 | E72: 11800 | F72: =F59*F51 | G72: =G59*G51 | H72: =H59*H51 | I72: =I59*I51 | J72: =J59*J51 | K72: =K59*K51
A73: (-) Capital Expenditures (CapEx) ($M) | B73: 10708 | C73: 10959 | D73: 9447 | E73: 10200 | F73: =F59*F52 | G73: =G59*G52 | H73: =H59*H52 | I73: =I59*I52 | J73: =J59*J52 | K73: =K59*K52
A74: (-) Change in Non-Cash Working Capital (ΔNWC) ($M) | B74: -2277 | C74: -4431 | D74: -6190 | E74: -5000 | F74: =(F59-E59)*F53 | G74: =(G59-F59)*G53 | H74: =(H59-G59)*H53 | I74: =(I59-H59)*I53 | J74: =(J59-I59)*J53 | K74: =(K59-J59)*K53
A75: Unlevered Free Cash Flow (UFCF) ($M) | B75: =B71+B72-B73-B74 | C75: =C71+C72-C73-C74 | D75: =D71+D72-D73-D74 | E75: =E71+E72-E73-E74 | F75: =F71+F72-F73-F74 | G75: =G71+G72-G73-G74 | H75: =H71+H72-H73-H74 | I75: =I71+I72-I73-I74 | ... K75: =K71+K72-K73-K74
A76: FCF Conversion (% of NOPAT) | B76: =B75/B71 | C76: =C75/C71 | D76: =D75/D71 | E76: =E75/E71 | F76: =F75/F71 | G76: =G75/G71 | H76: =H75/H71 | I76: =I75/I71 | ... K76: =K75/K71
A78: DISCOUNTING & DCF VALUATION SCHEDULE ($M)
A79: Historical / Projection Metric | B79: FY2022A | C79: FY2023A | D79: FY2024A | E79: FY2025A | F79: FY2026E | G79: FY2027E | H79: FY2028E | I79: FY2029E | J79: FY2030E | K79: Terminal
A80: Unlevered Free Cash Flow ($M) | F80: =F75 | G80: =G75 | H80: =H75 | I80: =I75 | J80: =J75 | K80: =K75
A81: Discount Period (Years, Mid-Year Convention) | F81: 0.5 | G81: 1.5 | H81: 2.5 | I81: 3.5 | J81: 4.5 | K81: 5
A82: Discount Factor | F82: =1/(1+F54)^F81 | G82: =1/(1+G54)^G81 | H82: =1/(1+H54)^H81 | I82: =1/(1+I54)^I81 | J82: =1/(1+J54)^J81 | K82: =1/(1+$K$54)^K81
A83: Present Value of FCF ($M) | F83: =F80*F82 | G83: =G80*G82 | H83: =H80*H82 | I83: =I80*I82 | J83: =J80*J82 | K83: =K85*K82
A84: Terminal Growth Rate (g) | K84: =$K$55
A85: Terminal Value (Undiscounted) ($M) | K85: =K80/($K$54-$K$55)
A86: Present Value of Terminal Value ($M) | K86: =K85*K82
A88: EQUITY VALUE BRIDGE & IMPLIED VALUATION ($M)
A89: Cumulative PV of 5-Year Explicit FCFs ($M) | C89: =SUM(F83:J83)
A90: Present Value of Terminal Value ($M) | C90: =K86
A91: Implied Enterprise Value ($M) | C91: =C89+C90
A92: (-) Total Debt ($M) | C92: =$C$11
A93: (+) Cash & Marketable Securities ($M) | C93: =$C$10
A94: (-) Net Debt / (+) Net Cash ($M) | C94: =$C$14
A95: Implied Equity Value ($M) | C95: =C91-C94
A96: Diluted Shares Outstanding (M) | C96: =$C$9
A97: IMPLIED SHARE PRICE ($ / Share) | C97: =C95/C96
A98: Current Stock Price ($ / Share) | C98: =$C$8
A99: Implied Upside / (Downside) (%) | C99: =(C97/C98)-1
A100: Terminal Value % of Enterprise Value | C100: =C90/C91
A103: SENSITIVITY 1: WACC vs. Terminal Growth Rate (Implied Share Price $)
A104: WACC \ g | B104: 0.015 | C104: 0.02 | D104: 0.025 | E104: 0.03 | F104: 0.035
A105: 0.068 | B105: =((($F$80/(1+$A105)^$F$81 + $G$80/(1+$A105)^$G$81 + $H$80/(1+$A105)^$H$81 + $I$80/(1+$A105)^$I$81 + $J$80/(1+$A105)^$J$81) + (($J$80*(1+B$104)/($A105-B$104))/(1+$A105)^$K$81)) - $C$14)/$C$9 | C105: =((($F$80/(1+$A105)^$F$81 + $G$80/(1+$A105)^$G$81 + $H$80/(1+$A105)^$H$81 + $I$80/(1+$A105)^$I$81 + $J$80/(1+$A105)^$J$81) + (($J$80*(1+C$104)/($A105-C$104))/(1+$A105)^$K$81)) - $C$14)/$C$9 | D105: =((($F$80/(1+$A105)^$F$81 + $G$80/(1+$A105)^$G$81 + $H$80/(1+$A105)^$H$81 + $I$80/(1+$A105)^$I$81 + $J$80/(1+$A105)^$J$81) + (($J$80*(1+D$104)/($A105-D$104))/(1+$A105)^$K$81)) - $C$14)/$C$9 | E105: =((($F$80/(1+$A105)^$F$81 + $G$80/(1+$A105)^$G$81 + $H$80/(1+$A105)^$H$81 + $I$80/(1+$A105)^$I$81 + $J$80/(1+$A105)^$J$81) + (($J$80*(1+E$104)/($A105-E$104))/(1+$A105)^$K$81)) - $C$14)/$C$9 | F105: =((($F$80/(1+$A105)^$F$81 + $G$80/(1+$A105)^$G$81 + $H$80/(1+$A105)^$H$81 + $I$80/(1+$A105)^$I$81 + $J$80/(1+$A105)^$J$81) + (($J$80*(1+F$104)/($A105-F$104))/(1+$A105)^$K$81)) - $C$14)/$C$9
A106: 0.073 | B106: =((($F$80/(1+$A106)^$F$81 + $G$80/(1+$A106)^$G$81 + $H$80/(1+$A106)^$H$81 + $I$80/(1+$A106)^$I$81 + $J$80/(1+$A106)^$J$81) + (($J$80*(1+B$104)/($A106-B$104))/(1+$A106)^$K$81)) - $C$14)/$C$9 | C106: =((($F$80/(1+$A106)^$F$81 + $G$80/(1+$A106)^$G$81 + $H$80/(1+$A106)^$H$81 + $I$80/(1+$A106)^$I$81 + $J$80/(1+$A106)^$J$81) + (($J$80*(1+C$104)/($A106-C$104))/(1+$A106)^$K$81)) - $C$14)/$C$9 | D106: =((($F$80/(1+$A106)^$F$81 + $G$80/(1+$A106)^$G$81 + $H$80/(1+$A106)^$H$81 + $I$80/(1+$A106)^$I$81 + $J$80/(1+$A106)^$J$81) + (($J$80*(1+D$104)/($A106-D$104))/(1+$A106)^$K$81)) - $C$14)/$C$9 | E106: =((($F$80/(1+$A106)^$F$81 + $G$80/(1+$A106)^$G$81 + $H$80/(1+$A106)^$H$81 + $I$80/(1+$A106)^$I$81 + $J$80/(1+$A106)^$J$81) + (($J$80*(1+E$104)/($A106-E$104))/(1+$A106)^$K$81)) - $C$14)/$C$9 | F106: =((($F$80/(1+$A106)^$F$81 + $G$80/(1+$A106)^$G$81 + $H$80/(1+$A106)^$H$81 + $I$80/(1+$A106)^$I$81 + $J$80/(1+$A106)^$J$81) + (($J$80*(1+F$104)/($A106-F$104))/(1+$A106)^$K$81)) - $C$14)/$C$9
A107: 0.078 | B107: =((($F$80/(1+$A107)^$F$81 + $G$80/(1+$A107)^$G$81 + $H$80/(1+$A107)^$H$81 + $I$80/(1+$A107)^$I$81 + $J$80/(1+$A107)^$J$81) + (($J$80*(1+B$104)/($A107-B$104))/(1+$A107)^$K$81)) - $C$14)/$C$9 | C107: =((($F$80/(1+$A107)^$F$81 + $G$80/(1+$A107)^$G$81 + $H$80/(1+$A107)^$H$81 + $I$80/(1+$A107)^$I$81 + $J$80/(1+$A107)^$J$81) + (($J$80*(1+C$104)/($A107-C$104))/(1+$A107)^$K$81)) - $C$14)/$C$9 | D107: =((($F$80/(1+$A107)^$F$81 + $G$80/(1+$A107)^$G$81 + $H$80/(1+$A107)^$H$81 + $I$80/(1+$A107)^$I$81 + $J$80/(1+$A107)^$J$81) + (($J$80*(1+D$104)/($A107-D$104))/(1+$A107)^$K$81)) - $C$14)/$C$9 | E107: =((($F$80/(1+$A107)^$F$81 + $G$80/(1+$A107)^$G$81 + $H$80/(1+$A107)^$H$81 + $I$80/(1+$A107)^$I$81 + $J$80/(1+$A107)^$J$81) + (($J$80*(1+E$104)/($A107-E$104))/(1+$A107)^$K$81)) - $C$14)/$C$9 | F107: =((($F$80/(1+$A107)^$F$81 + $G$80/(1+$A107)^$G$81 + $H$80/(1+$A107)^$H$81 + $I$80/(1+$A107)^$I$81 + $J$80/(1+$A107)^$J$81) + (($J$80*(1+F$104)/($A107-F$104))/(1+$A107)^$K$81)) - $C$14)/$C$9
A108: 0.083 | B108: =((($F$80/(1+$A108)^$F$81 + $G$80/(1+$A108)^$G$81 + $H$80/(1+$A108)^$H$81 + $I$80/(1+$A108)^$I$81 + $J$80/(1+$A108)^$J$81) + (($J$80*(1+B$104)/($A108-B$104))/(1+$A108)^$K$81)) - $C$14)/$C$9 | C108: =((($F$80/(1+$A108)^$F$81 + $G$80/(1+$A108)^$G$81 + $H$80/(1+$A108)^$H$81 + $I$80/(1+$A108)^$I$81 + $J$80/(1+$A108)^$J$81) + (($J$80*(1+C$104)/($A108-C$104))/(1+$A108)^$K$81)) - $C$14)/$C$9 | D108: =((($F$80/(1+$A108)^$F$81 + $G$80/(1+$A108)^$G$81 + $H$80/(1+$A108)^$H$81 + $I$80/(1+$A108)^$I$81 + $J$80/(1+$A108)^$J$81) + (($J$80*(1+D$104)/($A108-D$104))/(1+$A108)^$K$81)) - $C$14)/$C$9 | E108: =((($F$80/(1+$A108)^$F$81 + $G$80/(1+$A108)^$G$81 + $H$80/(1+$A108)^$H$81 + $I$80/(1+$A108)^$I$81 + $J$80/(1+$A108)^$J$81) + (($J$80*(1+E$104)/($A108-E$104))/(1+$A108)^$K$81)) - $C$14)/$C$9 | F108: =((($F$80/(1+$A108)^$F$81 + $G$80/(1+$A108)^$G$81 + $H$80/(1+$A108)^$H$81 + $I$80/(1+$A108)^$I$81 + $J$80/(1+$A108)^$J$81) + (($J$80*(1+F$104)/($A108-F$104))/(1+$A108)^$K$81)) - $C$14)/$C$9
A109: 0.088 | B109: =((($F$80/(1+$A109)^$F$81 + $G$80/(1+$A109)^$G$81 + $H$80/(1+$A109)^$H$81 + $I$80/(1+$A109)^$I$81 + $J$80/(1+$A109)^$J$81) + (($J$80*(1+B$104)/($A109-B$104))/(1+$A109)^$K$81)) - $C$14)/$C$9 | C109: =((($F$80/(1+$A109)^$F$81 + $G$80/(1+$A109)^$G$81 + $H$80/(1+$A109)^$H$81 + $I$80/(1+$A109)^$I$81 + $J$80/(1+$A109)^$J$81) + (($J$80*(1+C$104)/($A109-C$104))/(1+$A109)^$K$81)) - $C$14)/$C$9 | D109: =((($F$80/(1+$A109)^$F$81 + $G$80/(1+$A109)^$G$81 + $H$80/(1+$A109)^$H$81 + $I$80/(1+$A109)^$I$81 + $J$80/(1+$A109)^$J$81) + (($J$80*(1+D$104)/($A109-D$104))/(1+$A109)^$K$81)) - $C$14)/$C$9 | E109: =((($F$80/(1+$A109)^$F$81 + $G$80/(1+$A109)^$G$81 + $H$80/(1+$A109)^$H$81 + $I$80/(1+$A109)^$I$81 + $J$80/(1+$A109)^$J$81) + (($J$80*(1+E$104)/($A109-E$104))/(1+$A109)^$K$81)) - $C$14)/$C$9 | F109: =((($F$80/(1+$A109)^$F$81 + $G$80/(1+$A109)^$G$81 + $H$80/(1+$A109)^$H$81 + $I$80/(1+$A109)^$I$81 + $J$80/(1+$A109)^$J$81) + (($J$80*(1+F$104)/($A109-F$104))/(1+$A109)^$K$81)) - $C$14)/$C$9
A112: SENSITIVITY 2: FY2026E Revenue Growth vs. FY2026E EBIT Margin (Implied Share Price $)
A113: Rev Growth \ EBIT Margin | B113: 0.3 | C113: 0.31 | D113: 0.32 | E113: 0.33 | F113: 0.34
A114: 0.05 | B114: =(($C$89+$C$90)*(B$113/$F$50)*((1+$A114)/(1+$F$49))-$C$14)/$C$9 | C114: =(($C$89+$C$90)*(C$113/$F$50)*((1+$A114)/(1+$F$49))-$C$14)/$C$9 | D114: =(($C$89+$C$90)*(D$113/$F$50)*((1+$A114)/(1+$F$49))-$C$14)/$C$9 | E114: =(($C$89+$C$90)*(E$113/$F$50)*((1+$A114)/(1+$F$49))-$C$14)/$C$9 | F114: =(($C$89+$C$90)*(F$113/$F$50)*((1+$A114)/(1+$F$49))-$C$14)/$C$9
...
