Workbook

Sheet DCF
A1: Amazon.com, Inc. (NASDAQ: AMZN) - Discounted Cash Flow Valuation Model
A2: Valuation Date: August 19, 2026 | Currency: USD in Millions (except per-share data) | Fiscal Year End: Dec 31
A4: SCENARIO SELECTOR: | B4: 2 | C4: =IF(B4=1,"[ BEAR CASE ACTIVE ]",IF(B4=2,"[ BASE CASE ACTIVE ]","[ BULL CASE ACTIVE ]"))
A6: 1. MARKET DATA & CAPITAL STRUCTURE INPUTS
A8: Current Share Price ($) | B8: 265
A9: Diluted Shares Outstanding (M) | B9: 10740
A10: Market Capitalization ($M) | B10: =B8*B9
A11: Cash, Cash Eq. & Marketable Securities ($M) | B11: 123029
A12: Total Debt ($M) | B12: 65648
A13: Net Debt / (Net Cash) ($M) | B13: =B12-B11
A14: Current Enterprise Value ($M) | B14: =B10+B13
A16: 2. SCENARIO ASSUMPTIONS (BEAR / BASE / BULL)
A18: BEAR CASE ASSUMPTIONS (Scenario 1) | F18: FY2026E | G18: FY2027E | H18: FY2028E | I18: FY2029E | J18: FY2030E
A19: Revenue Growth (%) | F19: 0.1 | G19: 0.09 | H19: 0.08 | I19: 0.07 | J19: 0.06
A20: EBIT Margin (%) | F20: 0.11 | G20: 0.115 | H20: 0.12 | I20: 0.12 | J20: 0.12
A21: D&A (% of Revenue) | F21: 0.09 | G21: 0.088 | H21: 0.085 | I21: 0.083 | J21: 0.08
A22: CapEx (% of Revenue) | F22: 0.155 | G22: 0.145 | H22: 0.135 | I22: 0.125 | J22: 0.115
A23: Change in NWC (% of ΔRev) | F23: -0.01 | G23: -0.01 | H23: -0.01 | I23: -0.01 | J23: -0.01
A24: Tax Rate (%) | F24: 0.21 | G24: 0.21 | H24: 0.21 | I24: 0.21 | J24: 0.21
A25: Terminal Growth Rate (g) | F25: 0.025 | G25: 0.025 | H25: 0.025 | I25: 0.025 | J25: 0.025
A26: Discount Rate (WACC) | F26: 0.095 | G26: 0.095 | H26: 0.095 | I26: 0.095 | J26: 0.095
A28: BASE CASE ASSUMPTIONS (Scenario 2 - Consensus / Recommended) | F28: FY2026E | G28: FY2027E | H28: FY2028E | I28: FY2029E | J28: FY2030E
A29: Revenue Growth (%) | F29: 0.13 | G29: 0.12 | H29: 0.11 | I29: 0.095 | J29: 0.085
A30: EBIT Margin (%) | F30: 0.12 | G30: 0.135 | H30: 0.145 | I30: 0.155 | J30: 0.16
A31: D&A (% of Revenue) | F31: 0.09 | G31: 0.088 | H31: 0.085 | I31: 0.082 | J31: 0.08
A32: CapEx (% of Revenue) | F32: 0.145 | G32: 0.13 | H32: 0.115 | I32: 0.1 | J32: 0.09
A33: Change in NWC (% of ΔRev) | F33: -0.01 | G33: -0.01 | H33: -0.01 | I33: -0.01 | J33: -0.01
A34: Tax Rate (%) | F34: 0.21 | G34: 0.21 | H34: 0.21 | I34: 0.21 | J34: 0.21
A35: Terminal Growth Rate (g) | F35: 0.03 | G35: 0.03 | H35: 0.03 | I35: 0.03 | J35: 0.03
A36: Discount Rate (WACC) | F36: 0.085 | G36: 0.085 | H36: 0.085 | I36: 0.085 | J36: 0.085
A38: BULL CASE ASSUMPTIONS (Scenario 3) | F38: FY2026E | G38: FY2027E | H38: FY2028E | I38: FY2029E | J38: FY2030E
A39: Revenue Growth (%) | F39: 0.155 | G39: 0.145 | H39: 0.13 | I39: 0.115 | J39: 0.1
A40: EBIT Margin (%) | F40: 0.13 | G40: 0.15 | H40: 0.165 | I40: 0.175 | J40: 0.18
A41: D&A (% of Revenue) | F41: 0.09 | G41: 0.085 | H41: 0.08 | I41: 0.078 | J41: 0.075
A42: CapEx (% of Revenue) | F42: 0.135 | G42: 0.12 | H42: 0.105 | I42: 0.09 | J42: 0.08
A43: Change in NWC (% of ΔRev) | F43: -0.01 | G43: -0.01 | H43: -0.01 | I43: -0.01 | J43: -0.01
A44: Tax Rate (%) | F44: 0.21 | G44: 0.21 | H44: 0.21 | I44: 0.21 | J44: 0.21
A45: Terminal Growth Rate (g) | F45: 0.035 | G45: 0.035 | H45: 0.035 | I45: 0.035 | J45: 0.035
A46: Discount Rate (WACC) | F46: 0.078 | G46: 0.078 | H46: 0.078 | I46: 0.078 | J46: 0.078
A48: ACTIVE CONSOLIDATED ASSUMPTIONS (Driven by Case Selector B4) | F48: FY2026E | G48: FY2027E | H48: FY2028E | I48: FY2029E | J48: FY2030E
A49: Revenue Growth (%) | F49: =IF($B$4=1,F19,IF($B$4=2,F29,F39)) | G49: =IF($B$4=1,G19,IF($B$4=2,G29,G39)) | H49: =IF($B$4=1,H19,IF($B$4=2,H29,H39)) | I49: =IF($B$4=1,I19,IF($B$4=2,I29,I39)) | J49: =IF($B$4=1,J19,IF($B$4=2,J29,J39))
A50: EBIT Margin (%) | F50: =IF($B$4=1,F20,IF($B$4=2,F30,F40)) | G50: =IF($B$4=1,G20,IF($B$4=2,G30,G40)) | H50: =IF($B$4=1,H20,IF($B$4=2,H30,H40)) | I50: =IF($B$4=1,I20,IF($B$4=2,I30,I40)) | J50: =IF($B$4=1,J20,IF($B$4=2,J30,J40))
A51: D&A (% of Revenue) | F51: =IF($B$4=1,F21,IF($B$4=2,F31,F41)) | G51: =IF($B$4=1,G21,IF($B$4=2,G31,G41)) | H51: =IF($B$4=1,H21,IF($B$4=2,H31,H41)) | I51: =IF($B$4=1,I21,IF($B$4=2,I31,I41)) | J51: =IF($B$4=1,J21,IF($B$4=2,J31,J41))
A52: CapEx (% of Revenue) | F52: =IF($B$4=1,F22,IF($B$4=2,F32,F42)) | G52: =IF($B$4=1,G22,IF($B$4=2,G32,G42)) | H52: =IF($B$4=1,H22,IF($B$4=2,H32,H42)) | I52: =IF($B$4=1,I22,IF($B$4=2,I32,I42)) | J52: =IF($B$4=1,J22,IF($B$4=2,J32,J42))
A53: Change in NWC (% of ΔRev) | F53: =IF($B$4=1,F23,IF($B$4=2,F33,F43)) | G53: =IF($B$4=1,G23,IF($B$4=2,G33,G43)) | H53: =IF($B$4=1,H23,IF($B$4=2,H33,H43)) | I53: =IF($B$4=1,I23,IF($B$4=2,I33,I43)) | J53: =IF($B$4=1,J23,IF($B$4=2,J33,J43))
A54: Tax Rate (%) | F54: =IF($B$4=1,F24,IF($B$4=2,F34,F44)) | G54: =IF($B$4=1,G24,IF($B$4=2,G34,G44)) | H54: =IF($B$4=1,H24,IF($B$4=2,H34,H44)) | I54: =IF($B$4=1,I24,IF($B$4=2,I34,I44)) | J54: =IF($B$4=1,J24,IF($B$4=2,J34,J44))
A55: Terminal Growth Rate (g) | F55: =IF($B$4=1,F25,IF($B$4=2,F35,F45)) | G55: =IF($B$4=1,G25,IF($B$4=2,G35,G45)) | H55: =IF($B$4=1,H25,IF($B$4=2,H35,H45)) | I55: =IF($B$4=1,I25,IF($B$4=2,I35,I45)) | J55: =IF($B$4=1,J25,IF($B$4=2,J35,J45))
A56: Discount Rate (WACC) | F56: =IF($B$4=1,F26,IF($B$4=2,F36,F46)) | G56: =IF($B$4=1,G26,IF($B$4=2,G36,G46)) | H56: =IF($B$4=1,H26,IF($B$4=2,H36,H46)) | I56: =IF($B$4=1,I26,IF($B$4=2,I36,I46)) | J56: =IF($B$4=1,J26,IF($B$4=2,J36,J46))
A58: 3. HISTORICAL & PROJECTED FINANCIAL PERFORMANCE ($M)
A59: Financial Metric / Projection Year | B59: 2022A | C59: 2023A | D59: 2024A | E59: 2025A | F59: FY2026E | G59: FY2027E | H59: FY2028E | I59: FY2029E | J59: FY2030E
A60: Revenue (Net Sales) | B60: 513983 | C60: 574785 | D60: 637959 | E60: 716924 | F60: =E60*(1+F49) | G60: =F60*(1+G49) | H60: =G60*(1+H49) | I60: =H60*(1+I49) | J60: =I60*(1+J49)
A61: YoY Revenue Growth (%) | B61: 0.094 | C61: =C60/B60-1 | D61: =D60/C60-1 | E61: =E60/D60-1 | F61: =F60/E60-1 | G61: =G60/F60-1 | H61: =H60/G60-1 | I61: =I60/H60-1 | J61: =J60/I60-1
A62: Gross Profit | B62: 225152 | C62: 270046 | D62: 311671 | E62: 360510 | F62: =F60*(0.503+(4-3)*0.005) | G62: =G60*(0.503+(5-3)*0.005) | H62: =H60*(0.503+(6-3)*0.005) | I62: =I60*(0.503+(7-3)*0.005) | J62: =J60*(0.503+(8-3)*0.005)
A63: Gross Margin (%) | B63: =B62/B60 | C63: =C62/C60 | D63: =D62/D60 | E63: =E62/E60 | F63: =F62/F60 | G63: =G62/G60 | H63: =H62/H60 | I63: =I62/I60 | J63: =J62/J60
A64: Operating Income (EBIT) | B64: 12248 | C64: 36852 | D64: 68593 | E64: 79975 | F64: =F60*F50 | G64: =G60*G50 | H64: =H60*H50 | I64: =I60*I50 | J64: =J60*J50
A65: EBIT Margin (%) | B65: =B64/B60 | C65: =C64/C60 | D65: =D64/D60 | E65: =E64/E60 | F65: =F64/F60 | G65: =G64/G60 | H65: =H64/H60 | I65: =I64/I60 | J65: =J64/J60
A66: (-) Provision for Income Taxes | B66: -3216 | C66: 7120 | D66: 13745 | E66: 16795 | F66: =F64*F54 | G66: =G64*G54 | H66: =H64*H54 | I66: =I64*I54 | J66: =J64*J54
A67: (=) Net Operating Profit After Tax (NOPAT) | B67: =B64-B66 | C67: =C64-C66 | D67: =D64-D66 | E67: =E64-E66 | F67: =F64-F66 | G67: =G64-G66 | H67: =H64-H66 | I67: =I64-I66 | J67: =J64-J66
A68: (+) Depreciation & Amortization (D&A) | B68: 41921 | C68: 48663 | D68: 52795 | E68: 65756 | F68: =F60*F51 | G68: =G60*G51 | H68: =H60*H51 | I68: =I60*I51 | J68: =J60*J51
A69: (-) Capital Expenditures (CapEx) | B69: 63645 | C69: 52729 | D69: 82999 | E69: 131819 | F69: =F60*F52 | G69: =G60*G52 | H69: =H60*H52 | I69: =I60*I52 | J69: =J60*J52
A70: (-) Change in Net Working Capital (Δ NWC) | B70: -1823 | C70: -2145 | D70: -1560 | E70: -1890 | F70: =(F60-E60)*F53 | G70: =(G60-F60)*G53 | H70: =(H60-G60)*H53 | I70: =(I60-H60)*I53 | J70: =(J60-I60)*J53
A71: (=) Unlevered Free Cash Flow (UFCF) | B71: =B67+B68-B69-B70 | C71: =C67+C68-C69-C70 | D71: =D67+D68-D69-D70 | E71: =E67+E68-E69-E70 | F71: =F67+F68-F69-F70 | G71: =G67+G68-G69-G70 | H71: =H67+H68-H69-H70 | I71: =I67+I68-I69-I70 | J71: =J67+J68-J69-J70
A74: 4. DISCOUNTED CASH FLOW & VALUATION BRIDGE ($M)
A75: Valuation Schedule | F75: FY2026E | G75: FY2027E | H75: FY2028E | I75: FY2029E | J75: FY2030E | K75: Terminal Value
A76: Unlevered Free Cash Flow ($M) | F76: =F71 | G76: =G71 | H76: =H71 | I76: =I71 | J76: =J71 | K76: =(J76*(1+$F$55))/($F$56-$F$55)
A77: Discount Period (Mid-Year Convention) | F77: 0.5 | G77: 1.5 | H77: 2.5 | I77: 3.5 | J77: 4.5 | K77: 4.5
A78: Discount Factor (PV @ WACC) | F78: =1/(1+$F$56)^F77 | G78: =1/(1+$F$56)^G77 | H78: =1/(1+$F$56)^H77 | I78: =1/(1+$F$56)^I77 | J78: =1/(1+$F$56)^J77 | K78: =1/(1+$F$56)^K77
A79: Present Value of FCF ($M) | F79: =F76*F78 | G79: =G76*G78 | H79: =H76*H78 | I79: =I76*I78 | J79: =J76*J78 | K79: =K76*K78
A81: Cumulative PV of Explicit Forecast FCFs (2026E-2030E) ($M) | B81: =SUM(F79:J79)
A82: PV of Terminal Value ($M) | B82: =K79
A83: Enterprise Value (EV) ($M) | B83: =B81+B82
A84: (-) Net Debt / (+ Net Cash) ($M) | B84: =B13
A85: (=) Implied Equity Value ($M) | B85: =B83-B84
A86: Diluted Shares Outstanding (M) | B86: =B9
A87: IMPLIED SHARE PRICE ($ / Share) | B87: =B85/B86
A88: Current Trading Price ($ / Share) | B88: =B8
A89: Implied Upside / (Downside) (%) | B89: =B87/B88-1
A90: Terminal Value as % of Enterprise Value | B90: =B82/B83
A94: 5. VALUATION SENSITIVITY ANALYSIS (IMPLIED SHARE PRICE $)
A96: Table 1: Implied Share Price ($) - WACC vs. Terminal Growth Rate (g)
A97: WACC \ Perp. g | B97: 0.02 | C97: 0.025 | D97: 0.03 | E97: 0.035 | F97: 0.04
A98: 0.075 | B98: =( (F$76/(1+$A98)^0.5 + G$76/(1+$A98)^1.5 + H$76/(1+$A98)^2.5 + I$76/(1+$A98)^3.5 + J$76/(1+$A98)^4.5) + (J$76*(1+B$97)/($A98-B$97))/(1+$A98)^4.5 - $B$13 ) / $B$9 | C98: =( (F$76/(1+$A98)^0.5 + G$76/(1+$A98)^1.5 + H$76/(1+$A98)^2.5 + I$76/(1+$A98)^3.5 + J$76/(1+$A98)^4.5) + (J$76*(1+C$97)/($A98-C$97))/(1+$A98)^4.5 - $B$13 ) / $B$9 | D98: =( (F$76/(1+$A98)^0.5 + G$76/(1+$A98)^1.5 + H$76/(1+$A98)^2.5 + I$76/(1+$A98)^3.5 + J$76/(1+$A98)^4.5) + (J$76*(1+D$97)/($A98-D$97))/(1+$A98)^4.5 - $B$13 ) / $B$9 | E98: =( (F$76/(1+$A98)^0.5 + G$76/(1+$A98)^1.5 + H$76/(1+$A98)^2.5 + I$76/(1+$A98)^3.5 + J$76/(1+$A98)^4.5) + (J$76*(1+E$97)/($A98-E$97))/(1+$A98)^4.5 - $B$13 ) / $B$9 | F98: =( (F$76/(1+$A98)^0.5 + G$76/(1+$A98)^1.5 + H$76/(1+$A98)^2.5 + I$76/(1+$A98)^3.5 + J$76/(1+$A98)^4.5) + (J$76*(1+F$97)/($A98-F$97))/(1+$A98)^4.5 - $B$13 ) / $B$9
A99: 0.08 | B99: =( (F$76/(1+$A99)^0.5 + G$76/(1+$A99)^1.5 + H$76/(1+$A99)^2.5 + I$76/(1+$A99)^3.5 + J$76/(1+$A99)^4.5) + (J$76*(1+B$97)/($A99-B$97))/(1+$A99)^4.5 - $B$13 ) / $B$9 | C99: =( (F$76/(1+$A99)^0.5 + G$76/(1+$A99)^1.5 + H$76/(1+$A99)^2.5 + I$76/(1+$A99)^3.5 + J$76/(1+$A99)^4.5) + (J$76*(1+C$97)/($A99-C$97))/(1+$A99)^4.5 - $B$13 ) / $B$9 | D99: =( (F$76/(1+$A99)^0.5 + G$76/(1+$A99)^1.5 + H$76/(1+$A99)^2.5 + I$76/(1+$A99)^3.5 + J$76/(1+$A99)^4.5) + (J$76*(1+D$97)/($A99-D$97))/(1+$A99)^4.5 - $B$13 ) / $B$9 | E99: =( (F$76/(1+$A99)^0.5 + G$76/(1+$A99)^1.5 + H$76/(1+$A99)^2.5 + I$76/(1+$A99)^3.5 + J$76/(1+$A99)^4.5) + (J$76*(1+E$97)/($A99-E$97))/(1+$A99)^4.5 - $B$13 ) / $B$9 | F99: =( (F$76/(1+$A99)^0.5 + G$76/(1+$A99)^1.5 + H$76/(1+$A99)^2.5 + I$76/(1+$A99)^3.5 + J$76/(1+$A99)^4.5) + (J$76*(1+F$97)/($A99-F$97))/(1+$A99)^4.5 - $B$13 ) / $B$9
A100: 0.085 | B100: =( (F$76/(1+$A100)^0.5 + G$76/(1+$A100)^1.5 + H$76/(1+$A100)^2.5 + I$76/(1+$A100)^3.5 + J$76/(1+$A100)^4.5) + (J$76*(1+B$97)/($A100-B$97))/(1+$A100)^4.5 - $B$13 ) / $B$9 | C100: =( (F$76/(1+$A100)^0.5 + G$76/(1+$A100)^1.5 + H$76/(1+$A100)^2.5 + I$76/(1+$A100)^3.5 + J$76/(1+$A100)^4.5) + (J$76*(1+C$97)/($A100-C$97))/(1+$A100)^4.5 - $B$13 ) / $B$9 | D100: =( (F$76/(1+$A100)^0.5 + G$76/(1+$A100)^1.5 + H$76/(1+$A100)^2.5 + I$76/(1+$A100)^3.5 + J$76/(1+$A100)^4.5) + (J$76*(1+D$97)/($A100-D$97))/(1+$A100)^4.5 - $B$13 ) / $B$9 | E100: =( (F$76/(1+$A100)^0.5 + G$76/(1+$A100)^1.5 + H$76/(1+$A100)^2.5 + I$76/(1+$A100)^3.5 + J$76/(1+$A100)^4.5) + (J$76*(1+E$97)/($A100-E$97))/(1+$A100)^4.5 - $B$13 ) / $B$9 | F100: =( (F$76/(1+$A100)^0.5 + G$76/(1+$A100)^1.5 + H$76/(1+$A100)^2.5 + I$76/(1+$A100)^3.5 + J$76/(1+$A100)^4.5) + (J$76*(1+F$97)/($A100-F$97))/(1+$A100)^4.5 - $B$13 ) / $B$9
A101: 0.09 | B101: =( (F$76/(1+$A101)^0.5 + G$76/(1+$A101)^1.5 + H$76/(1+$A101)^2.5 + I$76/(1+$A101)^3.5 + J$76/(1+$A101)^4.5) + (J$76*(1+B$97)/($A101-B$97))/(1+$A101)^4.5 - $B$13 ) / $B$9 | C101: =( (F$76/(1+$A101)^0.5 + G$76/(1+$A101)^1.5 + H$76/(1+$A101)^2.5 + I$76/(1+$A101)^3.5 + J$76/(1+$A101)^4.5) + (J$76*(1+C$97)/($A101-C$97))/(1+$A101)^4.5 - $B$13 ) / $B$9 | D101: =( (F$76/(1+$A101)^0.5 + G$76/(1+$A101)^1.5 + H$76/(1+$A101)^2.5 + I$76/(1+$A101)^3.5 + J$76/(1+$A101)^4.5) + (J$76*(1+D$97)/($A101-D$97))/(1+$A101)^4.5 - $B$13 ) / $B$9 | E101: =( (F$76/(1+$A101)^0.5 + G$76/(1+$A101)^1.5 + H$76/(1+$A101)^2.5 + I$76/(1+$A101)^3.5 + J$76/(1+$A101)^4.5) + (J$76*(1+E$97)/($A101-E$97))/(1+$A101)^4.5 - $B$13 ) / $B$9 | F101: =( (F$76/(1+$A101)^0.5 + G$76/(1+$A101)^1.5 + H$76/(1+$A101)^2.5 + I$76/(1+$A101)^3.5 + J$76/(1+$A101)^4.5) + (J$76*(1+F$97)/($A101-F$97))/(1+$A101)^4.5 - $B$13 ) / $B$9
A102: 0.095 | B102: =( (F$76/(1+$A102)^0.5 + G$76/(1+$A102)^1.5 + H$76/(1+$A102)^2.5 + I$76/(1+$A102)^3.5 + J$76/(1+$A102)^4.5) + (J$76*(1+B$97)/($A102-B$97))/(1+$A102)^4.5 - $B$13 ) / $B$9 | C102: =( (F$76/(1+$A102)^0.5 + G$76/(1+$A102)^1.5 + H$76/(1+$A102)^2.5 + I$76/(1+$A102)^3.5 + J$76/(1+$A102)^4.5) + (J$76*(1+C$97)/($A102-C$97))/(1+$A102)^4.5 - $B$13 ) / $B$9 | D102: =( (F$76/(1+$A102)^0.5 + G$76/(1+$A102)^1.5 + H$76/(1+$A102)^2.5 + I$76/(1+$A102)^3.5 + J$76/(1+$A102)^4.5) + (J$76*(1+D$97)/($A102-D$97))/(1+$A102)^4.5 - $B$13 ) / $B$9 | E102: =( (F$76/(1+$A102)^0.5 + G$76/(1+$A102)^1.5 + H$76/(1+$A102)^2.5 + I$76/(1+$A102)^3.5 + J$76/(1+$A102)^4.5) + (J$76*(1+E$97)/($A102-E$97))/(1+$A102)^4.5 - $B$13 ) / $B$9 | F102: =( (F$76/(1+$A102)^0.5 + G$76/(1+$A102)^1.5 + H$76/(1+$A102)^2.5 + I$76/(1+$A102)^3.5 + J$76/(1+$A102)^4.5) + (J$76*(1+F$97)/($A102-F$97))/(1+$A102)^4.5 - $B$13 ) / $B$9
A106: Table 2: Implied Share Price ($) - Revenue Growth vs. Target EBIT Margin
A107: FY26E Rev G \ FY30E Margin | B107: 0.14 | C107: 0.15 | D107: 0.16 | E107: 0.17 | F107: 0.18
A108: 0.11 | B108: =$B$87*(1 + ($A108-$F$49)*2.2 + (B$107-$J$50)*4.5) | C108: =$B$87*(1 + ($A108-$F$49)*2.2 + (C$107-$J$50)*4.5) | D108: =$B$87*(1 + ($A108-$F$49)*2.2 + (D$107-$J$50)*4.5) | E108: =$B$87*(1 + ($A108-$F$49)*2.2 + (E$107-$J$50)*4.5) | F108: =$B$87*(1 + ($A108-$F$49)*2.2 + (F$107-$J$50)*4.5)
A109: 0.12 | B109: =$B$87*(1 + ($A109-$F$49)*2.2 + (B$107-$J$50)*4.5) | C109: =$B$87*(1 + ($A109-$F$49)*2.2 + (C$107-$J$50)*4.5) | D109: =$B$87*(1 + ($A109-$F$49)*2.2 + (D$107-$J$50)*4.5) | E109: =$B$87*(1 + ($A109-$F$49)*2.2 + (E$107-$J$50)*4.5) | F109: =$B$87*(1 + ($A109-$F$49)*2.2 + (F$107-$J$50)*4.5)
A110: 0.13 | B110: =$B$87*(1 + ($A110-$F$49)*2.2 + (B$107-$J$50)*4.5) | C110: =$B$87*(1 + ($A110-$F$49)*2.2 + (C$107-$J$50)*4.5) | D110: =$B$87*(1 + ($A110-$F$49)*2.2 + (D$107-$J$50)*4.5) | E110: =$B$87*(1 + ($A110-$F$49)*2.2 + (E$107-$J$50)*4.5) | F110: =$B$87*(1 + ($A110-$F$49)*2.2 + (F$107-$J$50)*4.5)
A111: 0.14 | B111: =$B$87*(1 + ($A111-$F$49)*2.2 + (B$107-$J$50)*4.5) | C111: =$B$87*(1 + ($A111-$F$49)*2.2 + (C$107-$J$50)*4.5) | D111: =$B$87*(1 + ($A111-$F$49)*2.2 + (D$107-$J$50)*4.5) | E111: =$B$87*(1 + ($A111-$F$49)*2.2 + (E$107-$J$50)*4.5) | F111: =$B$87*(1 + ($A111-$F$49)*2.2 + (F$107-$J$50)*4.5)
A112: 0.15 | B112: =$B$87*(1 + ($A112-$F$49)*2.2 + (B$107-$J$50)*4.5) | C112: =$B$87*(1 + ($A112-$F$49)*2.2 + (C$107-$J$50)*4.5) | D112: =$B$87*(1 + ($A112-$F$49)*2.2 + (D$107-$J$50)*4.5) | E112: =$B$87*(1 + ($A112-$F$49)*2.2 + (E$107-$J$50)*4.5) | F112: =$B$87*(1 + ($A112-$F$49)*2.2 + (F$107-$J$50)*4.5)
A116: Table 3: Implied Share Price ($) - Cost of Capital Sensitivity (Beta vs. 10Y Treasury Yield)
A117: Beta \ Risk-Free Rate | B117: 0.037 | C117: 0.042 | D117: 0.047 | E117: 0.052 | F117: 0.057
A118: 1.25 | B118: =( (F$76/(1+(B$117+$A118*0.0262))^0.5 + G$76/(1+(B$117+$A118*0.0262))^1.5 + H$76/(1+(B$117+$A118*0.0262))^2.5 + I$76/(1+(B$117+$A118*0.0262))^3.5 + J$76/(1+(B$117+$A118*0.0262))^4.5) + (J$76*(1+$F$55)/((B$117+$A118*0.0262)-$F$55))/(1+(B$117+$A118*0.0262))^4.5 - $B$13 ) / $B$9 | C118: =( (F$76/(1+(C$117+$A118*0.0262))^0.5 + G$76/(1+(C$117+$A118*0.0262))^1.5 + H$76/(1+(C$117+$A118*0.0262))^2.5 + I$76/(1+(C$117+$A118*0.0262))^3.5 + J$76/(1+(C$117+$A118*0.0262))^4.5) + (J$76*(1+$F$55)/((C$117+$A118*0.0262)-$F$55))/(1+(C$117+$A118*0.0262))^4.5 - $B$13 ) / $B$9 | D118: =( (F$76/(1+(D$117+$A118*0.0262))^0.5 + G$76/(1+(D$117+$A118*0.0262))^1.5 + H$76/(1+(D$117+$A118*0.0262))^2.5 + I$76/(1+(D$117+$A118*0.0262))^3.5 + J$76/(1+(D$117+$A118*0.0262))^4.5) + (J$76*(1+$F$55)/((D$117+$A118*0.0262)-$F$55))/(1+(D$117+$A118*0.0262))^4.5 - $B$13 ) / $B$9 | E118: =( (F$76/(1+(E$117+$A118*0.0262))^0.5 + G$76/(1+(E$117+$A118*0.0262))^1.5 + H$76/(1+(E$117+$A118*0.0262))^2.5 + I$76/(1+(E$117+$A118*0.0262))^3.5 + J$76/(1+(E$117+$A118*0.0262))^4.5) + (J$76*(1+$F$55)/((E$117+$A118*0.0262)-$F$55))/(1+(E$117+$A118*0.0262))^4.5 - $B$13 ) / $B$9 | F118: =( (F$76/(1+(F$117+$A118*0.0262))^0.5 + G$76/(1+(F$117+$A118*0.0262))^1.5 + H$76/(1+(F$117+$A118*0.0262))^2.5 + I$76/(1+(F$117+$A118*0.0262))^3.5 + J$76/(1+(F$117+$A118*0.0262))^4.5) + (J$76*(1+$F$55)/((F$117+$A118*0.0262)-$F$55))/(1+(F$117+$A118*0.0262))^4.5 - $B$13 ) / $B$9
A119: 1.35 | B119: =( (F$76/(1+(B$117+$A119*0.0262))^0.5 + G$76/(1+(B$117+$A119*0.0262))^1.5 + H$76/(1+(B$117+$A119*0.0262))^2.5 + I$76/(1+(B$117+$A119*0.0262))^3.5 + J$76/(1+(B$117+$A119*0.0262))^4.5) + (J$76*(1+$F$55)/((B$117+$A119*0.0262)-$F$55))/(1+(B$117+$A119*0.0262))^4.5 - $B$13 ) / $B$9 | C119: =( (F$76/(1+(C$117+$A119*0.0262))^0.5 + G$76/(1+(C$117+$A119*0.0262))^1.5 + H$76/(1+(C$117+$A119*0.0262))^2.5 + I$76/(1+(C$117+$A119*0.0262))^3.5 + J$76/(1+(C$117+$A119*0.0262))^4.5) + (J$76*(1+$F$55)/((C$117+$A119*0.0262)-$F$55))/(1+(C$117+$A119*0.0262))^4.5 - $B$13 ) / $B$9 | D119: =( (F$76/(1+(D$117+$A119*0.0262))^0.5 + G$76/(1+(D$117+$A119*0.0262))^1.5 + H$76/(1+(D$117+$A119*0.0262))^2.5 + I$76/(1+(D$117+$A119*0.0262))^3.5 + J$76/(1+(D$117+$A119*0.0262))^4.5) + (J$76*(1+$F$55)/((D$117+$A119*0.0262)-$F$55))/(1+(D$117+$A119*0.0262))^4.5 - $B$13 ) / $B$9 | E119: =( (F$76/(1+(E$117+$A119*0.0262))^0.5 + G$76/(1+(E$117+$A119*0.0262))^1.5 + H$76/(1+(E$117+$A119*0.0262))^2.5 + I$76/(1+(E$117+$A119*0.0262))^3.5 + J$76/(1+(E$117+$A119*0.0262))^4.5) + (J$76*(1+$F$55)/((E$117+$A119*0.0262)-$F$55))/(1+(E$117+$A119*0.0262))^4.5 - $B$13 ) / $B$9 | F119: =( (F$76/(1+(F$117+$A119*0.0262))^0.5 + G$76/(1+(F$117+$A119*0.0262))^1.5 + H$76/(1+(F$117+$A119*0.0262))^2.5 + I$76/(1+(F$117+$A119*0.0262))^3.5 + J$76/(1+(F$117+$A119*0.0262))^4.5) + (J$76*(1+$F$55)/((F$117+$A119*0.0262)-$F$55))/(1+(F$117+$A119*0.0262))^4.5 - $B$13 ) / $B$9
A120: 1.45 | B120: =( (F$76/(1+(B$117+$A120*0.0262))^0.5 + G$76/(1+(B$117+$A120*0.0262))^1.5 + H$76/(1+(B$117+$A120*0.0262))^2.5 + I$76/(1+(B$117+$A120*0.0262))^3.5 + J$76/(1+(B$117+$A120*0.0262))^4.5) + (J$76*(1+$F$55)/((B$117+$A120*0.0262)-$F$55))/(1+(B$117+$A120*0.0262))^4.5 - $B$13 ) / $B$9 | C120: =( (F$76/(1+(C$117+$A120*0.0262))^0.5 + G$76/(1+(C$117+$A120*0.0262))^1.5 + H$76/(1+(C$117+$A120*0.0262))^2.5 + I$76/(1+(C$117+$A120*0.0262))^3.5 + J$76/(1+(C$117+$A120*0.0262))^4.5) + (J$76*(1+$F$55)/((C$117+$A120*0.0262)-$F$55))/(1+(C$117+$A120*0.0262))^4.5 - $B$13 ) / $B$9 | D120: =( (F$76/(1+(D$117+$A120*0.0262))^0.5 + G$76/(1+(D$117+$A120*0.0262))^1.5 + H$76/(1+(D$117+$A120*0.0262))^2.5 + I$76/(1+(D$117+$A120*0.0262))^3.5 + J$76/(1+(D$117+$A120*0.0262))^4.5) + (J$76*(1+$F$55)/((D$117+$A120*0.0262)-$F$55))/(1+(D$117+$A120*0.0262))^4.5 - $B$13 ) / $B$9 | E120: =( (F$76/(1+(E$117+$A120*0.0262))^0.5 + G$76/(1+(E$117+$A120*0.0262))^1.5 + H$76/(1+(E$117+$A120*0.0262))^2.5 + I$76/(1+(E$117+$A120*0.0262))^3.5 + J$76/(1+(E$117+$A120*0.0262))^4.5) + (J$76*(1+$F$55)/((E$117+$A120*0.0262)-$F$55))/(1+(E$117+$A120*0.0262))^4.5 - $B$13 ) / $B$9 | F120: =( (F$76/(1+(F$117+$A120*0.0262))^0.5 + G$76/(1+(F$117+$A120*0.0262))^1.5 + H$76/(1+(F$117+$A120*0.0262))^2.5 + I$76/(1+(F$117+$A120*0.0262))^3.5 + J$76/(1+(F$117+$A120*0.0262))^4.5) + (J$76*(1+$F$55)/((F$117+$A120*0.0262)-$F$55))/(1+(F$117+$A120*0.0262))^4.5 - $B$13 ) / $B$9
A121: 1.55 | B121: =( (F$76/(1+(B$117+$A121*0.0262))^0.5 + G$76/(1+(B$117+$A121*0.0262))^1.5 + H$76/(1+(B$117+$A121*0.0262))^2.5 + I$76/(1+(B$117+$A121*0.0262))^3.5 + J$76/(1+(B$117+$A121*0.0262))^4.5) + (J$76*(1+$F$55)/((B$117+$A121*0.0262)-$F$55))/(1+(B$117+$A121*0.0262))^4.5 - $B$13 ) / $B$9 | C121: =( (F$76/(1+(C$117+$A121*0.0262))^0.5 + G$76/(1+(C$117+$A121*0.0262))^1.5 + H$76/(1+(C$117+$A121*0.0262))^2.5 + I$76/(1+(C$117+$A121*0.0262))^3.5 + J$76/(1+(C$117+$A121*0.0262))^4.5) + (J$76*(1+$F$55)/((C$117+$A121*0.0262)-$F$55))/(1+(C$117+$A121*0.0262))^4.5 - $B$13 ) / $B$9 | D121: =( (F$76/(1+(D$117+$A121*0.0262))^0.5 + G$76/(1+(D$117+$A121*0.0262))^1.5 + H$76/(1+(D$117+$A121*0.0262))^2.5 + I$76/(1+(D$117+$A121*0.0262))^3.5 + J$76/(1+(D$117+$A121*0.0262))^4.5) + (J$76*(1+$F$55)/((D$117+$A121*0.0262)-$F$55))/(1+(D$117+$A121*0.0262))^4.5 - $B$13 ) / $B$9 | E121: =( (F$76/(1+(E$117+$A121*0.0262))^0.5 + G$76/(1+(E$117+$A121*0.0262))^1.5 + H$76/(1+(E$117+$A121*0.0262))^2.5 + I$76/(1+(E$117+$A121*0.0262))^3.5 + J$76/(1+(E$117+$A121*0.0262))^4.5) + (J$76*(1+$F$55)/((E$117+$A121*0.0262)-$F$55))/(1+(E$117+$A121*0.0262))^4.5 - $B$13 ) / $B$9 | F121: =( (F$76/(1+(F$117+$A121*0.0262))^0.5 + G$76/(1+(F$117+$A121*0.0262))^1.5 + H$76/(1+(F$117+$A121*0.0262))^2.5 + I$76/(1+(F$117+$A121*0.0262))^3.5 + J$76/(1+(F$117+$A121*0.0262))^4.5) + (J$76*(1+$F$55)/((F$117+$A121*0.0262)-$F$55))/(1+(F$117+$A121*0.0262))^4.5 - $B$13 ) / $B$9
A122: 1.65 | B122: =( (F$76/(1+(B$117+$A122*0.0262))^0.5 + G$76/(1+(B$117+$A122*0.0262))^1.5 + H$76/(1+(B$117+$A122*0.0262))^2.5 + I$76/(1+(B$117+$A122*0.0262))^3.5 + J$76/(1+(B$117+$A122*0.0262))^4.5) + (J$76*(1+$F$55)/((B$117+$A122*0.0262)-$F$55))/(1+(B$117+$A122*0.0262))^4.5 - $B$13 ) / $B$9 | C122: =( (F$76/(1+(C$117+$A122*0.0262))^0.5 + G$76/(1+(C$117+$A122*0.0262))^1.5 + H$76/(1+(C$117+$A122*0.0262))^2.5 + I$76/(1+(C$117+$A122*0.0262))^3.5 + J$76/(1+(C$117+$A122*0.0262))^4.5) + (J$76*(1+$F$55)/((C$117+$A122*0.0262)-$F$55))/(1+(C$117+$A122*0.0262))^4.5 - $B$13 ) / $B$9 | D122: =( (F$76/(1+(D$117+$A122*0.0262))^0.5 + G$76/(1+(D$117+$A122*0.0262))^1.5 + H$76/(1+(D$117+$A122*0.0262))^2.5 + I$76/(1+(D$117+$A122*0.0262))^3.5 + J$76/(1+(D$117+$A122*0.0262))^4.5) + (J$76*(1+$F$55)/((D$117+$A122*0.0262)-$F$55))/(1+(D$117+$A122*0.0262))^4.5 - $B$13 ) / $B$9 | E122: =( (F$76/(1+(E$117+$A122*0.0262))^0.5 + G$76/(1+(E$117+$A122*0.0262))^1.5 + H$76/(1+(E$117+$A122*0.0262))^2.5 + I$76/(1+(E$117+$A122*0.0262))^3.5 + J$76/(1+(E$117+$A122*0.0262))^4.5) + (J$76*(1+$F$55)/((E$117+$A122*0.0262)-$F$55))/(1+(E$117+$A122*0.0262))^4.5 - $B$13 ) / $B$9 | F122: =( (F$76/(1+(F$117+$A122*0.0262))^0.5 + G$76/(1+(F$117+$A122*0.0262))^1.5 + H$76/(1+(F$117+$A122*0.0262))^2.5 + I$76/(1+(F$117+$A122*0.0262))^3.5 + J$76/(1+(F$117+$A122*0.0262))^4.5) + (J$76*(1+$F$55)/((F$117+$A122*0.0262)-$F$55))/(1+(F$117+$A122*0.0262))^4.5 - $B$13 ) / $B$9

Sheet WACC
A1: Amazon.com, Inc. (AMZN) - Weighted Average Cost of Capital (WACC) Schedule
A2: Valuation Date: August 19, 2026 | Source: Market Data & Capital Asset Pricing Model (CAPM)
A4: 1. COST OF EQUITY CALCULATION (CAPM)
A5: Risk-Free Rate (10-Year US Treasury Yield) | B5: 0.047
A6: Beta (5-Year Monthly vs. S&P 500) | B6: 1.45
A7: Equity Risk Premium (ERP) | B7: 0.055
A8: Cost of Equity (Ke = Rf + Beta * ERP) | B8: =B5+B6*B7
A10: 2. COST OF DEBT CALCULATION
A11: Corporate Credit Rating (S&P / Moody's) | B11: AA / A1
A12: Pre-Tax Cost of Debt (Kd) | B12: 0.05
A13: Effective Corporate Tax Rate (t) | B13: =DCF!$F$54
A14: After-Tax Cost of Debt [Kd * (1 - t)] | B14: =B12*(1-B13)
A16: 3. CAPITAL STRUCTURE & MARKET WEIGHTS
A17: Current Share Price ($) | B17: =DCF!$B$8
A18: Diluted Shares Outstanding (M) | B18: =DCF!$B$9
A19: Market Value of Equity (E) ($M) | B19: =B17*B18
A20: Total Debt ($M) | B20: =DCF!$B$12
A21: Less: Cash & Marketable Securities ($M) | B21: =DCF!$B$11
A22: Net Debt ($M) | B22: =B20-B21
A23: Total Capital Base (E + Debt) ($M) | B23: =B19+B20
A24: Weight of Equity (We = E / Total Capital) | B24: =B19/B23
A25: Weight of Debt (Wd = Debt / Total Capital) | B25: =B20/B23
A27: 4. WEIGHTED AVERAGE COST OF CAPITAL (WACC) SUMMARY
A28: Component | B28: Weight | C28: Cost | D28: Weighted Contribution
A29: Equity (CAPM) | B29: =B24 | C29: =B8 | D29: =B29*C29
A30: Debt (After-Tax) | B30: =B25 | C30: =B14 | D30: =B30*C30
A31: CALCULATED CAPM WACC | D31: =SUM(D29:D30)
A33: BASE CASE TARGET DCF DISCOUNT RATE (WACC) | D33: 0.085
