Workbook

Sheet DCF Valuation
A1: Alphabet Inc. (NASDAQ: GOOGL / GOOG)
A2: Institutional DCF Valuation Model | Report Date: August 19, 2026 | Financial Source: SEC Form 10-K, 10-Q & Consensus Estimates
A4: Active Scenario Selector: | B4: 2 | C4: =IF(B4=1,"[1] BEAR CASE (Antitrust Headwinds / Search Disruption / AI ROI Drag)",IF(B4=2,"[2] BASE CASE (Cloud Scaling / Gemini AI Monetization / Sustained Search Moat)","[3] BULL CASE (Waymo Commercialization / Cloud Hypergrowth / Agentic AI Leadership)"))
A6: I. MARKET DATA & CAPITAL STRUCTURE INPUTS
A7: Current Stock Price ($) | B7: 341.37
A8: Diluted Shares Outstanding (M) | B8: 12200
A9: Implied Equity Market Capitalization ($M) | B9: =B7*B8
A10: Cash, Cash Eq. & Marketable Securities ($M) | B10: 242500
A11: Total Debt (Current + Noncurrent Debt) ($M) | B11: 98200
A12: Net Debt ($M) [Net Cash if negative] | B12: =B11-B10
A13: Implied Enterprise Value ($M) | B13: =B9+B12
A14: Effective Corporate Tax Rate (%) | B14: 0.175
A15: Market Equity Risk Premium (ERP) (%) | B15: 0.055
A16: Long-Term Risk-Free Rate (%) | B16: 0.0469
A17: Equity Beta (5-Year Monthly vs S&P 500) | B17: 1.24
A19: II. SCENARIO DRIVER ASSUMPTIONS (BEAR / BASE / BULL)
A20: SCENARIO 1: BEAR CASE ASSUMPTIONS
A21: Assumption Driver | B21: FY26E | C21: FY27E | D21: FY28E | E21: FY29E | F21: FY30E | G21: Terminal | H21: Parameter Description / Methodology
A22: Revenue Growth Rate (%) | B22: 0.11 | C22: 0.09 | D22: 0.075 | E22: 0.06 | F22: 0.05 | G22: 0.025 | H22: Search share loss, antitrust remedies, slower cloud migration
A23: Gross Margin (%) | B23: 0.56 | C23: 0.555 | D23: 0.55 | E23: 0.545 | F23: 0.54 | G23: 0.54 | H23: Higher TAC and massive data center energy / compute depreciation
A24: S&M Expense (% of Revenue) | B24: 0.08 | C24: 0.08 | D24: 0.078 | E24: 0.078 | F24: 0.078 | G24: 0.078 | H24: Aggressive defensive advertising to protect search volume
A25: R&D Expense (% of Revenue) | B25: 0.145 | C25: 0.145 | D25: 0.14 | E25: 0.14 | F25: 0.14 | G25: 0.14 | H25: Sustained AI talent wars and foundational model retraining
A26: G&A Expense (% of Revenue) | B26: 0.045 | C26: 0.045 | D26: 0.042 | E26: 0.042 | F26: 0.042 | G26: 0.042 | H26: Elevated legal defense costs and regulatory compliance
A27: CapEx (% of Revenue) | B27: 0.39 | C27: 0.3 | D27: 0.22 | E27: 0.18 | F27: 0.14 | G27: 0.1 | H27: Aggressive AI cluster spending with prolonged payback horizon
A28: Terminal Perpetuity Growth (g) / WACC | B28: - | C28: - | D28: - | E28: - | F28: - | G28: 0.025 | H28: Conservative long-term inflation-matching growth (2.50%) | Bear WACC: 12.50%
A29: SCENARIO 2: BASE CASE ASSUMPTIONS (CONSENSUS & STRATEGIC AI BUILD)
A30: Assumption Driver | B30: FY26E | C30: FY27E | D30: FY28E | E30: FY29E | F30: FY30E | G30: Terminal | H30: Parameter Description / Methodology
A31: Revenue Growth Rate (%) | B31: 0.16 | C31: 0.14 | D31: 0.12 | E31: 0.105 | F31: 0.09 | G31: 0.03 | H31: Cloud scaling (+40-50%), YouTube monetization, Gemini Search integration
A32: Gross Margin (%) | B32: 0.58 | C32: 0.582 | D32: 0.585 | E32: 0.588 | F32: 0.59 | G32: 0.59 | H32: Cloud margin expansion and custom TPU silicon cost efficiencies
A33: S&M Expense (% of Revenue) | B33: 0.075 | C33: 0.072 | D33: 0.07 | E33: 0.068 | F33: 0.065 | G33: 0.065 | H33: Operating leverage from digital enterprise distribution
A34: R&D Expense (% of Revenue) | B34: 0.138 | C34: 0.135 | D34: 0.132 | E34: 0.128 | F34: 0.125 | G34: 0.125 | H34: Disciplined R&D scaling with AI-assisted software productivity
A35: G&A Expense (% of Revenue) | B35: 0.042 | C35: 0.04 | D35: 0.038 | E35: 0.036 | F35: 0.035 | G35: 0.035 | H35: Corporate efficiency and automation of back-office operations
A36: CapEx (% of Revenue) | B36: 0.38 | C36: 0.26 | D36: 0.18 | E36: 0.14 | F36: 0.11 | G36: 0.08 | H36: 2026 peak AI CapEx ($178B), normalizing to sustainable steady-state
A37: Terminal Perpetuity Growth (g) / WACC | B37: - | C37: - | D37: - | E37: - | F37: - | G37: 0.03 | H37: GDP+ Tech leader growth (3.00%) | WACC dynamically linked to 'WACC Build'
A38: SCENARIO 3: BULL CASE ASSUMPTIONS (AGENTIC AI & CLOUD ACCELERATION)
A39: Assumption Driver | B39: FY26E | C39: FY27E | D39: FY28E | E39: FY29E | F39: FY30E | G39: Terminal | H39: Parameter Description / Methodology
A40: Revenue Growth Rate (%) | B40: 0.2 | C40: 0.175 | D40: 0.15 | E40: 0.13 | F40: 0.11 | G40: 0.035 | H40: Waymo commercial scaling, Google Workspace AI enterprise ARPU explosion
A41: Gross Margin (%) | B41: 0.59 | C41: 0.595 | D41: 0.6 | E41: 0.605 | F41: 0.61 | G41: 0.61 | H41: High-margin software subscription revenues and TPU 6th gen efficiencies
A42: S&M Expense (% of Revenue) | B42: 0.07 | C42: 0.065 | D42: 0.062 | E42: 0.06 | F42: 0.058 | G42: 0.058 | H42: Self-reinforcing viral adoption of Gemini personal AI assistants
A43: R&D Expense (% of Revenue) | B43: 0.13 | C43: 0.125 | D43: 0.12 | E43: 0.115 | F43: 0.11 | G43: 0.11 | H43: Massive operating leverage across global developer ecosystem
A44: G&A Expense (% of Revenue) | B44: 0.038 | C44: 0.035 | D44: 0.032 | E44: 0.03 | F44: 0.03 | G44: 0.03 | H44: Maximized operational leverage and AI workflow automation
A45: CapEx (% of Revenue) | B45: 0.37 | C45: 0.24 | D45: 0.16 | E45: 0.12 | F45: 0.09 | G45: 0.07 | H45: Hyper-efficient AI compute architecture and external cloud monetization
A46: Terminal Perpetuity Growth (g) / WACC | B46: - | C46: - | D46: - | E46: - | F46: - | G46: 0.035 | H46: Global GDP Outperformance (3.50%) | Bull WACC: 11.00%
A47: ACTIVE CONSOLIDATED SCENARIO DRIVERS (DYNAMICALLY PULLED VIA SELECTOR)
A48: Assumption Driver | B48: FY26E | C48: FY27E | D48: FY28E | E48: FY29E | F48: FY30E | G48: Terminal | H48: Parameter Description / Methodology
A49: Selected Revenue Growth (%) | B49: =IF($B$4=1,B22,IF($B$4=2,B31,B40)) | C49: =IF($B$4=1,C22,IF($B$4=2,C31,C40)) | D49: =IF($B$4=1,D22,IF($B$4=2,D31,D40)) | E49: =IF($B$4=1,E22,IF($B$4=2,E31,E40)) | F49: =IF($B$4=1,F22,IF($B$4=2,F31,F40)) | G49: =IF($B$4=1,G22,IF($B$4=2,G31,G40)) | H49: Dynamic revenue growth rate linked to selected case
A50: Selected Gross Margin (%) | B50: =IF($B$4=1,B23,IF($B$4=2,B32,B41)) | C50: =IF($B$4=1,C23,IF($B$4=2,C32,C41)) | D50: =IF($B$4=1,D23,IF($B$4=2,D32,D41)) | E50: =IF($B$4=1,E23,IF($B$4=2,E32,E41)) | F50: =IF($B$4=1,F23,IF($B$4=2,F32,F41)) | G50: =IF($B$4=1,G23,IF($B$4=2,G32,G41)) | H50: Dynamic gross profit margin linked to selected case
A51: Selected S&M Expense (%) | B51: =IF($B$4=1,B24,IF($B$4=2,B33,B42)) | C51: =IF($B$4=1,C24,IF($B$4=2,C33,C42)) | D51: =IF($B$4=1,D24,IF($B$4=2,D33,D42)) | E51: =IF($B$4=1,E24,IF($B$4=2,E33,E42)) | F51: =IF($B$4=1,F24,IF($B$4=2,F33,F42)) | G51: =IF($B$4=1,G24,IF($B$4=2,G33,G42)) | H51: Dynamic S&M as % of revenue
A52: Selected R&D Expense (%) | B52: =IF($B$4=1,B25,IF($B$4=2,B34,B43)) | C52: =IF($B$4=1,C25,IF($B$4=2,C34,C43)) | D52: =IF($B$4=1,D25,IF($B$4=2,D34,D43)) | E52: =IF($B$4=1,E25,IF($B$4=2,E34,E43)) | F52: =IF($B$4=1,F25,IF($B$4=2,F34,F43)) | G52: =IF($B$4=1,G25,IF($B$4=2,G34,G43)) | H52: Dynamic R&D as % of revenue
A53: Selected G&A Expense (%) | B53: =IF($B$4=1,B26,IF($B$4=2,B35,B44)) | C53: =IF($B$4=1,C26,IF($B$4=2,C35,C44)) | D53: =IF($B$4=1,D26,IF($B$4=2,D35,D44)) | E53: =IF($B$4=1,E26,IF($B$4=2,E35,E44)) | F53: =IF($B$4=1,F26,IF($B$4=2,F35,F44)) | G53: =IF($B$4=1,G26,IF($B$4=2,G35,G44)) | H53: Dynamic G&A as % of revenue
A54: Selected CapEx (% of Revenue) | B54: =IF($B$4=1,B27,IF($B$4=2,B36,B45)) | C54: =IF($B$4=1,C27,IF($B$4=2,C36,C45)) | D54: =IF($B$4=1,D27,IF($B$4=2,D36,D45)) | E54: =IF($B$4=1,E27,IF($B$4=2,E36,E45)) | F54: =IF($B$4=1,F27,IF($B$4=2,F36,F45)) | G54: =IF($B$4=1,G27,IF($B$4=2,G36,G45)) | H54: Dynamic CapEx intensity as % of revenue
A55: Selected Terminal Growth (g) | B55: - | C55: - | D55: - | E55: - | F55: - | G55: =IF($B$4=1,G28,IF($B$4=2,G37,G46)) | H55: Dynamic terminal perpetuity growth rate
A56: Applied WACC Discount Rate (%) | B56: ='WACC Build'!$E$26 | C56: ='WACC Build'!$E$26 | D56: ='WACC Build'!$E$26 | E56: ='WACC Build'!$E$26 | F56: ='WACC Build'!$E$26 | G56: ='WACC Build'!$E$26 | H56: 加權平均資金成本 (WACC Build 連結)
A58: III. CONSOLIDATED INCOME STATEMENT PROJECTIONS ($M)
A59: Income Statement Line Item ($M) | B59: FY24A | C59: FY25A | D59: FY26E | E59: FY27E | F59: FY28E | G59: FY29E | H59: FY30E
A60: Total Revenues | B60: 350018 | C60: 402836 | D60: =C60*(1+B49) | E60: =D60*(1+C49) | F60: =E60*(1+D49) | G60: =F60*(1+E49) | H60: =G60*(1+F49)
A61: YoY Revenue Growth (%) | B61: 0.1387 | C61: =C60/B60-1 | D61: =D60/C60-1 | E61: =E60/D60-1 | F61: =F60/E60-1 | G61: =G60/F60-1 | H61: =H60/G60-1
A62: Cost of Revenues (TAC, Data Center Ops, Content) | B62: 146306 | C62: 167177 | D62: =D60-D63 | E62: =E60-E63 | F62: =F60-F63 | G62: =G60-G63 | H62: =H60-H63
A63: Gross Profit | B63: 203712 | C63: 235659 | D63: =D60*B50 | E63: =E60*C50 | F63: =F60*D50 | G63: =G60*E50 | H63: =H60*F50
A64: Gross Profit Margin (%) | B64: =B63/B60 | C64: =C63/C60 | D64: =D63/D60 | E64: =E63/E60 | F64: =F63/F60 | G64: =G63/G60 | H64: =H63/H60
A65: Operating Expenses:
A66: Sales & Marketing (S&M) | B66: 28495 | C66: 32200 | D66: =D60*B51 | E66: =E60*C51 | F66: =F60*D51 | G66: =G60*E51 | H66: =H60*F51
A67: Research & Development (R&D) | B67: 49326 | C67: 56400 | D67: =D60*B52 | E67: =E60*C52 | F67: =F60*D52 | G67: =G60*E52 | H67: =H60*F52
A68: General & Administrative (G&A) | B68: 13501 | C68: 18020 | D68: =D60*B53 | E68: =E60*C53 | F68: =F60*D53 | G68: =G60*E53 | H68: =H60*F53
A69: Total Operating Expenses | B69: =B66+B67+B68 | C69: =C66+C67+C68 | D69: =D66+D67+D68 | E69: =E66+E67+E68 | F69: =F66+F67+F68 | G69: =G66+G67+G68 | H69: =H66+H67+H68
A70: Operating Income (EBIT) | B70: 112390 | C70: 129039 | D70: =D63-D69 | E70: =E63-E69 | F70: =F63-F69 | G70: =G63-G69 | H70: =H63-H69
A71: EBIT Margin (%) | B71: =B70/B60 | C71: =C70/C60 | D71: =D70/D60 | E71: =E70/E60 | F71: =F70/F60 | G71: =G70/G60 | H71: =H70/H60
A72: Provision for Income Taxes | B72: =B70*$B$14 | C72: =C70*$B$14 | D72: =D70*$B$14 | E72: =E70*$B$14 | F72: =F70*$B$14 | G72: =G70*$B$14 | H72: =H70*$B$14
A73: Effective Tax Rate (%) | B73: =B72/B70 | C73: =C72/C70 | D73: =D72/D70 | E73: =E72/E70 | F73: =F72/F70 | G73: =G72/G70 | H73: =H72/H70
A74: Net Operating Profit After Tax (NOPAT) | B74: =B70-B72 | C74: =C70-C72 | D74: =D70-D72 | E74: =E70-E72 | F74: =F70-F72 | G74: =G70-G72 | H74: =H70-H72
A76: IV. UNLEVERED FREE CASH FLOW BUILD (UFCF) ($M)
A77: Cash Flow Line Item ($M) | B77: FY24A | C77: FY25A | D77: FY26E | E77: FY27E | F77: FY28E | G77: FY29E | H77: FY30E
A78: Net Operating Profit After Tax (NOPAT) | B78: =B74 | C78: =C74 | D78: =D74 | E78: =E74 | F78: =F74 | G78: =G74 | H78: =H74
A79: (+) Depreciation & Amortization (D&A) | B79: 15311 | C79: 18530 | D79: =D60*0.055 | E79: =E60*0.062 | F79: =F60*0.068 | G79: =G60*0.070 | H79: =H60*0.070
A80: D&A (% of Revenue) | B80: =B79/B60 | C80: =C79/C60 | D80: =D79/D60 | E80: =E79/E60 | F80: =F79/F60 | G80: =G79/G60 | H80: =H79/H60
A81: (-) Capital Expenditures (AI Compute & Data Centers) | B81: 52500 | C81: 91400 | D81: =D60*B54 | E81: =E60*C54 | F81: =F60*D54 | G81: =G60*E54 | H81: =H60*F54
A82: CapEx (% of Revenue) | B82: =B81/B60 | C82: =C81/C60 | D82: =D81/D60 | E82: =E81/E60 | F82: =F81/F60 | G82: =G81/G60 | H82: =H81/H60
A83: (-) Change in Net Working Capital (ΔNWC @ 2.0% of ΔRev) | B83: 1200 | C83: 1056 | D83: =(D60-C60)*0.02 | E83: =(E60-D60)*0.02 | F83: =(F60-E60)*0.02 | G83: =(G60-F60)*0.02 | H83: =(H60-G60)*0.02
A84: Unlevered Free Cash Flow (UFCF) | B84: =B78+B79-B81-B83 | C84: =C78+C79-C81-C83 | D84: =D78+D79-D81-D83 | E84: =E78+E79-E81-E83 | F84: =F78+F79-F81-F83 | G84: =G78+G79-G81-G83 | H84: =H78+H79-H81-H83
A85: FCF Conversion (% of NOPAT) | B85: =B84/B78 | C85: =C84/C78 | D85: =D84/D78 | E85: =E84/E78 | F85: =F84/F78 | G85: =G84/G78 | H85: =H84/H78
A87: V. DISCOUNTING SCHEDULE, TERMINAL VALUE & VALUATION BRIDGE ($M)
A88: Valuation & Discounting Line Item | B88: FY26E | C88: FY27E | D88: FY28E | E88: FY29E | F88: FY30E | G88: Terminal Period | H88: Summary Totals / Metric Description
A89: Unlevered Free Cash Flow (UFCF) ($M) | B89: =D84 | C89: =E84 | D89: =F84 | E89: =G84 | F89: =H84 | G89: =F89*(1+G55) | H89: =SUM(B89:F89)
A90: Mid-Year Discount Period (t) | B90: 0.5 | C90: 1.5 | D90: 2.5 | E90: 3.5 | F90: 4.5 | G90: 4.5 | H90: -
A91: Discount Factor (WACC Discounting) | B91: =1/(1+$B$56)^B90 | C91: =1/(1+$B$56)^C90 | D91: =1/(1+$B$56)^D90 | E91: =1/(1+$B$56)^E90 | F91: =1/(1+$B$56)^F90 | G91: =1/(1+$B$56)^G90 | H91: -
A92: Present Value of Cash Flow (PV of UFCF) | B92: =B89*B91 | C92: =C89*C91 | D92: =D89*D91 | E92: =E89*E91 | F92: =F89*F91 | G92: - | H92: =SUM(B92:F92)
A93: Nominal Terminal Value (Perpetuity Growth Method) | B93: - | C93: - | D93: - | E93: - | F93: - | G93: =G89/($B$56-G55) | H93: -
A94: Present Value of Terminal Value (PV of TV) | B94: - | C94: - | D94: - | E94: - | F94: - | G94: =G93*G91 | H94: -
A96: VALUATION BRIDGE & PER-SHARE IMPLICATIONS
A97: Cumulative PV of Explicit 5-Year FCFs ($M) | B97: =H92 | D97: Terminal Value Checks & Metrics:
A98: Present Value of Terminal Value ($M) | B98: =G94 | D98: PV of TV % of Enterprise Value | E98: =B98/B99
A99: Enterprise Value ($M) | B99: =B97+B98 | D99: Implied Exit Multiple (EV / FY30E EBITDA) | E99: =B99/(H70+H79)
A100: (-) Total Debt ($M) | B100: =-B11
A101: (+) Cash, Cash Eq. & Marketable Securities ($M) | B101: =B10
A102: Net Debt Adjustment [Net Cash Addition] ($M) | B102: =B100+B101
A103: Implied Equity Value ($M) | B103: =B99+B102
A104: Diluted Shares Outstanding (M) | B104: =B8
A105: IMPLIED INTRINSIC VALUE PER SHARE ($) | B105: =B103/B104
A106: Current Market Stock Price ($) | B106: =B7
A107: Implied Upside / (Downside) (%) | B107: =B105/B106-1
...

Sheet WACC Build
A1: Alphabet Inc. (NASDAQ: GOOGL / GOOG)
A2: Weighted Average Cost of Capital (WACC) Schedule | CAPM Methodology & Capital Structure
A4: I. COST OF EQUITY (CAPM METHODOLOGY)
A5: Risk-Free Rate (10-Yr US Treasury Yield) | B5: 0.0469
A6: Equity Beta (5-Year Monthly vs S&P 500) | B6: 1.24
A7: Market Equity Risk Premium (ERP) | B7: 0.055
A8: Cost of Equity (Ke = Rf + Beta * ERP) | B8: =B5+B6*B7
A10: II. COST OF DEBT & CAPITAL STRUCTURE WEIGHTS
A11: Pre-Tax Cost of Debt (Kd) | B11: 0.0485
A12: Effective Corporate Tax Rate (t) | B12: 0.175
A13: After-Tax Cost of Debt (Kd * (1 - t)) | B13: =B11*(1-B12)
A14: Current Share Price ($) | B14: ='DCF Valuation'!B7
A15: Diluted Shares Outstanding (M) | B15: ='DCF Valuation'!B8
A16: Market Capitalization ($M) | B16: =B14*B15
A17: Total Debt (Current + Noncurrent Debt) ($M) | B17: 98200
A18: Cash, Cash Equivalents & Marketable Securities ($M) | B18: 242500
A19: Net Debt ($M) [Net Cash if negative] | B19: =B17-B18
A20: Enterprise Value ($M) | B20: =B16+B19
A22: III. WACC CALCULATION SUMMARY
A23: Component | B23: Market Value ($M) | C23: Capital Weight (%) | D23: Cost of Capital (%) | E23: Weighted Contribution (%)
A24: Common Equity (Market Cap) | B24: =B16 | C24: =B24/$B$20 | D24: =B8 | E24: =C24*D24
A25: Net Debt (Net Cash Adjustment) | B25: =B19 | C25: =B25/$B$20 | D25: =B13 | E25: =C25*D25
A26: Total Capitalization / Base WACC | B26: =B20 | C26: =SUM(C24:C25) | D26: - | E26: =SUM(E24:E25)
