Workbook

Sheet DCF Valuation
A1: Microsoft Corporation (NASDAQ: MSFT)
A2: Institutional DCF Valuation Model | Report Date: August 19, 2026 | Financial Source: SEC Form 10-K (FY2022-FY2026)
A4: Active Scenario Selector: | B4: 2 | C4: =IF(B4=1,"[1] BEAR CASE (AI Digestion / Cloud Slowdown)",IF(B4=2,"[2] BASE CASE (Consensus AI Cloud Scaling & Copilot Monetization)","[3] BULL CASE (AI Supercycle & Azure Platform Dominance)"))
A6: I. MARKET DATA & CAPITAL STRUCTURE INPUTS
A7: Current Stock Price ($) | B7: 481.59
A8: Diluted Shares Outstanding (M) | B8: 7435
A9: Implied Equity Market Capitalization ($M) | B9: =B7*B8
A10: Cash and Short-Term Investments ($M) | B10: 76843
A11: Total Debt ($M) | B11: 47600
A12: Net Debt ($M) [Net Cash if negative] | B12: =B11-B10
A13: Implied Enterprise Value ($M) | B13: =B9+B12
A14: Effective Corporate Tax Rate (%) | B14: 0.2
A15: Risk-Free Rate (10-Yr US Treasury) (%) | B15: ='WACC Build'!B5
A16: Equity Beta (5-Year Monthly) | B16: ='WACC Build'!B6
A17: Market Equity Risk Premium (ERP) (%) | B17: ='WACC Build'!B7
A18: Base Case WACC (%) | B18: ='WACC Build'!E26
A20: II. SCENARIO ASSUMPTIONS & DRIVER BLOCKS
A21: Driver / Assumption | B21: FY2026A | C21: FY2027E | D21: FY2028E | E21: FY2029E | F21: FY2030E | G21: FY2031E | H21: Terminal / WACC
A22: Bear Case Assumptions (Selector = 1)
A23: Revenue Growth (%) | B23: - | C23: 0.11 | D23: 0.095 | E23: 0.085 | F23: 0.075 | G23: 0.065 | H23: 0.025
A24: Gross Margin (%) | B24: - | C24: 0.675 | D24: 0.675 | E24: 0.67 | F24: 0.665 | G24: 0.66 | H24: -
A25: EBIT Margin (%) | B25: - | C25: 0.455 | D25: 0.45 | E25: 0.445 | F25: 0.44 | G25: 0.435 | H25: 0.115
A26: D&A (% of Revenue) | B26: - | C26: 0.135 | D26: 0.145 | E26: 0.14 | F26: 0.135 | G26: 0.125 | H26: -
A27: CapEx (% of Revenue) | B27: - | C27: 0.3 | D27: 0.26 | E27: 0.22 | F27: 0.18 | G27: 0.15 | H27: -
A28: Δ NWC (% of Δ Revenue) | B28: - | C28: 0.015 | D28: 0.015 | E28: 0.015 | F28: 0.015 | G28: 0.015 | H28: -
A29: Base Case Assumptions (Selector = 2)
A30: Revenue Growth (%) | B30: - | C30: 0.145 | D30: 0.13 | E30: 0.115 | F30: 0.1 | G30: 0.085 | H30: 0.03
A31: Gross Margin (%) | B31: - | C31: 0.685 | D31: 0.69 | E31: 0.695 | F31: 0.7 | G31: 0.702 | H31: -
A32: EBIT Margin (%) | B32: - | C32: 0.47 | D32: 0.478 | E32: 0.486 | F32: 0.493 | G32: 0.5 | H32: ='WACC Build'!E26
A33: D&A (% of Revenue) | B33: - | C33: 0.13 | D33: 0.14 | E33: 0.135 | F33: 0.13 | G33: 0.12 | H33: -
A34: CapEx (% of Revenue) | B34: - | C34: 0.28 | D34: 0.23 | E34: 0.19 | F34: 0.16 | G34: 0.135 | H34: -
A35: Δ NWC (% of Δ Revenue) | B35: - | C35: 0.01 | D35: 0.01 | E35: 0.01 | F35: 0.01 | G35: 0.01 | H35: -
A36: Bull Case Assumptions (Selector = 3)
A37: Revenue Growth (%) | B37: - | C37: 0.175 | D37: 0.16 | E37: 0.14 | F37: 0.125 | G37: 0.105 | H37: 0.035
A38: Gross Margin (%) | B38: - | C38: 0.695 | D38: 0.705 | E38: 0.712 | F38: 0.718 | G38: 0.725 | H38: -
A39: EBIT Margin (%) | B39: - | C39: 0.48 | D39: 0.492 | E39: 0.505 | F39: 0.515 | G39: 0.525 | H39: 0.1
A40: D&A (% of Revenue) | B40: - | C40: 0.125 | D40: 0.135 | E40: 0.13 | F40: 0.125 | G40: 0.115 | H40: -
A41: CapEx (% of Revenue) | B41: - | C41: 0.26 | D41: 0.21 | E41: 0.175 | F41: 0.145 | G41: 0.12 | H41: -
A42: Δ NWC (% of Δ Revenue) | B42: - | C42: 0.01 | D42: 0.01 | E42: 0.01 | F42: 0.01 | G42: 0.01 | H42: -
A43: ACTIVE CONSOLIDATED DRIVERS (PULLED VIA INDEX FORMULAS)
A44: Active Revenue Growth (%) | B44: - | C44: =INDEX((C$23,C$30,C$37),1,1,$B$4) | D44: =INDEX((D$23,D$30,D$37),1,1,$B$4) | E44: =INDEX((E$23,E$30,E$37),1,1,$B$4) | F44: =INDEX((F$23,F$30,F$37),1,1,$B$4) | G44: =INDEX((G$23,G$30,G$37),1,1,$B$4) | H44: =INDEX((H$23,H$30,H$37),1,1,$B$4)
A45: Active Gross Margin (%) | B45: - | C45: =INDEX((C$24,C$31,C$38),1,1,$B$4) | D45: =INDEX((D$24,D$31,D$38),1,1,$B$4) | E45: =INDEX((E$24,E$31,E$38),1,1,$B$4) | F45: =INDEX((F$24,F$31,F$38),1,1,$B$4) | G45: =INDEX((G$24,G$31,G$38),1,1,$B$4) | H45: -
A46: Active EBIT Margin (%) | B46: - | C46: =INDEX((C$25,C$32,C$39),1,1,$B$4) | D46: =INDEX((D$25,D$32,D$39),1,1,$B$4) | E46: =INDEX((E$25,E$32,E$39),1,1,$B$4) | F46: =INDEX((F$25,F$32,F$39),1,1,$B$4) | G46: =INDEX((G$25,G$32,G$39),1,1,$B$4) | H46: =INDEX((H$25,H$32,H$39),1,1,$B$4)
A47: Active D&A (% of Revenue) | B47: - | C47: =INDEX((C$26,C$33,C$40),1,1,$B$4) | D47: =INDEX((D$26,D$33,D$40),1,1,$B$4) | E47: =INDEX((E$26,E$33,E$40),1,1,$B$4) | F47: =INDEX((F$26,F$33,F$40),1,1,$B$4) | G47: =INDEX((G$26,G$33,G$40),1,1,$B$4) | H47: -
A48: Active CapEx (% of Revenue) | B48: - | C48: =INDEX((C$27,C$34,C$41),1,1,$B$4) | D48: =INDEX((D$27,D$34,D$41),1,1,$B$4) | E48: =INDEX((E$27,E$34,E$41),1,1,$B$4) | F48: =INDEX((F$27,F$34,F$41),1,1,$B$4) | G48: =INDEX((G$27,G$34,G$41),1,1,$B$4) | H48: -
A49: Active Δ NWC (% of Δ Revenue) | B49: - | C49: =INDEX((C$28,C$35,C$42),1,1,$B$4) | D49: =INDEX((D$28,D$35,D$42),1,1,$B$4) | E49: =INDEX((E$28,E$35,E$42),1,1,$B$4) | F49: =INDEX((F$28,F$35,F$42),1,1,$B$4) | G49: =INDEX((G$28,G$35,G$42),1,1,$B$4) | H49: -
A51: III. FINANCIAL PERFORMANCE & 5-YEAR PROJECTIONS ($M)
A52: Income Statement Line Item ($M) | B52: FY2022A | C52: FY2023A | D52: FY2024A | E52: FY2025A | F52: FY2026A | G52: FY2027E | H52: FY2028E | I52: FY2029E | J52: FY2030E | K52: FY2031E
A53: Total Revenue | B53: 198270 | C53: 211915 | D53: 245120 | E53: 281724 | F53: 331839 | G53: =F53*(1+C44) | H53: =G53*(1+D44) | I53: =H53*(1+E44) | J53: =I53*(1+F44) | K53: =J53*(1+G44)
A54: Revenue YoY Growth (%) | B54: - | C54: =C53/B53-1 | D54: =D53/C53-1 | E54: =E53/D53-1 | F54: =F53/E53-1 | G54: =G53/F53-1 | H54: =H53/G53-1 | I54: =I53/H53-1 | J54: =J53/I53-1 | K54: =K53/J53-1
A55: Gross Profit | B55: 135620 | C55: 146052 | D55: 171010 | E55: 193893 | F55: 225465 | G55: =G53*C45 | H55: =H53*D45 | I55: =I53*E45 | J55: =J53*F45 | K55: =K53*G45
A56: Gross Margin (%) | B56: =B55/B53 | C56: =C55/C53 | D56: =D55/D53 | E56: =E55/E53 | F56: =F55/F53 | G56: =G55/G53 | H56: =H55/H53 | I56: =I55/I53 | ... K56: =K55/K53
A57: Research and Development (R&D) | B57: 24512 | C57: 27195 | D57: 29510 | E57: 32488 | F57: 37830 | G57: =G53*0.112 | H57: =H53*0.110 | I57: =I53*0.108 | J57: =J53*0.105 | K57: =K53*0.102
A58: Sales and Marketing (S&M) | B58: 21825 | C58: 22759 | D58: 24260 | E58: 25654 | F58: 27870 | G58: =G53*0.082 | H58: =H53*0.078 | I58: =I53*0.075 | J58: =J53*0.072 | K58: =K53*0.070
A59: General and Administrative (G&A) | B59: 5414 | C59: 7575 | D59: 7807 | E59: 7256 | F59: 4528 | G59: =G55-G60-G57-G58 | H59: =H55-H60-H57-H58 | I59: =I55-I60-I57-I58 | J59: =J55-J60-J57-J58 | K59: =K55-K60-K57-K58
A60: Operating Income (EBIT) | B60: 83383 | C60: 88523 | D60: 109433 | E60: 128495 | F60: 155237 | G60: =G53*C46 | H60: =H53*D46 | I60: =I53*E46 | J60: =J53*F46 | K60: =K53*G46
A61: EBIT Margin (%) | B61: =B60/B53 | C61: =C60/C53 | D61: =D60/D53 | E61: =E60/E53 | F61: =F60/F53 | G61: =G60/G53 | H61: =H60/H53 | I61: =I60/I53 | ... K61: =K60/K53
A62: (-) Provision for Income Taxes | B62: 10978 | C62: 16950 | D62: 21080 | E62: 25700 | F62: 31047 | G62: =G60*$B$14 | H62: =H60*$B$14 | I62: =I60*$B$14 | J62: =J60*$B$14 | K62: =K60*$B$14
A63: Net Operating Profit After Tax (NOPAT) | B63: =B60-B62 | C63: =C60-C62 | D63: =D60-D62 | E63: =E60-E62 | F63: =F60-F62 | G63: =G60-G62 | H63: =H60-H62 | I63: =I60-I62 | ... K63: =K60-K62
A65: IV. UNLEVERED FREE CASH FLOW (UFCF) BUILD ($M)
A66: Cash Flow Line Item ($M) | B66: FY2022A | C66: FY2023A | D66: FY2024A | E66: FY2025A | F66: FY2026A | G66: FY2027E | H66: FY2028E | I66: FY2029E | J66: FY2030E | K66: FY2031E
A67: Net Operating Profit After Tax (NOPAT) | B67: =B63 | C67: =C63 | D67: =D63 | E67: =E63 | F67: =F63 | G67: =G63 | H67: =H63 | I67: =I63 | ... K67: =K63
A68: (+) Depreciation & Amortization (D&A) | B68: 14460 | C68: 13861 | D68: 22287 | E68: 34153 | F68: 38534 | G68: =G53*C47 | H68: =H53*D47 | I68: =I53*E47 | J68: =J53*F47 | K68: =K53*G47
A69: (-) Capital Expenditures (CapEx) | B69: 23886 | C69: 28107 | D69: 44480 | E69: 72500 | F69: 115900 | G69: =G53*C48 | H69: =H53*D48 | I69: =I53*E48 | J69: =J53*F48 | K69: =K53*G48
A70: (-) Change in Net Working Capital (Δ NWC) | B70: 1800 | C70: 2000 | D70: 3500 | E70: 4000 | F70: 5000 | G70: =(G53-F53)*C49 | H70: =(H53-G53)*D49 | I70: =(I53-H53)*E49 | J70: =(J53-I53)*F49 | K70: =(K53-J53)*G49
A71: Unlevered Free Cash Flow (UFCF) | B71: =B67+B68-B69-B70 | C71: =C67+C68-C69-C70 | D71: =D67+D68-D69-D70 | E71: =E67+E68-E69-E70 | F71: =F67+F68-F69-F70 | G71: =G67+G68-G69-G70 | H71: =H67+H68-H69-H70 | I71: =I67+I68-I69-I70 | ... K71: =K67+K68-K69-K70
A72: FCF Conversion Margin (% of Revenue) | B72: =B71/B53 | C72: =C71/C53 | D72: =D71/D53 | E72: =E71/E53 | F72: =F71/F53 | G72: =G71/G53 | H72: =H71/H53 | I72: =I71/I53 | ... K72: =K71/K53
A74: V. DISCOUNTING SCHEDULE & VALUATION SUMMARY ($M)
A75: DCF Component ($M) | B75: FY2027E | C75: FY2028E | D75: FY2029E | E75: FY2030E | F75: FY2031E | G75: Terminal Year
A76: Unlevered Free Cash Flow (UFCF) | B76: =G71 | C76: =H71 | D76: =I71 | E76: =J71 | F76: =K71 | G76: =F76*(1+$H$44)
A77: Mid-Year Discount Period (t) | B77: 0.5 | C77: 1.5 | D77: 2.5 | E77: 3.5 | F77: 4.5 | G77: 4.5
A78: Discount Factor (WACC Discounting) | B78: =1/(1+$H$46)^B77 | C78: =1/(1+$H$46)^C77 | D78: =1/(1+$H$46)^D77 | E78: =1/(1+$H$46)^E77 | F78: =1/(1+$H$46)^F77 | G78: =1/(1+$H$46)^G77
A79: Present Value of Cash Flow (PV of UFCF) | B79: =B76*B78 | C79: =C76*C78 | D79: =D76*D78 | E79: =E76*E78 | F79: =F76*F78 | G79: -
A80: Nominal Terminal Value (Perpetuity Growth Method) | B80: - | C80: - | D80: - | E80: - | F80: - | G80: =G76/($H$46-$H$44)
A81: Present Value of Terminal Value (PV of TV) | B81: - | C81: - | D81: - | E81: - | F81: - | G81: =G80*G78
A83: VALUATION BRIDGE & PER-SHARE IMPLICATION
A84: Cumulative PV of Explicit 5-Year FCFs ($M) | B84: =SUM(B79:F79) | D84: Terminal Value Metrics & Checks:
A85: Present Value of Terminal Value ($M) | B85: =G81 | D85: PV of TV % of Enterprise Value | E85: =B85/B86
A86: Enterprise Value ($M) | B86: =B84+B85 | D86: Implied Exit Multiple (EV / FY31E EBITDA) | E86: =B86/(K60+K68)
A87: (-) Total Debt ($M) | B87: =-B11
A88: (+) Cash and Short-Term Investments ($M) | B88: =B10
A89: Net Debt Adjustment ($M) [Net Cash = +$] | B89: =B87+B88
A90: Implied Equity Value ($M) | B90: =B86+B89
A91: Diluted Shares Outstanding (M) | B91: =B8
A92: IMPLIED INTRINSIC VALUE PER SHARE ($) | B92: =B90/B91
A93: Current Market Stock Price ($) | B93: =B7
A94: Implied Upside / (Downside) (%) | B94: =B92/B93-1
A98: VI. INSTITUTIONAL SENSITIVITY MATRICES (5x5 GRIDS WITH FULL DCF RECALCULATION)
A100: TABLE 1: IMPLIED SHARE PRICE ($) - WACC vs. TERMINAL GROWTH RATE (g)
A101: WACC \ Terminal g | B101: =$H$44-0.01 | C101: =$H$44-0.005 | D101: =$H$44 | E101: =$H$44+0.005 | F101: =$H$44+0.01
A102: =$H$46-0.01 | B102: =(($B$76/(1+$A102)^0.5 + $C$76/(1+$A102)^1.5 + $D$76/(1+$A102)^2.5 + $E$76/(1+$A102)^3.5 + $F$76/(1+$A102)^4.5) + (($F$76*(1+B$101)/($A102-B$101))/(1+$A102)^4.5) + $B$89)/$B$91 | C102: =(($B$76/(1+$A102)^0.5 + $C$76/(1+$A102)^1.5 + $D$76/(1+$A102)^2.5 + $E$76/(1+$A102)^3.5 + $F$76/(1+$A102)^4.5) + (($F$76*(1+C$101)/($A102-C$101))/(1+$A102)^4.5) + $B$89)/$B$91 | D102: =(($B$76/(1+$A102)^0.5 + $C$76/(1+$A102)^1.5 + $D$76/(1+$A102)^2.5 + $E$76/(1+$A102)^3.5 + $F$76/(1+$A102)^4.5) + (($F$76*(1+D$101)/($A102-D$101))/(1+$A102)^4.5) + $B$89)/$B$91 | E102: =(($B$76/(1+$A102)^0.5 + $C$76/(1+$A102)^1.5 + $D$76/(1+$A102)^2.5 + $E$76/(1+$A102)^3.5 + $F$76/(1+$A102)^4.5) + (($F$76*(1+E$101)/($A102-E$101))/(1+$A102)^4.5) + $B$89)/$B$91 | F102: =(($B$76/(1+$A102)^0.5 + $C$76/(1+$A102)^1.5 + $D$76/(1+$A102)^2.5 + $E$76/(1+$A102)^3.5 + $F$76/(1+$A102)^4.5) + (($F$76*(1+F$101)/($A102-F$101))/(1+$A102)^4.5) + $B$89)/$B$91
A103: =$H$46-0.005 | B103: =(($B$76/(1+$A103)^0.5 + $C$76/(1+$A103)^1.5 + $D$76/(1+$A103)^2.5 + $E$76/(1+$A103)^3.5 + $F$76/(1+$A103)^4.5) + (($F$76*(1+B$101)/($A103-B$101))/(1+$A103)^4.5) + $B$89)/$B$91 | C103: =(($B$76/(1+$A103)^0.5 + $C$76/(1+$A103)^1.5 + $D$76/(1+$A103)^2.5 + $E$76/(1+$A103)^3.5 + $F$76/(1+$A103)^4.5) + (($F$76*(1+C$101)/($A103-C$101))/(1+$A103)^4.5) + $B$89)/$B$91 | D103: =(($B$76/(1+$A103)^0.5 + $C$76/(1+$A103)^1.5 + $D$76/(1+$A103)^2.5 + $E$76/(1+$A103)^3.5 + $F$76/(1+$A103)^4.5) + (($F$76*(1+D$101)/($A103-D$101))/(1+$A103)^4.5) + $B$89)/$B$91 | E103: =(($B$76/(1+$A103)^0.5 + $C$76/(1+$A103)^1.5 + $D$76/(1+$A103)^2.5 + $E$76/(1+$A103)^3.5 + $F$76/(1+$A103)^4.5) + (($F$76*(1+E$101)/($A103-E$101))/(1+$A103)^4.5) + $B$89)/$B$91 | F103: =(($B$76/(1+$A103)^0.5 + $C$76/(1+$A103)^1.5 + $D$76/(1+$A103)^2.5 + $E$76/(1+$A103)^3.5 + $F$76/(1+$A103)^4.5) + (($F$76*(1+F$101)/($A103-F$101))/(1+$A103)^4.5) + $B$89)/$B$91
A104: =$H$46 | B104: =(($B$76/(1+$A104)^0.5 + $C$76/(1+$A104)^1.5 + $D$76/(1+$A104)^2.5 + $E$76/(1+$A104)^3.5 + $F$76/(1+$A104)^4.5) + (($F$76*(1+B$101)/($A104-B$101))/(1+$A104)^4.5) + $B$89)/$B$91 | C104: =(($B$76/(1+$A104)^0.5 + $C$76/(1+$A104)^1.5 + $D$76/(1+$A104)^2.5 + $E$76/(1+$A104)^3.5 + $F$76/(1+$A104)^4.5) + (($F$76*(1+C$101)/($A104-C$101))/(1+$A104)^4.5) + $B$89)/$B$91 | D104: =(($B$76/(1+$A104)^0.5 + $C$76/(1+$A104)^1.5 + $D$76/(1+$A104)^2.5 + $E$76/(1+$A104)^3.5 + $F$76/(1+$A104)^4.5) + (($F$76*(1+D$101)/($A104-D$101))/(1+$A104)^4.5) + $B$89)/$B$91 | E104: =(($B$76/(1+$A104)^0.5 + $C$76/(1+$A104)^1.5 + $D$76/(1+$A104)^2.5 + $E$76/(1+$A104)^3.5 + $F$76/(1+$A104)^4.5) + (($F$76*(1+E$101)/($A104-E$101))/(1+$A104)^4.5) + $B$89)/$B$91 | F104: =(($B$76/(1+$A104)^0.5 + $C$76/(1+$A104)^1.5 + $D$76/(1+$A104)^2.5 + $E$76/(1+$A104)^3.5 + $F$76/(1+$A104)^4.5) + (($F$76*(1+F$101)/($A104-F$101))/(1+$A104)^4.5) + $B$89)/$B$91
A105: =$H$46+0.005 | B105: =(($B$76/(1+$A105)^0.5 + $C$76/(1+$A105)^1.5 + $D$76/(1+$A105)^2.5 + $E$76/(1+$A105)^3.5 + $F$76/(1+$A105)^4.5) + (($F$76*(1+B$101)/($A105-B$101))/(1+$A105)^4.5) + $B$89)/$B$91 | C105: =(($B$76/(1+$A105)^0.5 + $C$76/(1+$A105)^1.5 + $D$76/(1+$A105)^2.5 + $E$76/(1+$A105)^3.5 + $F$76/(1+$A105)^4.5) + (($F$76*(1+C$101)/($A105-C$101))/(1+$A105)^4.5) + $B$89)/$B$91 | D105: =(($B$76/(1+$A105)^0.5 + $C$76/(1+$A105)^1.5 + $D$76/(1+$A105)^2.5 + $E$76/(1+$A105)^3.5 + $F$76/(1+$A105)^4.5) + (($F$76*(1+D$101)/($A105-D$101))/(1+$A105)^4.5) + $B$89)/$B$91 | E105: =(($B$76/(1+$A105)^0.5 + $C$76/(1+$A105)^1.5 + $D$76/(1+$A105)^2.5 + $E$76/(1+$A105)^3.5 + $F$76/(1+$A105)^4.5) + (($F$76*(1+E$101)/($A105-E$101))/(1+$A105)^4.5) + $B$89)/$B$91 | F105: =(($B$76/(1+$A105)^0.5 + $C$76/(1+$A105)^1.5 + $D$76/(1+$A105)^2.5 + $E$76/(1+$A105)^3.5 + $F$76/(1+$A105)^4.5) + (($F$76*(1+F$101)/($A105-F$101))/(1+$A105)^4.5) + $B$89)/$B$91
A106: =$H$46+0.01 | B106: =(($B$76/(1+$A106)^0.5 + $C$76/(1+$A106)^1.5 + $D$76/(1+$A106)^2.5 + $E$76/(1+$A106)^3.5 + $F$76/(1+$A106)^4.5) + (($F$76*(1+B$101)/($A106-B$101))/(1+$A106)^4.5) + $B$89)/$B$91 | C106: =(($B$76/(1+$A106)^0.5 + $C$76/(1+$A106)^1.5 + $D$76/(1+$A106)^2.5 + $E$76/(1+$A106)^3.5 + $F$76/(1+$A106)^4.5) + (($F$76*(1+C$101)/($A106-C$101))/(1+$A106)^4.5) + $B$89)/$B$91 | D106: =(($B$76/(1+$A106)^0.5 + $C$76/(1+$A106)^1.5 + $D$76/(1+$A106)^2.5 + $E$76/(1+$A106)^3.5 + $F$76/(1+$A106)^4.5) + (($F$76*(1+D$101)/($A106-D$101))/(1+$A106)^4.5) + $B$89)/$B$91 | E106: =(($B$76/(1+$A106)^0.5 + $C$76/(1+$A106)^1.5 + $D$76/(1+$A106)^2.5 + $E$76/(1+$A106)^3.5 + $F$76/(1+$A106)^4.5) + (($F$76*(1+E$101)/($A106-E$101))/(1+$A106)^4.5) + $B$89)/$B$91 | F106: =(($B$76/(1+$A106)^0.5 + $C$76/(1+$A106)^1.5 + $D$76/(1+$A106)^2.5 + $E$76/(1+$A106)^3.5 + $F$76/(1+$A106)^4.5) + (($F$76*(1+F$101)/($A106-F$101))/(1+$A106)^4.5) + $B$89)/$B$91
A110: TABLE 2: IMPLIED SHARE PRICE ($) - REVENUE GROWTH MULTIPLIER vs. FY31E EBIT MARGIN
A111: Growth Multiplier \ EBIT Margin | B111: =$G$46-0.04 | C111: =$G$46-0.02 | D111: =$G$46 | E111: =$G$46+0.02 | F111: =$G$46+0.04
A112: 0.8 | B112: =((($B$76*$A112*(B$111/$G$46)/(1+$H$46)^0.5 + $C$76*$A112*(B$111/$G$46)/(1+$H$46)^1.5 + $D$76*$A112*(B$111/$G$46)/(1+$H$46)^2.5 + $E$76*$A112*(B$111/$G$46)/(1+$H$46)^3.5 + $F$76*$A112*(B$111/$G$46)/(1+$H$46)^4.5) + (($F$76*$A112*(B$111/$G$46)*(1+$H$44)/($H$46-$H$44))/(1+$H$46)^4.5) + $B$89)/$B$91) | C112: =((($B$76*$A112*(C$111/$G$46)/(1+$H$46)^0.5 + $C$76*$A112*(C$111/$G$46)/(1+$H$46)^1.5 + $D$76*$A112*(C$111/$G$46)/(1+$H$46)^2.5 + $E$76*$A112*(C$111/$G$46)/(1+$H$46)^3.5 + $F$76*$A112*(C$111/$G$46)/(1+$H$46)^4.5) + (($F$76*$A112*(C$111/$G$46)*(1+$H$44)/($H$46-$H$44))/(1+$H$46)^4.5) + $B$89)/$B$91) | D112: =((($B$76*$A112*(D$111/$G$46)/(1+$H$46)^0.5 + $C$76*$A112*(D$111/$G$46)/(1+$H$46)^1.5 + $D$76*$A112*(D$111/$G$46)/(1+$H$46)^2.5 + $E$76*$A112*(D$111/$G$46)/(1+$H$46)^3.5 + $F$76*$A112*(D$111/$G$46)/(1+$H$46)^4.5) + (($F$76*$A112*(D$111/$G$46)*(1+$H$44)/($H$46-$H$44))/(1+$H$46)^4.5) + $B$89)/$B$91) | E112: =((($B$76*$A112*(E$111/$G$46)/(1+$H$46)^0.5 + $C$76*$A112*(E$111/$G$46)/(1+$H$46)^1.5 + $D$76*$A112*(E$111/$G$46)/(1+$H$46)^2.5 + $E$76*$A112*(E$111/$G$46)/(1+$H$46)^3.5 + $F$76*$A112*(E$111/$G$46)/(1+$H$46)^4.5) + (($F$76*$A112*(E$111/$G$46)*(1+$H$44)/($H$46-$H$44))/(1+$H$46)^4.5) + $B$89)/$B$91) | F112: =((($B$76*$A112*(F$111/$G$46)/(1+$H$46)^0.5 + $C$76*$A112*(F$111/$G$46)/(1+$H$46)^1.5 + $D$76*$A112*(F$111/$G$46)/(1+$H$46)^2.5 + $E$76*$A112*(F$111/$G$46)/(1+$H$46)^3.5 + $F$76*$A112*(F$111/$G$46)/(1+$H$46)^4.5) + (($F$76*$A112*(F$111/$G$46)*(1+$H$44)/($H$46-$H$44))/(1+$H$46)^4.5) + $B$89)/$B$91)
A113: 0.9 | B113: =((($B$76*$A113*(B$111/$G$46)/(1+$H$46)^0.5 + $C$76*$A113*(B$111/$G$46)/(1+$H$46)^1.5 + $D$76*$A113*(B$111/$G$46)/(1+$H$46)^2.5 + $E$76*$A113*(B$111/$G$46)/(1+$H$46)^3.5 + $F$76*$A113*(B$111/$G$46)/(1+$H$46)^4.5) + (($F$76*$A113*(B$111/$G$46)*(1+$H$44)/($H$46-$H$44))/(1+$H$46)^4.5) + $B$89)/$B$91) | C113: =((($B$76*$A113*(C$111/$G$46)/(1+$H$46)^0.5 + $C$76*$A113*(C$111/$G$46)/(1+$H$46)^1.5 + $D$76*$A113*(C$111/$G$46)/(1+$H$46)^2.5 + $E$76*$A113*(C$111/$G$46)/(1+$H$46)^3.5 + $F$76*$A113*(C$111/$G$46)/(1+$H$46)^4.5) + (($F$76*$A113*(C$111/$G$46)*(1+$H$44)/($H$46-$H$44))/(1+$H$46)^4.5) + $B$89)/$B$91) | D113: =((($B$76*$A113*(D$111/$G$46)/(1+$H$46)^0.5 + $C$76*$A113*(D$111/$G$46)/(1+$H$46)^1.5 + $D$76*$A113*(D$111/$G$46)/(1+$H$46)^2.5 + $E$76*$A113*(D$111/$G$46)/(1+$H$46)^3.5 + $F$76*$A113*(D$111/$G$46)/(1+$H$46)^4.5) + (($F$76*$A113*(D$111/$G$46)*(1+$H$44)/($H$46-$H$44))/(1+$H$46)^4.5) + $B$89)/$B$91) | E113: =((($B$76*$A113*(E$111/$G$46)/(1+$H$46)^0.5 + $C$76*$A113*(E$111/$G$46)/(1+$H$46)^1.5 + $D$76*$A113*(E$111/$G$46)/(1+$H$46)^2.5 + $E$76*$A113*(E$111/$G$46)/(1+$H$46)^3.5 + $F$76*$A113*(E$111/$G$46)/(1+$H$46)^4.5) + (($F$76*$A113*(E$111/$G$46)*(1+$H$44)/($H$46-$H$44))/(1+$H$46)^4.5) + $B$89)/$B$91) | F113: =((($B$76*$A113*(F$111/$G$46)/(1+$H$46)^0.5 + $C$76*$A113*(F$111/$G$46)/(1+$H$46)^1.5 + $D$76*$A113*(F$111/$G$46)/(1+$H$46)^2.5 + $E$76*$A113*(F$111/$G$46)/(1+$H$46)^3.5 + $F$76*$A113*(F$111/$G$46)/(1+$H$46)^4.5) + (($F$76*$A113*(F$111/$G$46)*(1+$H$44)/($H$46-$H$44))/(1+$H$46)^4.5) + $B$89)/$B$91)
A114: 1 | B114: =((($B$76*$A114*(B$111/$G$46)/(1+$H$46)^0.5 + $C$76*$A114*(B$111/$G$46)/(1+$H$46)^1.5 + $D$76*$A114*(B$111/$G$46)/(1+$H$46)^2.5 + $E$76*$A114*(B$111/$G$46)/(1+$H$46)^3.5 + $F$76*$A114*(B$111/$G$46)/(1+$H$46)^4.5) + (($F$76*$A114*(B$111/$G$46)*(1+$H$44)/($H$46-$H$44))/(1+$H$46)^4.5) + $B$89)/$B$91) | C114: =((($B$76*$A114*(C$111/$G$46)/(1+$H$46)^0.5 + $C$76*$A114*(C$111/$G$46)/(1+$H$46)^1.5 + $D$76*$A114*(C$111/$G$46)/(1+$H$46)^2.5 + $E$76*$A114*(C$111/$G$46)/(1+$H$46)^3.5 + $F$76*$A114*(C$111/$G$46)/(1+$H$46)^4.5) + (($F$76*$A114*(C$111/$G$46)*(1+$H$44)/($H$46-$H$44))/(1+$H$46)^4.5) + $B$89)/$B$91) | D114: =((($B$76*$A114*(D$111/$G$46)/(1+$H$46)^0.5 + $C$76*$A114*(D$111/$G$46)/(1+$H$46)^1.5 + $D$76*$A114*(D$111/$G$46)/(1+$H$46)^2.5 + $E$76*$A114*(D$111/$G$46)/(1+$H$46)^3.5 + $F$76*$A114*(D$111/$G$46)/(1+$H$46)^4.5) + (($F$76*$A114*(D$111/$G$46)*(1+$H$44)/($H$46-$H$44))/(1+$H$46)^4.5) + $B$89)/$B$91) | E114: =((($B$76*$A114*(E$111/$G$46)/(1+$H$46)^0.5 + $C$76*$A114*(E$111/$G$46)/(1+$H$46)^1.5 + $D$76*$A114*(E$111/$G$46)/(1+$H$46)^2.5 + $E$76*$A114*(E$111/$G$46)/(1+$H$46)^3.5 + $F$76*$A114*(E$111/$G$46)/(1+$H$46)^4.5) + (($F$76*$A114*(E$111/$G$46)*(1+$H$44)/($H$46-$H$44))/(1+$H$46)^4.5) + $B$89)/$B$91) | F114: =((($B$76*$A114*(F$111/$G$46)/(1+$H$46)^0.5 + $C$76*$A114*(F$111/$G$46)/(1+$H$46)^1.5 + $D$76*$A114*(F$111/$G$46)/(1+$H$46)^2.5 + $E$76*$A114*(F$111/$G$46)/(1+$H$46)^3.5 + $F$76*$A114*(F$111/$G$46)/(1+$H$46)^4.5) + (($F$76*$A114*(F$111/$G$46)*(1+$H$44)/($H$46-$H$44))/(1+$H$46)^4.5) + $B$89)/$B$91)
...

Sheet WACC Build
A1: Microsoft Corporation (NASDAQ: MSFT)
A2: Weighted Average Cost of Capital (WACC) Schedule | CAPM Methodology & Capital Structure
A4: I. COST OF EQUITY (CAPM METHODOLOGY)
A5: Risk-Free Rate (10-Yr US Treasury Yield) | B5: 0.0475
A6: Equity Beta (5-Year Monthly vs S&P 500) | B6: 1.1
A7: Market Equity Risk Premium (ERP) | B7: 0.055
A8: Cost of Equity (Ke = Rf + Beta * ERP) | B8: =B5+B6*B7
A10: II. COST OF DEBT & CAPITAL STRUCTURE WEIGHTS
A11: Pre-Tax Cost of Debt (Kd) | B11: 0.0495
A12: Effective Corporate Tax Rate (t) | B12: 0.2
A13: After-Tax Cost of Debt (Kd * (1 - t)) | B13: =B11*(1-B12)
A14: Current Share Price ($) | B14: ='DCF Valuation'!B7
A15: Diluted Shares Outstanding (M) | B15: ='DCF Valuation'!B8
A16: Market Capitalization ($M) | B16: =B14*B15
A17: Total Debt ($M) | B17: 47600
A18: Cash and Short-Term Investments ($M) | B18: 76843
A19: Net Debt ($M) [Net Cash if negative] | B19: =B17-B18
A20: Total Capitalization ($M) | B20: =B16+B17
A22: III. WACC CALCULATION SUMMARY
A23: Component | B23: Market Value ($M) | C23: Capital Weight (%) | D23: Cost of Capital (%) | E23: Weighted Contribution (%)
A24: Common Equity (Market Cap) | B24: =B16 | C24: =B24/$B$20 | D24: =B8 | E24: =C24*D24
A25: Total Debt | B25: =B17 | C25: =B25/$B$20 | D25: =B13 | E25: =C25*D25
A26: Total Capitalization / Base WACC | B26: =B20 | C26: =SUM(C24:C25) | D26: - | E26: =SUM(E24:E25)
