Workbook

Sheet DCF
A1: Maison Solutions Inc. (NASDAQ: MSS) - Institutional DCF Valuation Model
A2: Valuation Date: August 2026 | Currency: USD in Millions (except per-share data) | Fiscal Year Ends April 30
A4: 1. MODEL CONTROL & SCENARIO SELECTOR
A5: Scenario Selector (1 = Bear, 2 = Base, 3 = Bull): | B5: 2
A6: Active Scenario Name: | B6: =IF(B5=1,"Bear Case (Conservative)",IF(B5=2,"Base Case (Consensus / Target)","Bull Case (Optimistic)"))
A8: 2. MARKET DATA & CAPITAL STRUCTURE INPUTS
A9: Current Share Price ($) | B9: 1.46
A10: Diluted Shares Outstanding (M) | B10: 2.53
A11: Current Market Capitalization ($M) | B11: =B9*B10
A12: Cash & Cash Equivalents ($M) | B12: 1.52
A13: Total Debt ($M) | B13: 47.6
A14: Net Debt ($M) | B14: =B13-B12
A15: Effective Corporate Tax Rate (%) | B15: 0.21
A17: 3. SCENARIO ASSUMPTIONS SCHEDULE
A18: Assumption / Parameter | C18: FY2024A | D18: FY2025A | E18: FY2026E | F18: FY2027E | G18: FY2028E | H18: FY2029E | I18: FY2030E | J18: Terminal
A19: BEAR CASE ASSUMPTIONS (1)
A20: Revenue Growth YoY (%) | E20: 0.04 | F20: 0.035 | G20: 0.03 | H20: 0.025 | I20: 0.025 | J20: 0.02
A21: EBIT Margin (%) | E21: 0 | F21: 0.005 | G21: 0.008 | H21: 0.01 | I21: 0.01
A22: Discount Rate / WACC (%) | E22: 0.11
A23: Terminal Growth Rate (%) | E23: 0.02
A24: BASE CASE ASSUMPTIONS (2)
A25: Revenue Growth YoY (%) | E25: 0.08 | F25: 0.07 | G25: 0.06 | H25: 0.05 | I25: 0.04 | J25: 0.025
A26: EBIT Margin (%) | E26: 0.008 | F26: 0.015 | G26: 0.02 | H26: 0.025 | I26: 0.028
A27: Discount Rate / WACC (%) | E27: 0.1
A28: Terminal Growth Rate (%) | E28: 0.025
A29: BULL CASE ASSUMPTIONS (3)
A30: Revenue Growth YoY (%) | E30: 0.14 | F30: 0.12 | G30: 0.1 | H30: 0.08 | I30: 0.06 | J30: 0.03
A31: EBIT Margin (%) | E31: 0.015 | F31: 0.025 | G31: 0.032 | H31: 0.038 | I31: 0.042
A32: Discount Rate / WACC (%) | E32: 0.09
A33: Terminal Growth Rate (%) | E33: 0.03
A35: 4. ACTIVE SCENARIO CONSOLIDATED DRIVERS
A36: Consolidated Driver | C36: FY2024A | D36: FY2025A | E36: FY2026E | F36: FY2027E | G36: FY2028E | H36: FY2029E | I36: FY2030E | J36: Terminal
A37: Selected Revenue Growth (%) | E37: =CHOOSE($B$5,E20,E25,E30) | F37: =CHOOSE($B$5,F20,F25,F30) | G37: =CHOOSE($B$5,G20,G25,G30) | H37: =CHOOSE($B$5,H20,H25,H30) | I37: =CHOOSE($B$5,I20,I25,I30) | J37: =CHOOSE($B$5,J20,J25,J30)
A38: Selected EBIT Margin (%) | E38: =CHOOSE($B$5,E21,E26,E31) | F38: =CHOOSE($B$5,F21,F26,F31) | G38: =CHOOSE($B$5,G21,G26,G31) | H38: =CHOOSE($B$5,H21,H26,H31) | I38: =CHOOSE($B$5,I21,I26,I31)
A39: Selected Discount Rate / WACC (%) | E39: =CHOOSE($B$5,E22,E27,E32)
A40: Selected Terminal Growth Rate (%) | E40: =CHOOSE($B$5,E23,E28,E33)
A41: D&A (% of Revenue) | E41: 0.009 | F41: 0.009 | G41: 0.009 | H41: 0.009 | I41: 0.009
A42: CapEx (% of Revenue) | E42: 0.012 | F42: 0.012 | G42: 0.012 | H42: 0.012 | I42: 0.012
A43: ΔNWC (% of ΔRevenue) | E43: 0.01 | F43: 0.01 | G43: 0.01 | H43: 0.01 | I43: 0.01
A45: 5. FINANCIAL STATEMENT & FREE CASH FLOW PROJECTION SCHEDULE ($M)
A46: Line Item ($M) | C46: FY2024A | D46: FY2025A | E46: FY2026E | F46: FY2027E | G46: FY2028E | H46: FY2029E | I46: FY2030E | J46: Terminal
A47: Revenue | C47: 58 | D47: 124.2 | E47: =D47*(1+E37) | F47: =E47*(1+F37) | G47: =F47*(1+G37) | H47: =G47*(1+H37) | I47: =H47*(1+I37) | J47: =I47*(1+E40)
A48: Revenue Growth YoY (%) | C48: - | D48: =(D47-C47)/C47 | E48: =(E47-D47)/D47 | F48: =(F47-E47)/E47 | G48: =(G47-F47)/F47 | H48: =(H47-G47)/G47 | I48: =(I47-H47)/H47 | J48: =E40
A49: Gross Profit | C49: 11.62 | D49: 26.34 | E49: =E47*0.215 | F49: =F47*0.218 | G49: =G47*0.220 | H49: =H47*0.222 | I49: =I47*0.225 | J49: =J47*0.225
A50: Gross Margin (%) | C50: =C49/C47 | D50: =D49/D47 | E50: =E49/E47 | F50: =F49/F47 | G50: =G49/G47 | H50: =H49/H47 | I50: =I49/I47 | J50: =J49/J47
A51: Operating Income / EBIT | C51: -2.7 | D51: -1.27 | E51: =E47*E38 | F51: =F47*F38 | G51: =G47*G38 | H51: =H47*H38 | I51: =I47*I38 | J51: =J47*I38
A52: EBIT Margin (%) | C52: =C51/C47 | D52: =D51/D47 | E52: =E51/E47 | F52: =F51/F47 | G52: =G51/G47 | H52: =H51/H47 | I52: =I51/I47 | J52: =J51/J47
A53: (-) Cash Taxes (EBIT * 21%) | E53: =E51*$B$15 | F53: =F51*$B$15 | G53: =G51*$B$15 | H53: =H51*$B$15 | I53: =I51*$B$15 | J53: =J51*$B$15
A54: Net Operating Profit After Tax (NOPAT) | E54: =E51-E53 | F54: =F51-F53 | G54: =G51-G53 | H54: =H51-H53 | I54: =I51-I53 | J54: =J51-J53
A55: (+) Depreciation & Amortization | C55: 0.46 | D55: 1.04 | E55: =E47*E41 | F55: =F47*F41 | G55: =G47*G41 | H55: =H47*H41 | I55: =I47*I41 | J55: =J47*I41
A56: (-) Capital Expenditures (CapEx) | E56: =E47*E42 | F56: =F47*F42 | G56: =G47*G42 | H56: =H47*H42 | I56: =I47*I42 | J56: =J47*I42
A57: (-) Change in Net Working Capital (ΔNWC) | E57: =(E47-D47)*E43 | F57: =(F47-E47)*F43 | G57: =(G47-F47)*G43 | H57: =(H47-G47)*H43 | I57: =(I47-H47)*I43 | J57: =(J47-I47)*I43
A58: Unlevered Free Cash Flow (UFCF) | E58: =E54+E55-E56-E57 | F58: =F54+F55-F56-F57 | G58: =G54+G55-G56-G57 | H58: =H54+H55-H56-H57 | I58: =I54+I55-I56-I57 | J58: =J54+J55-J56-J57
A60: 6. DISCOUNTING & CASH FLOW PRESENT VALUE ($M)
A61: Discount Period (Mid-Year Convention) | E61: 0.5 | F61: 1.5 | G61: 2.5 | H61: 3.5 | I61: 4.5 | J61: 5
A62: Discount Factor (1 / (1 + WACC)^t) | E62: =1/(1+$E$39)^E61 | F62: =1/(1+$E$39)^F61 | G62: =1/(1+$E$39)^G61 | H62: =1/(1+$E$39)^H61 | I62: =1/(1+$E$39)^I61 | J62: =1/(1+$E$39)^J61
A63: Present Value of Projected FCF ($M) | E63: =E58*E62 | F63: =F58*F62 | G63: =G58*G62 | H63: =H58*H62 | I63: =I58*I62 | J63: -
A65: 7. VALUATION SUMMARY & PER SHARE EQUITY VALUE BRIDGE
A66: Cumulative PV of Explicit FCFs (FY26E - FY30E) | B66: =SUM(E63:I63)
A67: Terminal Year Unlevered Free Cash Flow (FCF_n+1) | B67: =I58*(1+E40)
A68: Terminal Value at Year 5 (TV_5 = FCF_n+1 / (WACC - g)) | B68: =B67/($E$39-$E$40)
A69: Present Value of Terminal Value (PV of TV) | B69: =B68*J62
A70: Enterprise Value (EV) | B70: =B66+B69
A71: Terminal Value as % of Enterprise Value | B71: =B69/B70
A72: (-) Total Debt | B72: =$B$13
A73: (+) Cash and Cash Equivalents | B73: =$B$12
A74: (-) Net Debt (Total Debt - Cash) | B74: =B72-B73
A75: Implied Equity Value (EV - Net Debt) | B75: =B70-B74
A76: Diluted Shares Outstanding (M) | B76: =$B$10
A77: Implied Share Price ($ / share) | B77: =B75/B76
A78: Current Market Share Price ($) | B78: =$B$9
A79: Implied Upside / (Downside) vs Current Price (%) | B79: =(B77/B78)-1
A81: 8. SENSITIVITY ANALYSIS 1: WACC VS. TERMINAL GROWTH RATE (Implied Share Price $)
A82: WACC \ Term g | C82: 0.015 | D82: 0.02 | E82: 0.025 | F82: 0.03 | G82: 0.035
A83: 0.09 | C83: =((E$63*( (1+$E$39)^0.5 / (1+$A83)^0.5 ) + F$63*( (1+$E$39)^1.5 / (1+$A83)^1.5 ) + G$63*( (1+$E$39)^2.5 / (1+$A83)^2.5 ) + H$63*( (1+$E$39)^3.5 / (1+$A83)^3.5 ) + I$63*( (1+$E$39)^4.5 / (1+$A83)^4.5 )) + ($B$67/($A83-C$82))/(1+$A83)^5.0 - $B$74)/$B$76 | D83: =((E$63*( (1+$E$39)^0.5 / (1+$A83)^0.5 ) + F$63*( (1+$E$39)^1.5 / (1+$A83)^1.5 ) + G$63*( (1+$E$39)^2.5 / (1+$A83)^2.5 ) + H$63*( (1+$E$39)^3.5 / (1+$A83)^3.5 ) + I$63*( (1+$E$39)^4.5 / (1+$A83)^4.5 )) + ($B$67/($A83-D$82))/(1+$A83)^5.0 - $B$74)/$B$76 | E83: =((E$63*( (1+$E$39)^0.5 / (1+$A83)^0.5 ) + F$63*( (1+$E$39)^1.5 / (1+$A83)^1.5 ) + G$63*( (1+$E$39)^2.5 / (1+$A83)^2.5 ) + H$63*( (1+$E$39)^3.5 / (1+$A83)^3.5 ) + I$63*( (1+$E$39)^4.5 / (1+$A83)^4.5 )) + ($B$67/($A83-E$82))/(1+$A83)^5.0 - $B$74)/$B$76 | F83: =((E$63*( (1+$E$39)^0.5 / (1+$A83)^0.5 ) + F$63*( (1+$E$39)^1.5 / (1+$A83)^1.5 ) + G$63*( (1+$E$39)^2.5 / (1+$A83)^2.5 ) + H$63*( (1+$E$39)^3.5 / (1+$A83)^3.5 ) + I$63*( (1+$E$39)^4.5 / (1+$A83)^4.5 )) + ($B$67/($A83-F$82))/(1+$A83)^5.0 - $B$74)/$B$76 | G83: =((E$63*( (1+$E$39)^0.5 / (1+$A83)^0.5 ) + F$63*( (1+$E$39)^1.5 / (1+$A83)^1.5 ) + G$63*( (1+$E$39)^2.5 / (1+$A83)^2.5 ) + H$63*( (1+$E$39)^3.5 / (1+$A83)^3.5 ) + I$63*( (1+$E$39)^4.5 / (1+$A83)^4.5 )) + ($B$67/($A83-G$82))/(1+$A83)^5.0 - $B$74)/$B$76
A84: 0.095 | C84: =((E$63*( (1+$E$39)^0.5 / (1+$A84)^0.5 ) + F$63*( (1+$E$39)^1.5 / (1+$A84)^1.5 ) + G$63*( (1+$E$39)^2.5 / (1+$A84)^2.5 ) + H$63*( (1+$E$39)^3.5 / (1+$A84)^3.5 ) + I$63*( (1+$E$39)^4.5 / (1+$A84)^4.5 )) + ($B$67/($A84-C$82))/(1+$A84)^5.0 - $B$74)/$B$76 | D84: =((E$63*( (1+$E$39)^0.5 / (1+$A84)^0.5 ) + F$63*( (1+$E$39)^1.5 / (1+$A84)^1.5 ) + G$63*( (1+$E$39)^2.5 / (1+$A84)^2.5 ) + H$63*( (1+$E$39)^3.5 / (1+$A84)^3.5 ) + I$63*( (1+$E$39)^4.5 / (1+$A84)^4.5 )) + ($B$67/($A84-D$82))/(1+$A84)^5.0 - $B$74)/$B$76 | E84: =((E$63*( (1+$E$39)^0.5 / (1+$A84)^0.5 ) + F$63*( (1+$E$39)^1.5 / (1+$A84)^1.5 ) + G$63*( (1+$E$39)^2.5 / (1+$A84)^2.5 ) + H$63*( (1+$E$39)^3.5 / (1+$A84)^3.5 ) + I$63*( (1+$E$39)^4.5 / (1+$A84)^4.5 )) + ($B$67/($A84-E$82))/(1+$A84)^5.0 - $B$74)/$B$76 | F84: =((E$63*( (1+$E$39)^0.5 / (1+$A84)^0.5 ) + F$63*( (1+$E$39)^1.5 / (1+$A84)^1.5 ) + G$63*( (1+$E$39)^2.5 / (1+$A84)^2.5 ) + H$63*( (1+$E$39)^3.5 / (1+$A84)^3.5 ) + I$63*( (1+$E$39)^4.5 / (1+$A84)^4.5 )) + ($B$67/($A84-F$82))/(1+$A84)^5.0 - $B$74)/$B$76 | G84: =((E$63*( (1+$E$39)^0.5 / (1+$A84)^0.5 ) + F$63*( (1+$E$39)^1.5 / (1+$A84)^1.5 ) + G$63*( (1+$E$39)^2.5 / (1+$A84)^2.5 ) + H$63*( (1+$E$39)^3.5 / (1+$A84)^3.5 ) + I$63*( (1+$E$39)^4.5 / (1+$A84)^4.5 )) + ($B$67/($A84-G$82))/(1+$A84)^5.0 - $B$74)/$B$76
A85: 0.1 | C85: =((E$63*( (1+$E$39)^0.5 / (1+$A85)^0.5 ) + F$63*( (1+$E$39)^1.5 / (1+$A85)^1.5 ) + G$63*( (1+$E$39)^2.5 / (1+$A85)^2.5 ) + H$63*( (1+$E$39)^3.5 / (1+$A85)^3.5 ) + I$63*( (1+$E$39)^4.5 / (1+$A85)^4.5 )) + ($B$67/($A85-C$82))/(1+$A85)^5.0 - $B$74)/$B$76 | D85: =((E$63*( (1+$E$39)^0.5 / (1+$A85)^0.5 ) + F$63*( (1+$E$39)^1.5 / (1+$A85)^1.5 ) + G$63*( (1+$E$39)^2.5 / (1+$A85)^2.5 ) + H$63*( (1+$E$39)^3.5 / (1+$A85)^3.5 ) + I$63*( (1+$E$39)^4.5 / (1+$A85)^4.5 )) + ($B$67/($A85-D$82))/(1+$A85)^5.0 - $B$74)/$B$76 | E85: =((E$63*( (1+$E$39)^0.5 / (1+$A85)^0.5 ) + F$63*( (1+$E$39)^1.5 / (1+$A85)^1.5 ) + G$63*( (1+$E$39)^2.5 / (1+$A85)^2.5 ) + H$63*( (1+$E$39)^3.5 / (1+$A85)^3.5 ) + I$63*( (1+$E$39)^4.5 / (1+$A85)^4.5 )) + ($B$67/($A85-E$82))/(1+$A85)^5.0 - $B$74)/$B$76 | F85: =((E$63*( (1+$E$39)^0.5 / (1+$A85)^0.5 ) + F$63*( (1+$E$39)^1.5 / (1+$A85)^1.5 ) + G$63*( (1+$E$39)^2.5 / (1+$A85)^2.5 ) + H$63*( (1+$E$39)^3.5 / (1+$A85)^3.5 ) + I$63*( (1+$E$39)^4.5 / (1+$A85)^4.5 )) + ($B$67/($A85-F$82))/(1+$A85)^5.0 - $B$74)/$B$76 | G85: =((E$63*( (1+$E$39)^0.5 / (1+$A85)^0.5 ) + F$63*( (1+$E$39)^1.5 / (1+$A85)^1.5 ) + G$63*( (1+$E$39)^2.5 / (1+$A85)^2.5 ) + H$63*( (1+$E$39)^3.5 / (1+$A85)^3.5 ) + I$63*( (1+$E$39)^4.5 / (1+$A85)^4.5 )) + ($B$67/($A85-G$82))/(1+$A85)^5.0 - $B$74)/$B$76
A86: 0.105 | C86: =((E$63*( (1+$E$39)^0.5 / (1+$A86)^0.5 ) + F$63*( (1+$E$39)^1.5 / (1+$A86)^1.5 ) + G$63*( (1+$E$39)^2.5 / (1+$A86)^2.5 ) + H$63*( (1+$E$39)^3.5 / (1+$A86)^3.5 ) + I$63*( (1+$E$39)^4.5 / (1+$A86)^4.5 )) + ($B$67/($A86-C$82))/(1+$A86)^5.0 - $B$74)/$B$76 | D86: =((E$63*( (1+$E$39)^0.5 / (1+$A86)^0.5 ) + F$63*( (1+$E$39)^1.5 / (1+$A86)^1.5 ) + G$63*( (1+$E$39)^2.5 / (1+$A86)^2.5 ) + H$63*( (1+$E$39)^3.5 / (1+$A86)^3.5 ) + I$63*( (1+$E$39)^4.5 / (1+$A86)^4.5 )) + ($B$67/($A86-D$82))/(1+$A86)^5.0 - $B$74)/$B$76 | E86: =((E$63*( (1+$E$39)^0.5 / (1+$A86)^0.5 ) + F$63*( (1+$E$39)^1.5 / (1+$A86)^1.5 ) + G$63*( (1+$E$39)^2.5 / (1+$A86)^2.5 ) + H$63*( (1+$E$39)^3.5 / (1+$A86)^3.5 ) + I$63*( (1+$E$39)^4.5 / (1+$A86)^4.5 )) + ($B$67/($A86-E$82))/(1+$A86)^5.0 - $B$74)/$B$76 | F86: =((E$63*( (1+$E$39)^0.5 / (1+$A86)^0.5 ) + F$63*( (1+$E$39)^1.5 / (1+$A86)^1.5 ) + G$63*( (1+$E$39)^2.5 / (1+$A86)^2.5 ) + H$63*( (1+$E$39)^3.5 / (1+$A86)^3.5 ) + I$63*( (1+$E$39)^4.5 / (1+$A86)^4.5 )) + ($B$67/($A86-F$82))/(1+$A86)^5.0 - $B$74)/$B$76 | G86: =((E$63*( (1+$E$39)^0.5 / (1+$A86)^0.5 ) + F$63*( (1+$E$39)^1.5 / (1+$A86)^1.5 ) + G$63*( (1+$E$39)^2.5 / (1+$A86)^2.5 ) + H$63*( (1+$E$39)^3.5 / (1+$A86)^3.5 ) + I$63*( (1+$E$39)^4.5 / (1+$A86)^4.5 )) + ($B$67/($A86-G$82))/(1+$A86)^5.0 - $B$74)/$B$76
A87: 0.11 | C87: =((E$63*( (1+$E$39)^0.5 / (1+$A87)^0.5 ) + F$63*( (1+$E$39)^1.5 / (1+$A87)^1.5 ) + G$63*( (1+$E$39)^2.5 / (1+$A87)^2.5 ) + H$63*( (1+$E$39)^3.5 / (1+$A87)^3.5 ) + I$63*( (1+$E$39)^4.5 / (1+$A87)^4.5 )) + ($B$67/($A87-C$82))/(1+$A87)^5.0 - $B$74)/$B$76 | D87: =((E$63*( (1+$E$39)^0.5 / (1+$A87)^0.5 ) + F$63*( (1+$E$39)^1.5 / (1+$A87)^1.5 ) + G$63*( (1+$E$39)^2.5 / (1+$A87)^2.5 ) + H$63*( (1+$E$39)^3.5 / (1+$A87)^3.5 ) + I$63*( (1+$E$39)^4.5 / (1+$A87)^4.5 )) + ($B$67/($A87-D$82))/(1+$A87)^5.0 - $B$74)/$B$76 | E87: =((E$63*( (1+$E$39)^0.5 / (1+$A87)^0.5 ) + F$63*( (1+$E$39)^1.5 / (1+$A87)^1.5 ) + G$63*( (1+$E$39)^2.5 / (1+$A87)^2.5 ) + H$63*( (1+$E$39)^3.5 / (1+$A87)^3.5 ) + I$63*( (1+$E$39)^4.5 / (1+$A87)^4.5 )) + ($B$67/($A87-E$82))/(1+$A87)^5.0 - $B$74)/$B$76 | F87: =((E$63*( (1+$E$39)^0.5 / (1+$A87)^0.5 ) + F$63*( (1+$E$39)^1.5 / (1+$A87)^1.5 ) + G$63*( (1+$E$39)^2.5 / (1+$A87)^2.5 ) + H$63*( (1+$E$39)^3.5 / (1+$A87)^3.5 ) + I$63*( (1+$E$39)^4.5 / (1+$A87)^4.5 )) + ($B$67/($A87-F$82))/(1+$A87)^5.0 - $B$74)/$B$76 | G87: =((E$63*( (1+$E$39)^0.5 / (1+$A87)^0.5 ) + F$63*( (1+$E$39)^1.5 / (1+$A87)^1.5 ) + G$63*( (1+$E$39)^2.5 / (1+$A87)^2.5 ) + H$63*( (1+$E$39)^3.5 / (1+$A87)^3.5 ) + I$63*( (1+$E$39)^4.5 / (1+$A87)^4.5 )) + ($B$67/($A87-G$82))/(1+$A87)^5.0 - $B$74)/$B$76
A90: 9. SENSITIVITY ANALYSIS 2: REVENUE GROWTH ADJUSTMENT VS. EBIT MARGIN (Implied Share Price $)
A91: EBIT Margin \ Rev Growth | C91: -0.02 | D91: -0.01 | E91: 0 | F91: 0.01 | G91: 0.02
A92: 0.018 | C92: =((E$63*(1+C$91)*($A92/$I$38) + F$63*(1+C$91)*($A92/$I$38) + G$63*(1+C$91)*($A92/$I$38) + H$63*(1+C$91)*($A92/$I$38) + I$63*(1+C$91)*($A92/$I$38)) + ($B$69*(1+C$91)*($A92/$I$38)) - $B$74)/$B$76 | D92: =((E$63*(1+D$91)*($A92/$I$38) + F$63*(1+D$91)*($A92/$I$38) + G$63*(1+D$91)*($A92/$I$38) + H$63*(1+D$91)*($A92/$I$38) + I$63*(1+D$91)*($A92/$I$38)) + ($B$69*(1+D$91)*($A92/$I$38)) - $B$74)/$B$76 | E92: =((E$63*(1+E$91)*($A92/$I$38) + F$63*(1+E$91)*($A92/$I$38) + G$63*(1+E$91)*($A92/$I$38) + H$63*(1+E$91)*($A92/$I$38) + I$63*(1+E$91)*($A92/$I$38)) + ($B$69*(1+E$91)*($A92/$I$38)) - $B$74)/$B$76 | F92: =((E$63*(1+F$91)*($A92/$I$38) + F$63*(1+F$91)*($A92/$I$38) + G$63*(1+F$91)*($A92/$I$38) + H$63*(1+F$91)*($A92/$I$38) + I$63*(1+F$91)*($A92/$I$38)) + ($B$69*(1+F$91)*($A92/$I$38)) - $B$74)/$B$76 | G92: =((E$63*(1+G$91)*($A92/$I$38) + F$63*(1+G$91)*($A92/$I$38) + G$63*(1+G$91)*($A92/$I$38) + H$63*(1+G$91)*($A92/$I$38) + I$63*(1+G$91)*($A92/$I$38)) + ($B$69*(1+G$91)*($A92/$I$38)) - $B$74)/$B$76
A93: 0.023 | C93: =((E$63*(1+C$91)*($A93/$I$38) + F$63*(1+C$91)*($A93/$I$38) + G$63*(1+C$91)*($A93/$I$38) + H$63*(1+C$91)*($A93/$I$38) + I$63*(1+C$91)*($A93/$I$38)) + ($B$69*(1+C$91)*($A93/$I$38)) - $B$74)/$B$76 | D93: =((E$63*(1+D$91)*($A93/$I$38) + F$63*(1+D$91)*($A93/$I$38) + G$63*(1+D$91)*($A93/$I$38) + H$63*(1+D$91)*($A93/$I$38) + I$63*(1+D$91)*($A93/$I$38)) + ($B$69*(1+D$91)*($A93/$I$38)) - $B$74)/$B$76 | E93: =((E$63*(1+E$91)*($A93/$I$38) + F$63*(1+E$91)*($A93/$I$38) + G$63*(1+E$91)*($A93/$I$38) + H$63*(1+E$91)*($A93/$I$38) + I$63*(1+E$91)*($A93/$I$38)) + ($B$69*(1+E$91)*($A93/$I$38)) - $B$74)/$B$76 | F93: =((E$63*(1+F$91)*($A93/$I$38) + F$63*(1+F$91)*($A93/$I$38) + G$63*(1+F$91)*($A93/$I$38) + H$63*(1+F$91)*($A93/$I$38) + I$63*(1+F$91)*($A93/$I$38)) + ($B$69*(1+F$91)*($A93/$I$38)) - $B$74)/$B$76 | G93: =((E$63*(1+G$91)*($A93/$I$38) + F$63*(1+G$91)*($A93/$I$38) + G$63*(1+G$91)*($A93/$I$38) + H$63*(1+G$91)*($A93/$I$38) + I$63*(1+G$91)*($A93/$I$38)) + ($B$69*(1+G$91)*($A93/$I$38)) - $B$74)/$B$76
A94: 0.028 | C94: =((E$63*(1+C$91)*($A94/$I$38) + F$63*(1+C$91)*($A94/$I$38) + G$63*(1+C$91)*($A94/$I$38) + H$63*(1+C$91)*($A94/$I$38) + I$63*(1+C$91)*($A94/$I$38)) + ($B$69*(1+C$91)*($A94/$I$38)) - $B$74)/$B$76 | D94: =((E$63*(1+D$91)*($A94/$I$38) + F$63*(1+D$91)*($A94/$I$38) + G$63*(1+D$91)*($A94/$I$38) + H$63*(1+D$91)*($A94/$I$38) + I$63*(1+D$91)*($A94/$I$38)) + ($B$69*(1+D$91)*($A94/$I$38)) - $B$74)/$B$76 | E94: =((E$63*(1+E$91)*($A94/$I$38) + F$63*(1+E$91)*($A94/$I$38) + G$63*(1+E$91)*($A94/$I$38) + H$63*(1+E$91)*($A94/$I$38) + I$63*(1+E$91)*($A94/$I$38)) + ($B$69*(1+E$91)*($A94/$I$38)) - $B$74)/$B$76 | F94: =((E$63*(1+F$91)*($A94/$I$38) + F$63*(1+F$91)*($A94/$I$38) + G$63*(1+F$91)*($A94/$I$38) + H$63*(1+F$91)*($A94/$I$38) + I$63*(1+F$91)*($A94/$I$38)) + ($B$69*(1+F$91)*($A94/$I$38)) - $B$74)/$B$76 | G94: =((E$63*(1+G$91)*($A94/$I$38) + F$63*(1+G$91)*($A94/$I$38) + G$63*(1+G$91)*($A94/$I$38) + H$63*(1+G$91)*($A94/$I$38) + I$63*(1+G$91)*($A94/$I$38)) + ($B$69*(1+G$91)*($A94/$I$38)) - $B$74)/$B$76
A95: 0.033 | C95: =((E$63*(1+C$91)*($A95/$I$38) + F$63*(1+C$91)*($A95/$I$38) + G$63*(1+C$91)*($A95/$I$38) + H$63*(1+C$91)*($A95/$I$38) + I$63*(1+C$91)*($A95/$I$38)) + ($B$69*(1+C$91)*($A95/$I$38)) - $B$74)/$B$76 | D95: =((E$63*(1+D$91)*($A95/$I$38) + F$63*(1+D$91)*($A95/$I$38) + G$63*(1+D$91)*($A95/$I$38) + H$63*(1+D$91)*($A95/$I$38) + I$63*(1+D$91)*($A95/$I$38)) + ($B$69*(1+D$91)*($A95/$I$38)) - $B$74)/$B$76 | E95: =((E$63*(1+E$91)*($A95/$I$38) + F$63*(1+E$91)*($A95/$I$38) + G$63*(1+E$91)*($A95/$I$38) + H$63*(1+E$91)*($A95/$I$38) + I$63*(1+E$91)*($A95/$I$38)) + ($B$69*(1+E$91)*($A95/$I$38)) - $B$74)/$B$76 | F95: =((E$63*(1+F$91)*($A95/$I$38) + F$63*(1+F$91)*($A95/$I$38) + G$63*(1+F$91)*($A95/$I$38) + H$63*(1+F$91)*($A95/$I$38) + I$63*(1+F$91)*($A95/$I$38)) + ($B$69*(1+F$91)*($A95/$I$38)) - $B$74)/$B$76 | G95: =((E$63*(1+G$91)*($A95/$I$38) + F$63*(1+G$91)*($A95/$I$38) + G$63*(1+G$91)*($A95/$I$38) + H$63*(1+G$91)*($A95/$I$38) + I$63*(1+G$91)*($A95/$I$38)) + ($B$69*(1+G$91)*($A95/$I$38)) - $B$74)/$B$76
A96: 0.038 | C96: =((E$63*(1+C$91)*($A96/$I$38) + F$63*(1+C$91)*($A96/$I$38) + G$63*(1+C$91)*($A96/$I$38) + H$63*(1+C$91)*($A96/$I$38) + I$63*(1+C$91)*($A96/$I$38)) + ($B$69*(1+C$91)*($A96/$I$38)) - $B$74)/$B$76 | D96: =((E$63*(1+D$91)*($A96/$I$38) + F$63*(1+D$91)*($A96/$I$38) + G$63*(1+D$91)*($A96/$I$38) + H$63*(1+D$91)*($A96/$I$38) + I$63*(1+D$91)*($A96/$I$38)) + ($B$69*(1+D$91)*($A96/$I$38)) - $B$74)/$B$76 | E96: =((E$63*(1+E$91)*($A96/$I$38) + F$63*(1+E$91)*($A96/$I$38) + G$63*(1+E$91)*($A96/$I$38) + H$63*(1+E$91)*($A96/$I$38) + I$63*(1+E$91)*($A96/$I$38)) + ($B$69*(1+E$91)*($A96/$I$38)) - $B$74)/$B$76 | F96: =((E$63*(1+F$91)*($A96/$I$38) + F$63*(1+F$91)*($A96/$I$38) + G$63*(1+F$91)*($A96/$I$38) + H$63*(1+F$91)*($A96/$I$38) + I$63*(1+F$91)*($A96/$I$38)) + ($B$69*(1+F$91)*($A96/$I$38)) - $B$74)/$B$76 | G96: =((E$63*(1+G$91)*($A96/$I$38) + F$63*(1+G$91)*($A96/$I$38) + G$63*(1+G$91)*($A96/$I$38) + H$63*(1+G$91)*($A96/$I$38) + I$63*(1+G$91)*($A96/$I$38)) + ($B$69*(1+G$91)*($A96/$I$38)) - $B$74)/$B$76
A99: 10. SENSITIVITY ANALYSIS 3: BETA VS. RISK-FREE RATE (Implied Share Price $)
A100: Beta \ Risk-Free Rate | C100: 0.037 | D100: 0.042 | E100: 0.047 | F100: 0.052 | G100: 0.057
A101: 1 | C101: =((E$63*( (1+$E$39)^0.5 / (1+((C$100 + $A101*0.055 + 0.02)*0.5 + 0.0711*0.5))^0.5 ) + F$63*( (1+$E$39)^1.5 / (1+((C$100 + $A101*0.055 + 0.02)*0.5 + 0.0711*0.5))^1.5 ) + G$63*( (1+$E$39)^2.5 / (1+((C$100 + $A101*0.055 + 0.02)*0.5 + 0.0711*0.5))^2.5 ) + H$63*( (1+$E$39)^3.5 / (1+((C$100 + $A101*0.055 + 0.02)*0.5 + 0.0711*0.5))^3.5 ) + I$63*( (1+$E$39)^4.5 / (1+((C$100 + $A101*0.055 + 0.02)*0.5 + 0.0711*0.5))^4.5 )) + ($B$67/(((C$100 + $A101*0.055 + 0.02)*0.5 + 0.0711*0.5)-$E$40))/(1+((C$100 + $A101*0.055 + 0.02)*0.5 + 0.0711*0.5))^5.0 - $B$74)/$B$76 | D101: =((E$63*( (1+$E$39)^0.5 / (1+((D$100 + $A101*0.055 + 0.02)*0.5 + 0.0711*0.5))^0.5 ) + F$63*( (1+$E$39)^1.5 / (1+((D$100 + $A101*0.055 + 0.02)*0.5 + 0.0711*0.5))^1.5 ) + G$63*( (1+$E$39)^2.5 / (1+((D$100 + $A101*0.055 + 0.02)*0.5 + 0.0711*0.5))^2.5 ) + H$63*( (1+$E$39)^3.5 / (1+((D$100 + $A101*0.055 + 0.02)*0.5 + 0.0711*0.5))^3.5 ) + I$63*( (1+$E$39)^4.5 / (1+((D$100 + $A101*0.055 + 0.02)*0.5 + 0.0711*0.5))^4.5 )) + ($B$67/(((D$100 + $A101*0.055 + 0.02)*0.5 + 0.0711*0.5)-$E$40))/(1+((D$100 + $A101*0.055 + 0.02)*0.5 + 0.0711*0.5))^5.0 - $B$74)/$B$76 | E101: =((E$63*( (1+$E$39)^0.5 / (1+((E$100 + $A101*0.055 + 0.02)*0.5 + 0.0711*0.5))^0.5 ) + F$63*( (1+$E$39)^1.5 / (1+((E$100 + $A101*0.055 + 0.02)*0.5 + 0.0711*0.5))^1.5 ) + G$63*( (1+$E$39)^2.5 / (1+((E$100 + $A101*0.055 + 0.02)*0.5 + 0.0711*0.5))^2.5 ) + H$63*( (1+$E$39)^3.5 / (1+((E$100 + $A101*0.055 + 0.02)*0.5 + 0.0711*0.5))^3.5 ) + I$63*( (1+$E$39)^4.5 / (1+((E$100 + $A101*0.055 + 0.02)*0.5 + 0.0711*0.5))^4.5 )) + ($B$67/(((E$100 + $A101*0.055 + 0.02)*0.5 + 0.0711*0.5)-$E$40))/(1+((E$100 + $A101*0.055 + 0.02)*0.5 + 0.0711*0.5))^5.0 - $B$74)/$B$76 | F101: =((E$63*( (1+$E$39)^0.5 / (1+((F$100 + $A101*0.055 + 0.02)*0.5 + 0.0711*0.5))^0.5 ) + F$63*( (1+$E$39)^1.5 / (1+((F$100 + $A101*0.055 + 0.02)*0.5 + 0.0711*0.5))^1.5 ) + G$63*( (1+$E$39)^2.5 / (1+((F$100 + $A101*0.055 + 0.02)*0.5 + 0.0711*0.5))^2.5 ) + H$63*( (1+$E$39)^3.5 / (1+((F$100 + $A101*0.055 + 0.02)*0.5 + 0.0711*0.5))^3.5 ) + I$63*( (1+$E$39)^4.5 / (1+((F$100 + $A101*0.055 + 0.02)*0.5 + 0.0711*0.5))^4.5 )) + ($B$67/(((F$100 + $A101*0.055 + 0.02)*0.5 + 0.0711*0.5)-$E$40))/(1+((F$100 + $A101*0.055 + 0.02)*0.5 + 0.0711*0.5))^5.0 - $B$74)/$B$76 | G101: =((E$63*( (1+$E$39)^0.5 / (1+((G$100 + $A101*0.055 + 0.02)*0.5 + 0.0711*0.5))^0.5 ) + F$63*( (1+$E$39)^1.5 / (1+((G$100 + $A101*0.055 + 0.02)*0.5 + 0.0711*0.5))^1.5 ) + G$63*( (1+$E$39)^2.5 / (1+((G$100 + $A101*0.055 + 0.02)*0.5 + 0.0711*0.5))^2.5 ) + H$63*( (1+$E$39)^3.5 / (1+((G$100 + $A101*0.055 + 0.02)*0.5 + 0.0711*0.5))^3.5 ) + I$63*( (1+$E$39)^4.5 / (1+((G$100 + $A101*0.055 + 0.02)*0.5 + 0.0711*0.5))^4.5 )) + ($B$67/(((G$100 + $A101*0.055 + 0.02)*0.5 + 0.0711*0.5)-$E$40))/(1+((G$100 + $A101*0.055 + 0.02)*0.5 + 0.0711*0.5))^5.0 - $B$74)/$B$76
A102: 1.1 | C102: =((E$63*( (1+$E$39)^0.5 / (1+((C$100 + $A102*0.055 + 0.02)*0.5 + 0.0711*0.5))^0.5 ) + F$63*( (1+$E$39)^1.5 / (1+((C$100 + $A102*0.055 + 0.02)*0.5 + 0.0711*0.5))^1.5 ) + G$63*( (1+$E$39)^2.5 / (1+((C$100 + $A102*0.055 + 0.02)*0.5 + 0.0711*0.5))^2.5 ) + H$63*( (1+$E$39)^3.5 / (1+((C$100 + $A102*0.055 + 0.02)*0.5 + 0.0711*0.5))^3.5 ) + I$63*( (1+$E$39)^4.5 / (1+((C$100 + $A102*0.055 + 0.02)*0.5 + 0.0711*0.5))^4.5 )) + ($B$67/(((C$100 + $A102*0.055 + 0.02)*0.5 + 0.0711*0.5)-$E$40))/(1+((C$100 + $A102*0.055 + 0.02)*0.5 + 0.0711*0.5))^5.0 - $B$74)/$B$76 | D102: =((E$63*( (1+$E$39)^0.5 / (1+((D$100 + $A102*0.055 + 0.02)*0.5 + 0.0711*0.5))^0.5 ) + F$63*( (1+$E$39)^1.5 / (1+((D$100 + $A102*0.055 + 0.02)*0.5 + 0.0711*0.5))^1.5 ) + G$63*( (1+$E$39)^2.5 / (1+((D$100 + $A102*0.055 + 0.02)*0.5 + 0.0711*0.5))^2.5 ) + H$63*( (1+$E$39)^3.5 / (1+((D$100 + $A102*0.055 + 0.02)*0.5 + 0.0711*0.5))^3.5 ) + I$63*( (1+$E$39)^4.5 / (1+((D$100 + $A102*0.055 + 0.02)*0.5 + 0.0711*0.5))^4.5 )) + ($B$67/(((D$100 + $A102*0.055 + 0.02)*0.5 + 0.0711*0.5)-$E$40))/(1+((D$100 + $A102*0.055 + 0.02)*0.5 + 0.0711*0.5))^5.0 - $B$74)/$B$76 | E102: =((E$63*( (1+$E$39)^0.5 / (1+((E$100 + $A102*0.055 + 0.02)*0.5 + 0.0711*0.5))^0.5 ) + F$63*( (1+$E$39)^1.5 / (1+((E$100 + $A102*0.055 + 0.02)*0.5 + 0.0711*0.5))^1.5 ) + G$63*( (1+$E$39)^2.5 / (1+((E$100 + $A102*0.055 + 0.02)*0.5 + 0.0711*0.5))^2.5 ) + H$63*( (1+$E$39)^3.5 / (1+((E$100 + $A102*0.055 + 0.02)*0.5 + 0.0711*0.5))^3.5 ) + I$63*( (1+$E$39)^4.5 / (1+((E$100 + $A102*0.055 + 0.02)*0.5 + 0.0711*0.5))^4.5 )) + ($B$67/(((E$100 + $A102*0.055 + 0.02)*0.5 + 0.0711*0.5)-$E$40))/(1+((E$100 + $A102*0.055 + 0.02)*0.5 + 0.0711*0.5))^5.0 - $B$74)/$B$76 | F102: =((E$63*( (1+$E$39)^0.5 / (1+((F$100 + $A102*0.055 + 0.02)*0.5 + 0.0711*0.5))^0.5 ) + F$63*( (1+$E$39)^1.5 / (1+((F$100 + $A102*0.055 + 0.02)*0.5 + 0.0711*0.5))^1.5 ) + G$63*( (1+$E$39)^2.5 / (1+((F$100 + $A102*0.055 + 0.02)*0.5 + 0.0711*0.5))^2.5 ) + H$63*( (1+$E$39)^3.5 / (1+((F$100 + $A102*0.055 + 0.02)*0.5 + 0.0711*0.5))^3.5 ) + I$63*( (1+$E$39)^4.5 / (1+((F$100 + $A102*0.055 + 0.02)*0.5 + 0.0711*0.5))^4.5 )) + ($B$67/(((F$100 + $A102*0.055 + 0.02)*0.5 + 0.0711*0.5)-$E$40))/(1+((F$100 + $A102*0.055 + 0.02)*0.5 + 0.0711*0.5))^5.0 - $B$74)/$B$76 | G102: =((E$63*( (1+$E$39)^0.5 / (1+((G$100 + $A102*0.055 + 0.02)*0.5 + 0.0711*0.5))^0.5 ) + F$63*( (1+$E$39)^1.5 / (1+((G$100 + $A102*0.055 + 0.02)*0.5 + 0.0711*0.5))^1.5 ) + G$63*( (1+$E$39)^2.5 / (1+((G$100 + $A102*0.055 + 0.02)*0.5 + 0.0711*0.5))^2.5 ) + H$63*( (1+$E$39)^3.5 / (1+((G$100 + $A102*0.055 + 0.02)*0.5 + 0.0711*0.5))^3.5 ) + I$63*( (1+$E$39)^4.5 / (1+((G$100 + $A102*0.055 + 0.02)*0.5 + 0.0711*0.5))^4.5 )) + ($B$67/(((G$100 + $A102*0.055 + 0.02)*0.5 + 0.0711*0.5)-$E$40))/(1+((G$100 + $A102*0.055 + 0.02)*0.5 + 0.0711*0.5))^5.0 - $B$74)/$B$76
A103: 1.2 | C103: =((E$63*( (1+$E$39)^0.5 / (1+((C$100 + $A103*0.055 + 0.02)*0.5 + 0.0711*0.5))^0.5 ) + F$63*( (1+$E$39)^1.5 / (1+((C$100 + $A103*0.055 + 0.02)*0.5 + 0.0711*0.5))^1.5 ) + G$63*( (1+$E$39)^2.5 / (1+((C$100 + $A103*0.055 + 0.02)*0.5 + 0.0711*0.5))^2.5 ) + H$63*( (1+$E$39)^3.5 / (1+((C$100 + $A103*0.055 + 0.02)*0.5 + 0.0711*0.5))^3.5 ) + I$63*( (1+$E$39)^4.5 / (1+((C$100 + $A103*0.055 + 0.02)*0.5 + 0.0711*0.5))^4.5 )) + ($B$67/(((C$100 + $A103*0.055 + 0.02)*0.5 + 0.0711*0.5)-$E$40))/(1+((C$100 + $A103*0.055 + 0.02)*0.5 + 0.0711*0.5))^5.0 - $B$74)/$B$76 | D103: =((E$63*( (1+$E$39)^0.5 / (1+((D$100 + $A103*0.055 + 0.02)*0.5 + 0.0711*0.5))^0.5 ) + F$63*( (1+$E$39)^1.5 / (1+((D$100 + $A103*0.055 + 0.02)*0.5 + 0.0711*0.5))^1.5 ) + G$63*( (1+$E$39)^2.5 / (1+((D$100 + $A103*0.055 + 0.02)*0.5 + 0.0711*0.5))^2.5 ) + H$63*( (1+$E$39)^3.5 / (1+((D$100 + $A103*0.055 + 0.02)*0.5 + 0.0711*0.5))^3.5 ) + I$63*( (1+$E$39)^4.5 / (1+((D$100 + $A103*0.055 + 0.02)*0.5 + 0.0711*0.5))^4.5 )) + ($B$67/(((D$100 + $A103*0.055 + 0.02)*0.5 + 0.0711*0.5)-$E$40))/(1+((D$100 + $A103*0.055 + 0.02)*0.5 + 0.0711*0.5))^5.0 - $B$74)/$B$76 | E103: =((E$63*( (1+$E$39)^0.5 / (1+((E$100 + $A103*0.055 + 0.02)*0.5 + 0.0711*0.5))^0.5 ) + F$63*( (1+$E$39)^1.5 / (1+((E$100 + $A103*0.055 + 0.02)*0.5 + 0.0711*0.5))^1.5 ) + G$63*( (1+$E$39)^2.5 / (1+((E$100 + $A103*0.055 + 0.02)*0.5 + 0.0711*0.5))^2.5 ) + H$63*( (1+$E$39)^3.5 / (1+((E$100 + $A103*0.055 + 0.02)*0.5 + 0.0711*0.5))^3.5 ) + I$63*( (1+$E$39)^4.5 / (1+((E$100 + $A103*0.055 + 0.02)*0.5 + 0.0711*0.5))^4.5 )) + ($B$67/(((E$100 + $A103*0.055 + 0.02)*0.5 + 0.0711*0.5)-$E$40))/(1+((E$100 + $A103*0.055 + 0.02)*0.5 + 0.0711*0.5))^5.0 - $B$74)/$B$76 | F103: =((E$63*( (1+$E$39)^0.5 / (1+((F$100 + $A103*0.055 + 0.02)*0.5 + 0.0711*0.5))^0.5 ) + F$63*( (1+$E$39)^1.5 / (1+((F$100 + $A103*0.055 + 0.02)*0.5 + 0.0711*0.5))^1.5 ) + G$63*( (1+$E$39)^2.5 / (1+((F$100 + $A103*0.055 + 0.02)*0.5 + 0.0711*0.5))^2.5 ) + H$63*( (1+$E$39)^3.5 / (1+((F$100 + $A103*0.055 + 0.02)*0.5 + 0.0711*0.5))^3.5 ) + I$63*( (1+$E$39)^4.5 / (1+((F$100 + $A103*0.055 + 0.02)*0.5 + 0.0711*0.5))^4.5 )) + ($B$67/(((F$100 + $A103*0.055 + 0.02)*0.5 + 0.0711*0.5)-$E$40))/(1+((F$100 + $A103*0.055 + 0.02)*0.5 + 0.0711*0.5))^5.0 - $B$74)/$B$76 | G103: =((E$63*( (1+$E$39)^0.5 / (1+((G$100 + $A103*0.055 + 0.02)*0.5 + 0.0711*0.5))^0.5 ) + F$63*( (1+$E$39)^1.5 / (1+((G$100 + $A103*0.055 + 0.02)*0.5 + 0.0711*0.5))^1.5 ) + G$63*( (1+$E$39)^2.5 / (1+((G$100 + $A103*0.055 + 0.02)*0.5 + 0.0711*0.5))^2.5 ) + H$63*( (1+$E$39)^3.5 / (1+((G$100 + $A103*0.055 + 0.02)*0.5 + 0.0711*0.5))^3.5 ) + I$63*( (1+$E$39)^4.5 / (1+((G$100 + $A103*0.055 + 0.02)*0.5 + 0.0711*0.5))^4.5 )) + ($B$67/(((G$100 + $A103*0.055 + 0.02)*0.5 + 0.0711*0.5)-$E$40))/(1+((G$100 + $A103*0.055 + 0.02)*0.5 + 0.0711*0.5))^5.0 - $B$74)/$B$76
A104: 1.3 | C104: =((E$63*( (1+$E$39)^0.5 / (1+((C$100 + $A104*0.055 + 0.02)*0.5 + 0.0711*0.5))^0.5 ) + F$63*( (1+$E$39)^1.5 / (1+((C$100 + $A104*0.055 + 0.02)*0.5 + 0.0711*0.5))^1.5 ) + G$63*( (1+$E$39)^2.5 / (1+((C$100 + $A104*0.055 + 0.02)*0.5 + 0.0711*0.5))^2.5 ) + H$63*( (1+$E$39)^3.5 / (1+((C$100 + $A104*0.055 + 0.02)*0.5 + 0.0711*0.5))^3.5 ) + I$63*( (1+$E$39)^4.5 / (1+((C$100 + $A104*0.055 + 0.02)*0.5 + 0.0711*0.5))^4.5 )) + ($B$67/(((C$100 + $A104*0.055 + 0.02)*0.5 + 0.0711*0.5)-$E$40))/(1+((C$100 + $A104*0.055 + 0.02)*0.5 + 0.0711*0.5))^5.0 - $B$74)/$B$76 | D104: =((E$63*( (1+$E$39)^0.5 / (1+((D$100 + $A104*0.055 + 0.02)*0.5 + 0.0711*0.5))^0.5 ) + F$63*( (1+$E$39)^1.5 / (1+((D$100 + $A104*0.055 + 0.02)*0.5 + 0.0711*0.5))^1.5 ) + G$63*( (1+$E$39)^2.5 / (1+((D$100 + $A104*0.055 + 0.02)*0.5 + 0.0711*0.5))^2.5 ) + H$63*( (1+$E$39)^3.5 / (1+((D$100 + $A104*0.055 + 0.02)*0.5 + 0.0711*0.5))^3.5 ) + I$63*( (1+$E$39)^4.5 / (1+((D$100 + $A104*0.055 + 0.02)*0.5 + 0.0711*0.5))^4.5 )) + ($B$67/(((D$100 + $A104*0.055 + 0.02)*0.5 + 0.0711*0.5)-$E$40))/(1+((D$100 + $A104*0.055 + 0.02)*0.5 + 0.0711*0.5))^5.0 - $B$74)/$B$76 | E104: =((E$63*( (1+$E$39)^0.5 / (1+((E$100 + $A104*0.055 + 0.02)*0.5 + 0.0711*0.5))^0.5 ) + F$63*( (1+$E$39)^1.5 / (1+((E$100 + $A104*0.055 + 0.02)*0.5 + 0.0711*0.5))^1.5 ) + G$63*( (1+$E$39)^2.5 / (1+((E$100 + $A104*0.055 + 0.02)*0.5 + 0.0711*0.5))^2.5 ) + H$63*( (1+$E$39)^3.5 / (1+((E$100 + $A104*0.055 + 0.02)*0.5 + 0.0711*0.5))^3.5 ) + I$63*( (1+$E$39)^4.5 / (1+((E$100 + $A104*0.055 + 0.02)*0.5 + 0.0711*0.5))^4.5 )) + ($B$67/(((E$100 + $A104*0.055 + 0.02)*0.5 + 0.0711*0.5)-$E$40))/(1+((E$100 + $A104*0.055 + 0.02)*0.5 + 0.0711*0.5))^5.0 - $B$74)/$B$76 | F104: =((E$63*( (1+$E$39)^0.5 / (1+((F$100 + $A104*0.055 + 0.02)*0.5 + 0.0711*0.5))^0.5 ) + F$63*( (1+$E$39)^1.5 / (1+((F$100 + $A104*0.055 + 0.02)*0.5 + 0.0711*0.5))^1.5 ) + G$63*( (1+$E$39)^2.5 / (1+((F$100 + $A104*0.055 + 0.02)*0.5 + 0.0711*0.5))^2.5 ) + H$63*( (1+$E$39)^3.5 / (1+((F$100 + $A104*0.055 + 0.02)*0.5 + 0.0711*0.5))^3.5 ) + I$63*( (1+$E$39)^4.5 / (1+((F$100 + $A104*0.055 + 0.02)*0.5 + 0.0711*0.5))^4.5 )) + ($B$67/(((F$100 + $A104*0.055 + 0.02)*0.5 + 0.0711*0.5)-$E$40))/(1+((F$100 + $A104*0.055 + 0.02)*0.5 + 0.0711*0.5))^5.0 - $B$74)/$B$76 | G104: =((E$63*( (1+$E$39)^0.5 / (1+((G$100 + $A104*0.055 + 0.02)*0.5 + 0.0711*0.5))^0.5 ) + F$63*( (1+$E$39)^1.5 / (1+((G$100 + $A104*0.055 + 0.02)*0.5 + 0.0711*0.5))^1.5 ) + G$63*( (1+$E$39)^2.5 / (1+((G$100 + $A104*0.055 + 0.02)*0.5 + 0.0711*0.5))^2.5 ) + H$63*( (1+$E$39)^3.5 / (1+((G$100 + $A104*0.055 + 0.02)*0.5 + 0.0711*0.5))^3.5 ) + I$63*( (1+$E$39)^4.5 / (1+((G$100 + $A104*0.055 + 0.02)*0.5 + 0.0711*0.5))^4.5 )) + ($B$67/(((G$100 + $A104*0.055 + 0.02)*0.5 + 0.0711*0.5)-$E$40))/(1+((G$100 + $A104*0.055 + 0.02)*0.5 + 0.0711*0.5))^5.0 - $B$74)/$B$76
A105: 1.4 | C105: =((E$63*( (1+$E$39)^0.5 / (1+((C$100 + $A105*0.055 + 0.02)*0.5 + 0.0711*0.5))^0.5 ) + F$63*( (1+$E$39)^1.5 / (1+((C$100 + $A105*0.055 + 0.02)*0.5 + 0.0711*0.5))^1.5 ) + G$63*( (1+$E$39)^2.5 / (1+((C$100 + $A105*0.055 + 0.02)*0.5 + 0.0711*0.5))^2.5 ) + H$63*( (1+$E$39)^3.5 / (1+((C$100 + $A105*0.055 + 0.02)*0.5 + 0.0711*0.5))^3.5 ) + I$63*( (1+$E$39)^4.5 / (1+((C$100 + $A105*0.055 + 0.02)*0.5 + 0.0711*0.5))^4.5 )) + ($B$67/(((C$100 + $A105*0.055 + 0.02)*0.5 + 0.0711*0.5)-$E$40))/(1+((C$100 + $A105*0.055 + 0.02)*0.5 + 0.0711*0.5))^5.0 - $B$74)/$B$76 | D105: =((E$63*( (1+$E$39)^0.5 / (1+((D$100 + $A105*0.055 + 0.02)*0.5 + 0.0711*0.5))^0.5 ) + F$63*( (1+$E$39)^1.5 / (1+((D$100 + $A105*0.055 + 0.02)*0.5 + 0.0711*0.5))^1.5 ) + G$63*( (1+$E$39)^2.5 / (1+((D$100 + $A105*0.055 + 0.02)*0.5 + 0.0711*0.5))^2.5 ) + H$63*( (1+$E$39)^3.5 / (1+((D$100 + $A105*0.055 + 0.02)*0.5 + 0.0711*0.5))^3.5 ) + I$63*( (1+$E$39)^4.5 / (1+((D$100 + $A105*0.055 + 0.02)*0.5 + 0.0711*0.5))^4.5 )) + ($B$67/(((D$100 + $A105*0.055 + 0.02)*0.5 + 0.0711*0.5)-$E$40))/(1+((D$100 + $A105*0.055 + 0.02)*0.5 + 0.0711*0.5))^5.0 - $B$74)/$B$76 | E105: =((E$63*( (1+$E$39)^0.5 / (1+((E$100 + $A105*0.055 + 0.02)*0.5 + 0.0711*0.5))^0.5 ) + F$63*( (1+$E$39)^1.5 / (1+((E$100 + $A105*0.055 + 0.02)*0.5 + 0.0711*0.5))^1.5 ) + G$63*( (1+$E$39)^2.5 / (1+((E$100 + $A105*0.055 + 0.02)*0.5 + 0.0711*0.5))^2.5 ) + H$63*( (1+$E$39)^3.5 / (1+((E$100 + $A105*0.055 + 0.02)*0.5 + 0.0711*0.5))^3.5 ) + I$63*( (1+$E$39)^4.5 / (1+((E$100 + $A105*0.055 + 0.02)*0.5 + 0.0711*0.5))^4.5 )) + ($B$67/(((E$100 + $A105*0.055 + 0.02)*0.5 + 0.0711*0.5)-$E$40))/(1+((E$100 + $A105*0.055 + 0.02)*0.5 + 0.0711*0.5))^5.0 - $B$74)/$B$76 | F105: =((E$63*( (1+$E$39)^0.5 / (1+((F$100 + $A105*0.055 + 0.02)*0.5 + 0.0711*0.5))^0.5 ) + F$63*( (1+$E$39)^1.5 / (1+((F$100 + $A105*0.055 + 0.02)*0.5 + 0.0711*0.5))^1.5 ) + G$63*( (1+$E$39)^2.5 / (1+((F$100 + $A105*0.055 + 0.02)*0.5 + 0.0711*0.5))^2.5 ) + H$63*( (1+$E$39)^3.5 / (1+((F$100 + $A105*0.055 + 0.02)*0.5 + 0.0711*0.5))^3.5 ) + I$63*( (1+$E$39)^4.5 / (1+((F$100 + $A105*0.055 + 0.02)*0.5 + 0.0711*0.5))^4.5 )) + ($B$67/(((F$100 + $A105*0.055 + 0.02)*0.5 + 0.0711*0.5)-$E$40))/(1+((F$100 + $A105*0.055 + 0.02)*0.5 + 0.0711*0.5))^5.0 - $B$74)/$B$76 | G105: =((E$63*( (1+$E$39)^0.5 / (1+((G$100 + $A105*0.055 + 0.02)*0.5 + 0.0711*0.5))^0.5 ) + F$63*( (1+$E$39)^1.5 / (1+((G$100 + $A105*0.055 + 0.02)*0.5 + 0.0711*0.5))^1.5 ) + G$63*( (1+$E$39)^2.5 / (1+((G$100 + $A105*0.055 + 0.02)*0.5 + 0.0711*0.5))^2.5 ) + H$63*( (1+$E$39)^3.5 / (1+((G$100 + $A105*0.055 + 0.02)*0.5 + 0.0711*0.5))^3.5 ) + I$63*( (1+$E$39)^4.5 / (1+((G$100 + $A105*0.055 + 0.02)*0.5 + 0.0711*0.5))^4.5 )) + ($B$67/(((G$100 + $A105*0.055 + 0.02)*0.5 + 0.0711*0.5)-$E$40))/(1+((G$100 + $A105*0.055 + 0.02)*0.5 + 0.0711*0.5))^5.0 - $B$74)/$B$76

Sheet WACC
A1: Maison Solutions Inc. (NASDAQ: MSS) - WACC Schedule
A3: CAPITAL ASSET PRICING MODEL (CAPM) & WACC BUILD
A4: Risk-Free Rate (Rf) | B4: 0.047 | C4: US 10-Year Treasury Yield (August 2026)
A5: Equity Beta (β) | B5: 1.2 | C5: Small-cap grocery / specialty retail adjusted beta
A6: Equity Risk Premium (ERP) | B6: 0.055 | C6: Standard institutional market risk premium (5.5%)
A7: Small-Cap Size Premium | B7: 0.02 | C7: Micro-cap liquidity and scale risk premium
A8: Cost of Equity (Ke = Rf + β*ERP + Size) | B8: =B4+B5*B6+B7 | C8: CAPM Cost of Equity
A10: Pre-Tax Cost of Debt (Kd) | B10: 0.09 | C10: Micro-cap borrowing and debt interest rate
A11: Effective Corporate Tax Rate (t) | B11: =DCF!$B$15 | C11: Statutory tax rate
A12: After-Tax Cost of Debt (Kd * (1 - t)) | B12: =B10*(1-B11) | C12: After-tax borrowing cost
A14: Target Equity Weight (We) | B14: 0.5 | C14: Normalized target capital structure
A15: Target Debt Weight (Wd) | B15: 0.5 | C15: Normalized target capital structure
A16: Weighted Average Cost of Capital (WACC) | B16: =B8*B14+B12*B15 | C16: Calculated Base WACC (10.20% normalized)

Sheet Sensitivity
A1: Maison Solutions Inc. (NASDAQ: MSS) - Executive Sensitivity Analysis
A3: TABLE 1: WACC VS. TERMINAL GROWTH RATE (Implied Share Price $)
A4: WACC \ g | B4: 0.015 | C4: 0.02 | D4: 0.025 | E4: 0.03 | F4: 0.035
A5: 0.09 | B5: =DCF!C83 | C5: =DCF!D83 | D5: =DCF!E83 | E5: =DCF!F83 | F5: =DCF!G83
A6: 0.095 | B6: =DCF!C84 | C6: =DCF!D84 | D6: =DCF!E84 | E6: =DCF!F84 | F6: =DCF!G84
A7: 0.1 | B7: =DCF!C85 | C7: =DCF!D85 | D7: =DCF!E85 | E7: =DCF!F85 | F7: =DCF!G85
A8: 0.105 | B8: =DCF!C86 | C8: =DCF!D86 | D8: =DCF!E86 | E8: =DCF!F86 | F8: =DCF!G86
A9: 0.11 | B9: =DCF!C87 | C9: =DCF!D87 | D9: =DCF!E87 | E9: =DCF!F87 | F9: =DCF!G87
