Workbook

Sheet DCF
A1: Space Exploration Technologies Corp. (SpaceX) - Institutional DCF Valuation Model
A2: Ticker: SPCX (NASDAQ) | Date: August 19, 2026 | Historical: 2023A-2025A | Projections: 2026E-2030E | Figures in USD Millions ($M)
A4: SCENARIO CONTROL & ACTIVE CASE SELECTOR
A5: Select Scenario Case (1 = Bear, 2 = Base, 3 = Bull): | B5: 2 | C5: Active Scenario: | D5: =IF(B5=1,"Bear Case",IF(B5=2,"Base Case (Consensus)","Bull Case"))
A7: MARKET DATA & CAPITAL STRUCTURE (USD Millions, except per share)
A8: Current Stock Price ($) | C8: 143.34
A9: Diluted Shares Outstanding (M) | C9: 13570
A10: Implied Market Capitalization ($M) | C10: =C8*C9
A11: Total Debt & Financing Lease Liabilities ($M) | C11: 38430
A12: Cash, Equivalents & Short-Term Investments ($M) | C12: 93520
A13: Net Debt / (Net Cash Position) ($M) | C13: =C11-C12
A14: Enterprise Value (Market EV) ($M) | C14: =C10+C13
A16: SCENARIO 1: BEAR CASE ASSUMPTIONS (CONSERVATIVE ADOPTION)
A17: Key DCF Driver / Assumption | F17: FY2026E | G17: FY2027E | H17: FY2028E | I17: FY2029E | J17: FY2030E | K17: Terminal
A18: Revenue YoY Growth (%) | F18: 1 | G18: 0.8 | H18: 0.5 | I18: 0.45 | J18: 0.35 | K18: -
A19: Gross Profit Margin (%) | F19: 0.36 | G19: 0.38 | H19: 0.4 | I19: 0.42 | J19: 0.44 | K19: -
A20: R&D Expense (% of Revenue) | F20: 0.25 | G20: 0.2 | H20: 0.16 | I20: 0.14 | J20: 0.12 | K20: -
A21: SG&A Expense (% of Revenue) | F21: 0.2 | G21: 0.17 | H21: 0.15 | I21: 0.14 | J21: 0.14 | K21: -
A22: Operating Margin (EBIT %) Target | F22: -0.09 | G22: 0.01 | H22: 0.09 | I22: 0.14 | J22: 0.18 | K22: -
A23: Effective Tax Rate (%) | F23: 0.21 | G23: 0.21 | H23: 0.21 | I23: 0.21 | J23: 0.21 | K23: -
A24: Depreciation & Amortization (% of Rev) | F24: 0.18 | G24: 0.14 | H24: 0.11 | I24: 0.09 | J24: 0.08 | K24: -
A25: Capital Expenditures (% of Rev) | F25: 0.25 | G25: 0.2 | H25: 0.16 | I25: 0.13 | J25: 0.11 | K25: -
A26: Change in NWC (% of Δ Revenue) | F26: 0.015 | G26: 0.015 | H26: 0.015 | I26: 0.015 | J26: 0.015 | K26: -
A27: Terminal Perpetuity Growth Rate (g) | F27: - | G27: - | H27: - | I27: - | J27: - | K27: 0.025
A28: Discount Rate (WACC) | F28: 0.115 | G28: 0.115 | H28: 0.115 | I28: 0.115 | J28: 0.115 | K28: 0.115
A30: SCENARIO 2: BASE CASE ASSUMPTIONS (CONSENSUS & MANAGEMENT ROADMAP)
A31: Key DCF Driver / Assumption | F31: FY2026E | G31: FY2027E | H31: FY2028E | I31: FY2029E | J31: FY2030E | K31: Terminal
A32: Revenue YoY Growth (%) | F32: 1.383 | G32: 1.247 | H32: 0.6 | I32: 0.438 | J32: 0.348 | K32: -
A33: Gross Profit Margin (%) | F33: 0.38 | G33: 0.42 | H33: 0.46 | I33: 0.49 | J33: 0.52 | K33: -
A34: R&D Expense (% of Revenue) | F34: 0.24 | G34: 0.18 | H34: 0.14 | I34: 0.12 | J34: 0.1 | K34: -
A35: SG&A Expense (% of Revenue) | F35: 0.19 | G35: 0.15 | H35: 0.13 | I35: 0.12 | J35: 0.12 | K35: -
A36: Operating Margin (EBIT %) Target | F36: -0.05 | G36: 0.09 | H36: 0.19 | I36: 0.25 | J36: 0.3 | K36: -
A37: Effective Tax Rate (%) | F37: 0.21 | G37: 0.21 | H37: 0.21 | I37: 0.21 | J37: 0.21 | K37: -
A38: Depreciation & Amortization (% of Rev) | F38: 0.18 | G38: 0.14 | H38: 0.11 | I38: 0.09 | J38: 0.08 | K38: -
A39: Capital Expenditures (% of Rev) | F39: 0.25 | G39: 0.18 | H39: 0.14 | I39: 0.11 | J39: 0.09 | K39: -
A40: Change in NWC (% of Δ Revenue) | F40: 0.015 | G40: 0.015 | H40: 0.015 | I40: 0.015 | J40: 0.015 | K40: -
A41: Terminal Perpetuity Growth Rate (g) | F41: - | G41: - | H41: - | I41: - | J41: - | K41: 0.03
A42: Discount Rate (WACC) | F42: =WACC!$B$21 | G42: =WACC!$B$21 | H42: =WACC!$B$21 | I42: =WACC!$B$21 | J42: =WACC!$B$21 | K42: =WACC!$B$21
A44: SCENARIO 3: BULL CASE ASSUMPTIONS (STARSHIP COMMERCIAL SCALE & AI SURGE)
A45: Key DCF Driver / Assumption | F45: FY2026E | G45: FY2027E | H45: FY2028E | I45: FY2029E | J45: FY2030E | K45: Terminal
A46: Revenue YoY Growth (%) | F46: 1.6 | G46: 1.45 | H46: 0.75 | I46: 0.5 | J46: 0.4 | K46: -
A47: Gross Profit Margin (%) | F47: 0.42 | G47: 0.46 | H47: 0.5 | I47: 0.53 | J47: 0.55 | K47: -
A48: R&D Expense (% of Revenue) | F48: 0.22 | G48: 0.16 | H48: 0.12 | I48: 0.1 | J48: 0.09 | K48: -
A49: SG&A Expense (% of Revenue) | F49: 0.18 | G49: 0.14 | H49: 0.12 | I49: 0.11 | J49: 0.11 | K49: -
A50: Operating Margin (EBIT %) Target | F50: 0.02 | G50: 0.16 | H50: 0.26 | I50: 0.32 | J50: 0.35 | K50: -
A51: Effective Tax Rate (%) | F51: 0.21 | G51: 0.21 | H51: 0.21 | I51: 0.21 | J51: 0.21 | K51: -
A52: Depreciation & Amortization (% of Rev) | F52: 0.18 | G52: 0.14 | H52: 0.11 | I52: 0.09 | J52: 0.08 | K52: -
A53: Capital Expenditures (% of Rev) | F53: 0.24 | G53: 0.16 | H53: 0.12 | I53: 0.1 | J53: 0.08 | K53: -
A54: Change in NWC (% of Δ Revenue) | F54: 0.015 | G54: 0.015 | H54: 0.015 | I54: 0.015 | J54: 0.015 | K54: -
A55: Terminal Perpetuity Growth Rate (g) | F55: - | G55: - | H55: - | I55: - | J55: - | K55: 0.035
A56: Discount Rate (WACC) | F56: 0.095 | G56: 0.095 | H56: 0.095 | I56: 0.095 | J56: 0.095 | K56: 0.095
A58: ACTIVE SCENARIO CONSOLIDATED ASSUMPTIONS (DYNAMIC MODEL DRIVERS)
A59: Active DCF Driver | F59: FY2026E | G59: FY2027E | H59: FY2028E | I59: FY2029E | J59: FY2030E | K59: Terminal
A60: Revenue YoY Growth (%) | F60: =CHOOSE($B$5, F18, F32, F46) | G60: =CHOOSE($B$5, G18, G32, G46) | H60: =CHOOSE($B$5, H18, H32, H46) | I60: =CHOOSE($B$5, I18, I32, I46) | J60: =CHOOSE($B$5, J18, J32, J46)
A61: Gross Profit Margin (%) | F61: =CHOOSE($B$5, F19, F33, F47) | G61: =CHOOSE($B$5, G19, G33, G47) | H61: =CHOOSE($B$5, H19, H33, H47) | I61: =CHOOSE($B$5, I19, I33, I47) | J61: =CHOOSE($B$5, J19, J33, J47)
A62: R&D Expense (% of Revenue) | F62: =CHOOSE($B$5, F20, F34, F48) | G62: =CHOOSE($B$5, G20, G34, G48) | H62: =CHOOSE($B$5, H20, H34, H48) | I62: =CHOOSE($B$5, I20, I34, I48) | J62: =CHOOSE($B$5, J20, J34, J48)
A63: SG&A Expense (% of Revenue) | F63: =CHOOSE($B$5, F21, F35, F49) | G63: =CHOOSE($B$5, G21, G35, G49) | H63: =CHOOSE($B$5, H21, H35, H49) | I63: =CHOOSE($B$5, I21, I35, I49) | J63: =CHOOSE($B$5, J21, J35, J49)
A64: Operating Margin (EBIT %) | F64: =CHOOSE($B$5, F22, F36, F50) | G64: =CHOOSE($B$5, G22, G36, G50) | H64: =CHOOSE($B$5, H22, H36, H50) | I64: =CHOOSE($B$5, I22, I36, I50) | J64: =CHOOSE($B$5, J22, J36, J50)
A65: Effective Tax Rate (%) | F65: =CHOOSE($B$5, F23, F37, F51) | G65: =CHOOSE($B$5, G23, G37, G51) | H65: =CHOOSE($B$5, H23, H37, H51) | I65: =CHOOSE($B$5, I23, I37, I51) | J65: =CHOOSE($B$5, J23, J37, J51)
A66: Depreciation & Amortization (% of Rev) | F66: =CHOOSE($B$5, F24, F38, F52) | G66: =CHOOSE($B$5, G24, G38, G52) | H66: =CHOOSE($B$5, H24, H38, H52) | I66: =CHOOSE($B$5, I24, I38, I52) | J66: =CHOOSE($B$5, J24, J38, J52)
A67: Capital Expenditures (% of Rev) | F67: =CHOOSE($B$5, F25, F39, F53) | G67: =CHOOSE($B$5, G25, G39, G53) | H67: =CHOOSE($B$5, H25, H39, H53) | I67: =CHOOSE($B$5, I25, I39, I53) | J67: =CHOOSE($B$5, J25, J39, J53)
A68: Change in NWC (% of Δ Revenue) | F68: =CHOOSE($B$5, F26, F40, F54) | G68: =CHOOSE($B$5, G26, G40, G54) | H68: =CHOOSE($B$5, H26, H40, H54) | I68: =CHOOSE($B$5, I26, I40, I54) | J68: =CHOOSE($B$5, J26, J40, J54)
A69: Terminal Perpetuity Growth Rate (g) | F69: - | G69: - | H69: - | I69: - | J69: - | K69: =CHOOSE($B$5, K27, K41, K55)
A70: Discount Rate (WACC) | F70: =CHOOSE($B$5, F28, F42, F56) | G70: =CHOOSE($B$5, G28, G42, G56) | H70: =CHOOSE($B$5, H28, H42, H56) | I70: =CHOOSE($B$5, I28, I42, I56) | J70: =CHOOSE($B$5, J28, J42, J56) | K70: =CHOOSE($B$5, K28, K42, K56)
A72: HISTORICAL & PROJECTED INCOME STATEMENT ($M)
A73: Income Statement Line Item | C73: 2023A | D73: 2024A | E73: 2025A | F73: 2026E | G73: 2027E | H73: 2028E | I73: 2029E | J73: 2030E
A74: Total Revenue | C74: 10390 | D74: 14020 | E74: 18670 | F74: =E74*(1+F60) | G74: =F74*(1+G60) | H74: =G74*(1+H60) | I74: =H74*(1+I60) | J74: =I74*(1+J60)
A75: % YoY Growth | C75: - | D75: =D74/C74-1 | E75: =E74/D74-1 | F75: =F74/E74-1 | G75: =G74/F74-1 | H75: =H74/G74-1 | I75: =I74/H74-1 | J75: =J74/I74-1
A76: Cost of Goods Sold (COGS) | C76: 7273 | D76: 9393 | E76: 12173 | F76: =F74*(1-F61) | G76: =G74*(1-G61) | H76: =H74*(1-H61) | I76: =I74*(1-I61) | J76: =J74*(1-J61)
A77: Gross Profit | C77: =C74-C76 | D77: =D74-D76 | E77: =E74-E76 | F77: =F74-F76 | G77: =G74-G76 | H77: =H74-H76 | I77: =I74-I76 | J77: =J74-J76
A78: % Gross Margin | C78: =C77/C74 | D78: =D77/D74 | E78: =E77/E74 | F78: =F77/F74 | G78: =G77/G74 | H78: =H77/H74 | I78: =I77/I74 | J78: =J77/J74
A79: Operating Expenses:
A80: Research & Development (R&D) | C80: 3100 | D80: 4400 | E80: 6067 | F80: =F74*F62 | G80: =G74*G62 | H80: =H74*H62 | I80: =I74*I62 | J80: =J74*J62
A81: Selling, General & Administrative (SG&A) | C81: 2100 | D81: 3000 | E81: 3930 | F81: =F74*F63 | G81: =G74*G63 | H81: =H74*H63 | I81: =I74*I63 | J81: =J74*J63
A82: Total Operating Expenses | C82: =SUM(C80:C81) | D82: =SUM(D80:D81) | E82: =SUM(E80:E81) | F82: =SUM(F80:F81) | G82: =SUM(G80:G81) | H82: =SUM(H80:H81) | I82: =SUM(I80:I81) | J82: =SUM(J80:J81)
A83: Operating Income / (Loss) (EBIT) | C83: =C77-C82 | D83: =D77-D82 | E83: =E77-E82 | F83: =F77-F82 | G83: =G77-G82 | H83: =H77-H82 | I83: =I77-I82 | J83: =J77-J82
A84: % EBIT Margin | C84: =C83/C74 | D84: =D83/D74 | E84: =E83/E74 | F84: =F83/F74 | G84: =G83/G74 | H84: =H83/H74 | I84: =I83/I74 | J84: =J83/J74
A85: Income Tax Provision (Taxes @ 21%) | C85: 0 | D85: 0 | E85: 0 | F85: =IF(F83>0, F83*F65, 0) | G85: =IF(G83>0, G83*G65, 0) | H85: =IF(H83>0, H83*H65, 0) | I85: =IF(I83>0, I83*I65, 0) | J85: =IF(J83>0, J83*J65, 0)
A86: Net Operating Profit After Tax (NOPAT) | C86: =C83-C85 | D86: =D83-D85 | E86: =E83-E85 | F86: =F83-F85 | G86: =G83-G85 | H86: =H83-H85 | I86: =I83-I85 | J86: =J83-J85
A88: UNLEVERED FREE CASH FLOW (UFCF) BUILD ($M)
A89: Cash Flow Line Item | C89: 2023A | D89: 2024A | E89: 2025A | F89: 2026E | G89: 2027E | H89: 2028E | I89: 2029E | J89: 2030E
A90: Net Operating Profit After Tax (NOPAT) | C90: =C86 | D90: =D86 | E90: =E86 | F90: =F86 | G90: =G86 | H90: =H86 | I90: =I86 | J90: =J86
A91: (+) Depreciation & Amortization (D&A) | C91: 4800 | D91: 7200 | E91: 10080 | F91: =F74*F66 | G91: =G74*G66 | H91: =H74*H66 | I91: =I74*I66 | J91: =J74*J66
A92: (-) Capital Expenditures (CapEx) | C92: 10500 | D92: 15200 | E92: 20700 | F92: =F74*F67 | G92: =G74*G67 | H92: =H74*H67 | I92: =I74*I67 | J92: =J74*J67
A93: (-) Change in Non-Cash Working Capital (ΔNWC) | C93: 0 | D93: 54.45 | E93: 69.75 | F93: =(F74-E74)*F68 | G93: =(G74-F74)*G68 | H93: =(H74-G74)*H68 | I93: =(I74-H74)*I68 | J93: =(J74-I74)*J68
A94: Unlevered Free Cash Flow (UFCF) | C94: =C90+C91-C92-C93 | D94: =D90+D91-D92-D93 | E94: =E90+E91-E92-E93 | F94: =F90+F91-F92-F93 | G94: =G90+G91-G92-G93 | H94: =H90+H91-H92-H93 | I94: =I90+I91-I92-I93 | J94: =J90+J91-J92-J93
A96: DISCOUNTING & PRESENT VALUE CALCULATION ($M)
A97: Valuation Metric / Period | F97: FY2026E | G97: FY2027E | H97: FY2028E | I97: FY2029E | J97: FY2030E | K97: Terminal
A98: Unlevered Free Cash Flow ($M) | F98: =F94 | G98: =G94 | H98: =H94 | I98: =I94 | J98: =J94 | K98: =J98*(1+K69)
A99: Discount Period (Mid-Year Convention) | F99: 0.5 | G99: 1.5 | H99: 2.5 | I99: 3.5 | J99: 4.5 | K99: 4.5
A100: Discount Factor (1 / (1 + WACC)^t) | F100: =1/(1+F70)^F99 | G100: =1/(1+G70)^G99 | H100: =1/(1+H70)^H99 | I100: =1/(1+I70)^I99 | J100: =1/(1+J70)^J99 | K100: =1/(1+K70)^K99
A101: Present Value of Cash Flow ($M) | F101: =F98*F100 | G101: =G98*G100 | H101: =H98*H100 | I101: =I98*I100 | J101: =J98*J100
A103: TERMINAL VALUE CALCULATION (GORDON GROWTH METHOD)
A104: Terminal Year Normalized FCF ($M) | K104: =K98
A105: Terminal Perpetuity Growth Rate (g) | K105: =K69
A106: Undiscounted Terminal Value (TV) ($M) | K106: =K104/(K70-K105)
A107: Present Value of Terminal Value ($M) | K107: =K106*K100
A109: VALUATION SUMMARY & PER SHARE BRIDGE ($M, except per share)
A110: Cumulative PV of 5-Year Explicit Cash Flows | C110: =SUM(F101:J101)
A111: Present Value of Terminal Value | C111: =K107
...

Sheet WACC
A1: Space Exploration Technologies Corp. (SpaceX) - Cost of Capital (WACC)
A2: Ticker: SPCX | Valuation Date: August 19, 2026 | Currency: USD in Millions ($M)
A4: 1. COST OF EQUITY CALCULATION (CAPM METHODOLOGY)
A5: Risk-Free Rate (10-Year US Treasury Yield) | B5: 0.0425
A6: Market Beta (5Y Monthly / Aerospace & Tech Blend) | B6: 1.35
A7: Equity Risk Premium (ERP) | B7: 0.055
A8: Cost of Equity (Ke = Rf + Beta * ERP) | B8: =B5+B6*B7
A10: 2. COST OF DEBT CALCULATION
A11: Pre-Tax Cost of Debt | B11: 0.065
A12: Effective Corporate Tax Rate | B12: =DCF!$F$65
A13: After-Tax Cost of Debt (Kd = Pre-Tax * (1 - Tax Rate)) | B13: =B11*(1-B12)
A15: 3. CAPITAL STRUCTURE & WEIGHTED AVERAGE COST OF CAPITAL (WACC)
A16: Capital Component | B16: Market Value ($M) | C16: Capital Weight (%) | D16: Cost of Capital (%) | E16: Weighted Contribution (%)
A17: Market Capitalization (Equity) | B17: =DCF!$C$10 | C17: =B17/$B$19 | D17: =B8 | E17: =C17*D17
A18: Total Debt & Lease Obligations | B18: =DCF!$C$11 | C18: =B18/$B$19 | D18: =B13 | E18: =C18*D18
A19: Total Capital (Equity + Debt) | B19: =B17+B18 | C19: =SUM(C17:C18) | D19: - | E19: =SUM(E17:E18)
A21: WEIGHTED AVERAGE COST OF CAPITAL (WACC) | B21: =E19
