Workbook

Sheet DCF Valuation
A1: Tesla, Inc. (NASDAQ: TSLA)
A2: Institutional DCF Valuation Model | Report Date: August 19, 2026 | Financial Source: SEC Form 10-K & Consensus Estimates
A4: Active Scenario Selector: | B4: 2 | C4: =IF(B4=1,"[1] BEAR CASE (EV Saturation / Margin Pressure / FSD Delay)",IF(B4=2,"[2] BASE CASE (Next-Gen Platform / Megapack Scale / Steady FSD)","[3] BULL CASE (Autonomous Robotaxi Fleet & Optimus Surge)"))
A6: I. MARKET DATA & CAPITAL STRUCTURE INPUTS
A7: Current Stock Price ($) | B7: 336.5
A8: Diluted Shares Outstanding (M) | B8: 3760
A9: Implied Equity Market Capitalization ($M) | B9: =B7*B8
A10: Cash, Cash Equivalents & ST Investments ($M) | B10: 44059
A11: Total Debt (Current + Noncurrent + Leases) ($M) | B11: 8376
A12: Net Debt ($M) | B12: =B11-B10
A13: Implied Enterprise Value ($M) | B13: =B9+B12
A14: Effective Corporate Tax Rate (%) | B14: 0.21
A15: Risk-Free Rate (10-Yr US Treasury) (%) | B15: ='WACC Build'!B5
A16: Equity Beta (5-Year Monthly) | B16: ='WACC Build'!B6
A17: Market Equity Risk Premium (ERP) (%) | B17: ='WACC Build'!B7
A18: Base Case WACC (%) | B18: ='WACC Build'!E26
A20: II. SCENARIO ASSUMPTIONS & DRIVER BLOCKS
A21: Driver / Assumption | B21: FY2025A | C21: FY2026E | D21: FY2027E | E21: FY2028E | F21: FY2029E | G21: FY2030E | H21: Terminal / WACC
A22: Bear Case Assumptions (Selector = 1)
A23: Revenue Growth (%) | B23: - | C23: 0.05 | D23: 0.06 | E23: 0.07 | F23: 0.06 | G23: 0.05 | H23: 0.025
A24: EBIT Margin (%) | B24: - | C24: 0.05 | D24: 0.06 | E24: 0.07 | F24: 0.075 | G24: 0.08 | H24: 0.155
A25: D&A (% of Revenue) | B25: - | C25: 0.065 | D25: 0.063 | E25: 0.06 | F25: 0.058 | G25: 0.055 | H25: -
A26: CapEx (% of Revenue) | B26: - | C26: 0.09 | D26: 0.088 | E26: 0.085 | F26: 0.082 | G26: 0.08 | H26: -
A27: Δ NWC (% of Δ Revenue) | B27: - | C27: 0.03 | D27: 0.03 | E27: 0.03 | F27: 0.03 | G27: 0.03 | H27: -
A29: Base Case Assumptions (Selector = 2)
A30: Revenue Growth (%) | B30: - | C30: 0.11 | D30: 0.15 | E30: 0.16 | F30: 0.14 | G30: 0.12 | H30: 0.03
A31: EBIT Margin (%) | B31: - | C31: 0.06 | D31: 0.08 | E31: 0.105 | F31: 0.122 | G31: 0.138 | H31: ='WACC Build'!E26
A32: D&A (% of Revenue) | B32: - | C32: 0.058 | D32: 0.055 | E32: 0.052 | F32: 0.05 | G32: 0.048 | H32: -
A33: CapEx (% of Revenue) | B33: - | C33: 0.085 | D33: 0.08 | E33: 0.075 | F33: 0.07 | G33: 0.065 | H33: -
A34: Δ NWC (% of Δ Revenue) | B34: - | C34: 0.025 | D34: 0.025 | E34: 0.025 | F34: 0.025 | G34: 0.025 | H34: -
A36: Bull Case Assumptions (Selector = 3)
A37: Revenue Growth (%) | B37: - | C37: 0.18 | D37: 0.25 | E37: 0.28 | F37: 0.24 | G37: 0.2 | H37: 0.04
A38: EBIT Margin (%) | B38: - | C38: 0.085 | D38: 0.13 | E38: 0.175 | F38: 0.205 | G38: 0.23 | H38: 0.135
A39: D&A (% of Revenue) | B39: - | C39: 0.055 | D39: 0.052 | E39: 0.05 | F39: 0.048 | G39: 0.045 | H39: -
A40: CapEx (% of Revenue) | B40: - | C40: 0.08 | D40: 0.075 | E40: 0.07 | F40: 0.065 | G40: 0.06 | H40: -
A41: Δ NWC (% of Δ Revenue) | B41: - | C41: 0.02 | D41: 0.02 | E41: 0.02 | F41: 0.02 | G41: 0.02 | H41: -
A43: ACTIVE CONSOLIDATED DRIVERS (PULLED VIA INDEX FORMULAS)
A44: Active Revenue Growth (%) | B44: - | C44: =INDEX((C$23,C$30,C$37),1,1,$B$4) | D44: =INDEX((D$23,D$30,D$37),1,1,$B$4) | E44: =INDEX((E$23,E$30,E$37),1,1,$B$4) | F44: =INDEX((F$23,F$30,F$37),1,1,$B$4) | G44: =INDEX((G$23,G$30,G$37),1,1,$B$4) | H44: =INDEX((H$23,H$30,H$37),1,1,$B$4)
A45: Active EBIT Margin (%) | B45: - | C45: =INDEX((C$24,C$31,C$38),1,1,$B$4) | D45: =INDEX((D$24,D$31,D$38),1,1,$B$4) | E45: =INDEX((E$24,E$31,E$38),1,1,$B$4) | F45: =INDEX((F$24,F$31,F$38),1,1,$B$4) | G45: =INDEX((G$24,G$31,G$38),1,1,$B$4) | H45: =INDEX((H$24,H$31,H$38),1,1,$B$4)
A46: Active D&A (% of Revenue) | B46: - | C46: =INDEX((C$25,C$32,C$39),1,1,$B$4) | D46: =INDEX((D$25,D$32,D$39),1,1,$B$4) | E46: =INDEX((E$25,E$32,E$39),1,1,$B$4) | F46: =INDEX((F$25,F$32,F$39),1,1,$B$4) | G46: =INDEX((G$25,G$32,G$39),1,1,$B$4) | H46: -
A47: Active CapEx (% of Revenue) | B47: - | C47: =INDEX((C$26,C$33,C$40),1,1,$B$4) | D47: =INDEX((D$26,D$33,D$40),1,1,$B$4) | E47: =INDEX((E$26,E$33,E$40),1,1,$B$4) | F47: =INDEX((F$26,F$33,F$40),1,1,$B$4) | G47: =INDEX((G$26,G$33,G$40),1,1,$B$4) | H47: -
A48: Active Δ NWC (% of Δ Revenue) | B48: - | C48: =INDEX((C$27,C$34,C$41),1,1,$B$4) | D48: =INDEX((D$27,D$34,D$41),1,1,$B$4) | E48: =INDEX((E$27,E$34,E$41),1,1,$B$4) | F48: =INDEX((F$27,F$34,F$41),1,1,$B$4) | G48: =INDEX((G$27,G$34,G$41),1,1,$B$4) | H48: -
A51: III. FINANCIAL PERFORMANCE & 5-YEAR PROJECTIONS ($M)
A52: Line Item ($M) | B52: FY2025A | C52: FY2026E | D52: FY2027E | E52: FY2028E | F52: FY2029E | G52: FY2030E | H52: Terminal Year
A53: Total Revenue | B53: 94827 | C53: =B53*(1+C44) | D53: =C53*(1+D44) | E53: =D53*(1+E44) | F53: =E53*(1+F44) | G53: =F53*(1+G44) | H53: =G53*(1+H44)
A54: YoY Revenue Growth (%) | B54: - | C54: =C53/B53-1 | D54: =D53/C53-1 | E54: =E53/D53-1 | F54: =F53/E53-1 | G54: =G53/F53-1 | H54: =H53/G53-1
A55: Operating Income (EBIT) | B55: 4355 | C55: =C53*C45 | D55: =D53*D45 | E55: =E53*E45 | F55: =F53*F45 | G55: =G53*G45 | H55: =H53*G45
A56: EBIT Margin (%) | B56: =B55/B53 | C56: =C55/C53 | D56: =D55/D53 | E56: =E55/E53 | F56: =F55/F53 | G56: =G55/G53 | H56: =H55/H53
A57: (-) Taxes on EBIT | B57: =IF(B55>0,B55*$B$14,0) | C57: =IF(C55>0,C55*$B$14,0) | D57: =IF(D55>0,D55*$B$14,0) | E57: =IF(E55>0,E55*$B$14,0) | F57: =IF(F55>0,F55*$B$14,0) | G57: =IF(G55>0,G55*$B$14,0) | H57: =IF(H55>0,H55*$B$14,0)
A58: Net Operating Profit After Tax (NOPAT) | B58: =B55-B57 | C58: =C55-C57 | D58: =D55-D57 | E58: =E55-E57 | F58: =F55-F57 | G58: =G55-G57 | H58: =H55-H57
A60: IV. UNLEVERED FREE CASH FLOW (UFCF) BUILD ($M)
A61: Cash Flow Line Item ($M) | B61: FY2025A | C61: FY2026E | D61: FY2027E | E61: FY2028E | F61: FY2029E | G61: FY2030E | H61: Terminal Year
A62: Net Operating Profit After Tax (NOPAT) | B62: =B58 | C62: =C58 | D62: =D58 | E62: =E58 | F62: =F58 | G62: =G58 | H62: =H58
A63: (+) Depreciation & Amortization (D&A) | B63: 6200 | C63: =C53*C46 | D63: =D53*D46 | E63: =E53*E46 | F63: =F53*F46 | G63: =G53*G46 | H63: =H53*G46
A64: (-) Capital Expenditures (CapEx) | B64: 8530 | C64: =C53*C47 | D64: =D53*D47 | E64: =E53*E47 | F64: =F53*F47 | G64: =G53*G47 | H64: =H53*G47
A65: (-) Change in Net Working Capital (Δ NWC) | B65: -1450 | C65: =(C53-B53)*C48 | D65: =(D53-C53)*D48 | E65: =(E53-D53)*E48 | F65: =(F53-E53)*F48 | G65: =(G53-F53)*G48 | H65: =(H53-G53)*G48
A66: Unlevered Free Cash Flow (UFCF) | B66: =B62+B63-B64-B65 | C66: =C62+C63-C64-C65 | D66: =D62+D63-D64-D65 | E66: =E62+E63-E64-E65 | F66: =F62+F63-F64-F65 | G66: =G62+G63-G64-G65 | H66: =H62+H63-H64-H65
A67: FCF Conversion Margin (% of Revenue) | B67: =B66/B53 | C67: =C66/C53 | D67: =D66/D53 | E67: =E66/E53 | F67: =F66/F53 | G67: =G66/G53 | H67: =H66/H53
A69: V. DISCOUNTING SCHEDULE & VALUATION SUMMARY ($M)
A70: DCF Component ($M) | B70: FY2026E | C70: FY2027E | D70: FY2028E | E70: FY2029E | F70: FY2030E | G70: Terminal Year
A71: Unlevered Free Cash Flow (UFCF) | B71: =C66 | C71: =D66 | D71: =E66 | E71: =F66 | F71: =G66 | G71: =F71*(1+$H$44) | H71: -
A72: Mid-Year Discount Period (t) | B72: 0.5 | C72: 1.5 | D72: 2.5 | E72: 3.5 | F72: 4.5 | G72: 4.5 | H72: -
A73: Discount Factor (WACC Discounting) | B73: =1/(1+$H$45)^B72 | C73: =1/(1+$H$45)^C72 | D73: =1/(1+$H$45)^D72 | E73: =1/(1+$H$45)^E72 | F73: =1/(1+$H$45)^F72 | G73: =1/(1+$H$45)^G72 | H73: -
A74: Present Value of Cash Flow (PV of UFCF) | B74: =B71*B73 | C74: =C71*C73 | D74: =D71*D73 | E74: =E71*E73 | F74: =F71*F73 | G74: - | H74: -
A75: Nominal Terminal Value (Perpetuity Growth Method) | B75: - | C75: - | D75: - | E75: - | F75: - | G75: =G71/($H$45-$H$44) | H75: -
A76: Present Value of Terminal Value (PV of TV) | B76: - | C76: - | D76: - | E76: - | F76: - | G76: =G75*G73 | H76: -
A78: VALUATION BRIDGE & PER-SHARE IMPLICATION
A79: Cumulative PV of Explicit 5-Year FCFs ($M) | B79: =SUM(B74:F74) | D79: Terminal Value Metrics & Checks:
A80: Present Value of Terminal Value ($M) | B80: =G76 | D80: PV of TV % of Enterprise Value | E80: =B80/B81
A81: Enterprise Value ($M) | B81: =B79+B80 | D81: Implied Exit Multiple (EV / FY30E EBITDA) | E81: =B81/(G55+G63)
A82: (-) Total Debt ($M) | B82: =-B11
A83: (+) Cash, Cash Equivalents & ST Investments ($M) | B83: =B10
A84: Net Debt Adjustment ($M) | B84: =B82+B83
A85: Implied Equity Value ($M) | B85: =B81+B84
A86: Diluted Shares Outstanding (M) | B86: =B8
A87: IMPLIED INTRINSIC VALUE PER SHARE ($) | B87: =B85/B86
A88: Current Market Stock Price ($) | B88: =B7
A89: Implied Upside / (Downside) (%) | B89: =B87/B88-1
A92: VI. INSTITUTIONAL SENSITIVITY MATRICES (5x5 GRIDS WITH FULL DCF RECALCULATION)
A94: TABLE 1: IMPLIED SHARE PRICE ($) - WACC vs. TERMINAL GROWTH RATE (g)
A95: WACC \ Terminal g | B95: 0.02 | C95: 0.025 | D95: 0.03 | E95: 0.035 | F95: 0.04
A96: 0.1296 | B96: =(($B$71/(1+$A96)^0.5 + $C$71/(1+$A96)^1.5 + $D$71/(1+$A96)^2.5 + $E$71/(1+$A96)^3.5 + $F$71/(1+$A96)^4.5) + (($F$71*(1+B$95)/($A96-B$95))/(1+$A96)^4.5) + $B$84)/$B$86 | C96: =(($B$71/(1+$A96)^0.5 + $C$71/(1+$A96)^1.5 + $D$71/(1+$A96)^2.5 + $E$71/(1+$A96)^3.5 + $F$71/(1+$A96)^4.5) + (($F$71*(1+C$95)/($A96-C$95))/(1+$A96)^4.5) + $B$84)/$B$86 | D96: =(($B$71/(1+$A96)^0.5 + $C$71/(1+$A96)^1.5 + $D$71/(1+$A96)^2.5 + $E$71/(1+$A96)^3.5 + $F$71/(1+$A96)^4.5) + (($F$71*(1+D$95)/($A96-D$95))/(1+$A96)^4.5) + $B$84)/$B$86 | E96: =(($B$71/(1+$A96)^0.5 + $C$71/(1+$A96)^1.5 + $D$71/(1+$A96)^2.5 + $E$71/(1+$A96)^3.5 + $F$71/(1+$A96)^4.5) + (($F$71*(1+E$95)/($A96-E$95))/(1+$A96)^4.5) + $B$84)/$B$86 | F96: =(($B$71/(1+$A96)^0.5 + $C$71/(1+$A96)^1.5 + $D$71/(1+$A96)^2.5 + $E$71/(1+$A96)^3.5 + $F$71/(1+$A96)^4.5) + (($F$71*(1+F$95)/($A96-F$95))/(1+$A96)^4.5) + $B$84)/$B$86
A97: 0.1396 | B97: =(($B$71/(1+$A97)^0.5 + $C$71/(1+$A97)^1.5 + $D$71/(1+$A97)^2.5 + $E$71/(1+$A97)^3.5 + $F$71/(1+$A97)^4.5) + (($F$71*(1+B$95)/($A97-B$95))/(1+$A97)^4.5) + $B$84)/$B$86 | C97: =(($B$71/(1+$A97)^0.5 + $C$71/(1+$A97)^1.5 + $D$71/(1+$A97)^2.5 + $E$71/(1+$A97)^3.5 + $F$71/(1+$A97)^4.5) + (($F$71*(1+C$95)/($A97-C$95))/(1+$A97)^4.5) + $B$84)/$B$86 | D97: =(($B$71/(1+$A97)^0.5 + $C$71/(1+$A97)^1.5 + $D$71/(1+$A97)^2.5 + $E$71/(1+$A97)^3.5 + $F$71/(1+$A97)^4.5) + (($F$71*(1+D$95)/($A97-D$95))/(1+$A97)^4.5) + $B$84)/$B$86 | E97: =(($B$71/(1+$A97)^0.5 + $C$71/(1+$A97)^1.5 + $D$71/(1+$A97)^2.5 + $E$71/(1+$A97)^3.5 + $F$71/(1+$A97)^4.5) + (($F$71*(1+E$95)/($A97-E$95))/(1+$A97)^4.5) + $B$84)/$B$86 | F97: =(($B$71/(1+$A97)^0.5 + $C$71/(1+$A97)^1.5 + $D$71/(1+$A97)^2.5 + $E$71/(1+$A97)^3.5 + $F$71/(1+$A97)^4.5) + (($F$71*(1+F$95)/($A97-F$95))/(1+$A97)^4.5) + $B$84)/$B$86
A98: 0.1496 | B98: =(($B$71/(1+$A98)^0.5 + $C$71/(1+$A98)^1.5 + $D$71/(1+$A98)^2.5 + $E$71/(1+$A98)^3.5 + $F$71/(1+$A98)^4.5) + (($F$71*(1+B$95)/($A98-B$95))/(1+$A98)^4.5) + $B$84)/$B$86 | C98: =(($B$71/(1+$A98)^0.5 + $C$71/(1+$A98)^1.5 + $D$71/(1+$A98)^2.5 + $E$71/(1+$A98)^3.5 + $F$71/(1+$A98)^4.5) + (($F$71*(1+C$95)/($A98-C$95))/(1+$A98)^4.5) + $B$84)/$B$86 | D98: =(($B$71/(1+$A98)^0.5 + $C$71/(1+$A98)^1.5 + $D$71/(1+$A98)^2.5 + $E$71/(1+$A98)^3.5 + $F$71/(1+$A98)^4.5) + (($F$71*(1+D$95)/($A98-D$95))/(1+$A98)^4.5) + $B$84)/$B$86 | E98: =(($B$71/(1+$A98)^0.5 + $C$71/(1+$A98)^1.5 + $D$71/(1+$A98)^2.5 + $E$71/(1+$A98)^3.5 + $F$71/(1+$A98)^4.5) + (($F$71*(1+E$95)/($A98-E$95))/(1+$A98)^4.5) + $B$84)/$B$86 | F98: =(($B$71/(1+$A98)^0.5 + $C$71/(1+$A98)^1.5 + $D$71/(1+$A98)^2.5 + $E$71/(1+$A98)^3.5 + $F$71/(1+$A98)^4.5) + (($F$71*(1+F$95)/($A98-F$95))/(1+$A98)^4.5) + $B$84)/$B$86
A99: 0.1596 | B99: =(($B$71/(1+$A99)^0.5 + $C$71/(1+$A99)^1.5 + $D$71/(1+$A99)^2.5 + $E$71/(1+$A99)^3.5 + $F$71/(1+$A99)^4.5) + (($F$71*(1+B$95)/($A99-B$95))/(1+$A99)^4.5) + $B$84)/$B$86 | C99: =(($B$71/(1+$A99)^0.5 + $C$71/(1+$A99)^1.5 + $D$71/(1+$A99)^2.5 + $E$71/(1+$A99)^3.5 + $F$71/(1+$A99)^4.5) + (($F$71*(1+C$95)/($A99-C$95))/(1+$A99)^4.5) + $B$84)/$B$86 | D99: =(($B$71/(1+$A99)^0.5 + $C$71/(1+$A99)^1.5 + $D$71/(1+$A99)^2.5 + $E$71/(1+$A99)^3.5 + $F$71/(1+$A99)^4.5) + (($F$71*(1+D$95)/($A99-D$95))/(1+$A99)^4.5) + $B$84)/$B$86 | E99: =(($B$71/(1+$A99)^0.5 + $C$71/(1+$A99)^1.5 + $D$71/(1+$A99)^2.5 + $E$71/(1+$A99)^3.5 + $F$71/(1+$A99)^4.5) + (($F$71*(1+E$95)/($A99-E$95))/(1+$A99)^4.5) + $B$84)/$B$86 | F99: =(($B$71/(1+$A99)^0.5 + $C$71/(1+$A99)^1.5 + $D$71/(1+$A99)^2.5 + $E$71/(1+$A99)^3.5 + $F$71/(1+$A99)^4.5) + (($F$71*(1+F$95)/($A99-F$95))/(1+$A99)^4.5) + $B$84)/$B$86
A100: 0.1696 | B100: =(($B$71/(1+$A100)^0.5 + $C$71/(1+$A100)^1.5 + $D$71/(1+$A100)^2.5 + $E$71/(1+$A100)^3.5 + $F$71/(1+$A100)^4.5) + (($F$71*(1+B$95)/($A100-B$95))/(1+$A100)^4.5) + $B$84)/$B$86 | C100: =(($B$71/(1+$A100)^0.5 + $C$71/(1+$A100)^1.5 + $D$71/(1+$A100)^2.5 + $E$71/(1+$A100)^3.5 + $F$71/(1+$A100)^4.5) + (($F$71*(1+C$95)/($A100-C$95))/(1+$A100)^4.5) + $B$84)/$B$86 | D100: =(($B$71/(1+$A100)^0.5 + $C$71/(1+$A100)^1.5 + $D$71/(1+$A100)^2.5 + $E$71/(1+$A100)^3.5 + $F$71/(1+$A100)^4.5) + (($F$71*(1+D$95)/($A100-D$95))/(1+$A100)^4.5) + $B$84)/$B$86 | E100: =(($B$71/(1+$A100)^0.5 + $C$71/(1+$A100)^1.5 + $D$71/(1+$A100)^2.5 + $E$71/(1+$A100)^3.5 + $F$71/(1+$A100)^4.5) + (($F$71*(1+E$95)/($A100-E$95))/(1+$A100)^4.5) + $B$84)/$B$86 | F100: =(($B$71/(1+$A100)^0.5 + $C$71/(1+$A100)^1.5 + $D$71/(1+$A100)^2.5 + $E$71/(1+$A100)^3.5 + $F$71/(1+$A100)^4.5) + (($F$71*(1+F$95)/($A100-F$95))/(1+$A100)^4.5) + $B$84)/$B$86
A104: TABLE 2: IMPLIED SHARE PRICE ($) - REVENUE GROWTH MULTIPLIER vs. FY30E EBIT MARGIN
A105: Growth Index \ EBIT Margin | B105: 0.098 | C105: 0.118 | D105: 0.138 | E105: 0.158 | F105: 0.178
A106: 0.8 | B106: =((($B$71*$A106*(B$105/$G$45)/(1+$H$45)^0.5 + $C$71*$A106*(B$105/$G$45)/(1+$H$45)^1.5 + $D$71*$A106*(B$105/$G$45)/(1+$H$45)^2.5 + $E$71*$A106*(B$105/$G$45)/(1+$H$45)^3.5 + $F$71*$A106*(B$105/$G$45)/(1+$H$45)^4.5) + (($F$71*$A106*(B$105/$G$45)*(1+$H$44)/($H$45-$H$44))/(1+$H$45)^4.5) + $B$84)/$B$86) | C106: =((($B$71*$A106*(C$105/$G$45)/(1+$H$45)^0.5 + $C$71*$A106*(C$105/$G$45)/(1+$H$45)^1.5 + $D$71*$A106*(C$105/$G$45)/(1+$H$45)^2.5 + $E$71*$A106*(C$105/$G$45)/(1+$H$45)^3.5 + $F$71*$A106*(C$105/$G$45)/(1+$H$45)^4.5) + (($F$71*$A106*(C$105/$G$45)*(1+$H$44)/($H$45-$H$44))/(1+$H$45)^4.5) + $B$84)/$B$86) | D106: =((($B$71*$A106*(D$105/$G$45)/(1+$H$45)^0.5 + $C$71*$A106*(D$105/$G$45)/(1+$H$45)^1.5 + $D$71*$A106*(D$105/$G$45)/(1+$H$45)^2.5 + $E$71*$A106*(D$105/$G$45)/(1+$H$45)^3.5 + $F$71*$A106*(D$105/$G$45)/(1+$H$45)^4.5) + (($F$71*$A106*(D$105/$G$45)*(1+$H$44)/($H$45-$H$44))/(1+$H$45)^4.5) + $B$84)/$B$86) | E106: =((($B$71*$A106*(E$105/$G$45)/(1+$H$45)^0.5 + $C$71*$A106*(E$105/$G$45)/(1+$H$45)^1.5 + $D$71*$A106*(E$105/$G$45)/(1+$H$45)^2.5 + $E$71*$A106*(E$105/$G$45)/(1+$H$45)^3.5 + $F$71*$A106*(E$105/$G$45)/(1+$H$45)^4.5) + (($F$71*$A106*(E$105/$G$45)*(1+$H$44)/($H$45-$H$44))/(1+$H$45)^4.5) + $B$84)/$B$86) | F106: =((($B$71*$A106*(F$105/$G$45)/(1+$H$45)^0.5 + $C$71*$A106*(F$105/$G$45)/(1+$H$45)^1.5 + $D$71*$A106*(F$105/$G$45)/(1+$H$45)^2.5 + $E$71*$A106*(F$105/$G$45)/(1+$H$45)^3.5 + $F$71*$A106*(F$105/$G$45)/(1+$H$45)^4.5) + (($F$71*$A106*(F$105/$G$45)*(1+$H$44)/($H$45-$H$44))/(1+$H$45)^4.5) + $B$84)/$B$86)
A107: 0.9 | B107: =((($B$71*$A107*(B$105/$G$45)/(1+$H$45)^0.5 + $C$71*$A107*(B$105/$G$45)/(1+$H$45)^1.5 + $D$71*$A107*(B$105/$G$45)/(1+$H$45)^2.5 + $E$71*$A107*(B$105/$G$45)/(1+$H$45)^3.5 + $F$71*$A107*(B$105/$G$45)/(1+$H$45)^4.5) + (($F$71*$A107*(B$105/$G$45)*(1+$H$44)/($H$45-$H$44))/(1+$H$45)^4.5) + $B$84)/$B$86) | C107: =((($B$71*$A107*(C$105/$G$45)/(1+$H$45)^0.5 + $C$71*$A107*(C$105/$G$45)/(1+$H$45)^1.5 + $D$71*$A107*(C$105/$G$45)/(1+$H$45)^2.5 + $E$71*$A107*(C$105/$G$45)/(1+$H$45)^3.5 + $F$71*$A107*(C$105/$G$45)/(1+$H$45)^4.5) + (($F$71*$A107*(C$105/$G$45)*(1+$H$44)/($H$45-$H$44))/(1+$H$45)^4.5) + $B$84)/$B$86) | D107: =((($B$71*$A107*(D$105/$G$45)/(1+$H$45)^0.5 + $C$71*$A107*(D$105/$G$45)/(1+$H$45)^1.5 + $D$71*$A107*(D$105/$G$45)/(1+$H$45)^2.5 + $E$71*$A107*(D$105/$G$45)/(1+$H$45)^3.5 + $F$71*$A107*(D$105/$G$45)/(1+$H$45)^4.5) + (($F$71*$A107*(D$105/$G$45)*(1+$H$44)/($H$45-$H$44))/(1+$H$45)^4.5) + $B$84)/$B$86) | E107: =((($B$71*$A107*(E$105/$G$45)/(1+$H$45)^0.5 + $C$71*$A107*(E$105/$G$45)/(1+$H$45)^1.5 + $D$71*$A107*(E$105/$G$45)/(1+$H$45)^2.5 + $E$71*$A107*(E$105/$G$45)/(1+$H$45)^3.5 + $F$71*$A107*(E$105/$G$45)/(1+$H$45)^4.5) + (($F$71*$A107*(E$105/$G$45)*(1+$H$44)/($H$45-$H$44))/(1+$H$45)^4.5) + $B$84)/$B$86) | F107: =((($B$71*$A107*(F$105/$G$45)/(1+$H$45)^0.5 + $C$71*$A107*(F$105/$G$45)/(1+$H$45)^1.5 + $D$71*$A107*(F$105/$G$45)/(1+$H$45)^2.5 + $E$71*$A107*(F$105/$G$45)/(1+$H$45)^3.5 + $F$71*$A107*(F$105/$G$45)/(1+$H$45)^4.5) + (($F$71*$A107*(F$105/$G$45)*(1+$H$44)/($H$45-$H$44))/(1+$H$45)^4.5) + $B$84)/$B$86)
A108: 1 | B108: =((($B$71*$A108*(B$105/$G$45)/(1+$H$45)^0.5 + $C$71*$A108*(B$105/$G$45)/(1+$H$45)^1.5 + $D$71*$A108*(B$105/$G$45)/(1+$H$45)^2.5 + $E$71*$A108*(B$105/$G$45)/(1+$H$45)^3.5 + $F$71*$A108*(B$105/$G$45)/(1+$H$45)^4.5) + (($F$71*$A108*(B$105/$G$45)*(1+$H$44)/($H$45-$H$44))/(1+$H$45)^4.5) + $B$84)/$B$86) | C108: =((($B$71*$A108*(C$105/$G$45)/(1+$H$45)^0.5 + $C$71*$A108*(C$105/$G$45)/(1+$H$45)^1.5 + $D$71*$A108*(C$105/$G$45)/(1+$H$45)^2.5 + $E$71*$A108*(C$105/$G$45)/(1+$H$45)^3.5 + $F$71*$A108*(C$105/$G$45)/(1+$H$45)^4.5) + (($F$71*$A108*(C$105/$G$45)*(1+$H$44)/($H$45-$H$44))/(1+$H$45)^4.5) + $B$84)/$B$86) | D108: =((($B$71*$A108*(D$105/$G$45)/(1+$H$45)^0.5 + $C$71*$A108*(D$105/$G$45)/(1+$H$45)^1.5 + $D$71*$A108*(D$105/$G$45)/(1+$H$45)^2.5 + $E$71*$A108*(D$105/$G$45)/(1+$H$45)^3.5 + $F$71*$A108*(D$105/$G$45)/(1+$H$45)^4.5) + (($F$71*$A108*(D$105/$G$45)*(1+$H$44)/($H$45-$H$44))/(1+$H$45)^4.5) + $B$84)/$B$86) | E108: =((($B$71*$A108*(E$105/$G$45)/(1+$H$45)^0.5 + $C$71*$A108*(E$105/$G$45)/(1+$H$45)^1.5 + $D$71*$A108*(E$105/$G$45)/(1+$H$45)^2.5 + $E$71*$A108*(E$105/$G$45)/(1+$H$45)^3.5 + $F$71*$A108*(E$105/$G$45)/(1+$H$45)^4.5) + (($F$71*$A108*(E$105/$G$45)*(1+$H$44)/($H$45-$H$44))/(1+$H$45)^4.5) + $B$84)/$B$86) | F108: =((($B$71*$A108*(F$105/$G$45)/(1+$H$45)^0.5 + $C$71*$A108*(F$105/$G$45)/(1+$H$45)^1.5 + $D$71*$A108*(F$105/$G$45)/(1+$H$45)^2.5 + $E$71*$A108*(F$105/$G$45)/(1+$H$45)^3.5 + $F$71*$A108*(F$105/$G$45)/(1+$H$45)^4.5) + (($F$71*$A108*(F$105/$G$45)*(1+$H$44)/($H$45-$H$44))/(1+$H$45)^4.5) + $B$84)/$B$86)
A109: 1.1 | B109: =((($B$71*$A109*(B$105/$G$45)/(1+$H$45)^0.5 + $C$71*$A109*(B$105/$G$45)/(1+$H$45)^1.5 + $D$71*$A109*(B$105/$G$45)/(1+$H$45)^2.5 + $E$71*$A109*(B$105/$G$45)/(1+$H$45)^3.5 + $F$71*$A109*(B$105/$G$45)/(1+$H$45)^4.5) + (($F$71*$A109*(B$105/$G$45)*(1+$H$44)/($H$45-$H$44))/(1+$H$45)^4.5) + $B$84)/$B$86) | C109: =((($B$71*$A109*(C$105/$G$45)/(1+$H$45)^0.5 + $C$71*$A109*(C$105/$G$45)/(1+$H$45)^1.5 + $D$71*$A109*(C$105/$G$45)/(1+$H$45)^2.5 + $E$71*$A109*(C$105/$G$45)/(1+$H$45)^3.5 + $F$71*$A109*(C$105/$G$45)/(1+$H$45)^4.5) + (($F$71*$A109*(C$105/$G$45)*(1+$H$44)/($H$45-$H$44))/(1+$H$45)^4.5) + $B$84)/$B$86) | D109: =((($B$71*$A109*(D$105/$G$45)/(1+$H$45)^0.5 + $C$71*$A109*(D$105/$G$45)/(1+$H$45)^1.5 + $D$71*$A109*(D$105/$G$45)/(1+$H$45)^2.5 + $E$71*$A109*(D$105/$G$45)/(1+$H$45)^3.5 + $F$71*$A109*(D$105/$G$45)/(1+$H$45)^4.5) + (($F$71*$A109*(D$105/$G$45)*(1+$H$44)/($H$45-$H$44))/(1+$H$45)^4.5) + $B$84)/$B$86) | E109: =((($B$71*$A109*(E$105/$G$45)/(1+$H$45)^0.5 + $C$71*$A109*(E$105/$G$45)/(1+$H$45)^1.5 + $D$71*$A109*(E$105/$G$45)/(1+$H$45)^2.5 + $E$71*$A109*(E$105/$G$45)/(1+$H$45)^3.5 + $F$71*$A109*(E$105/$G$45)/(1+$H$45)^4.5) + (($F$71*$A109*(E$105/$G$45)*(1+$H$44)/($H$45-$H$44))/(1+$H$45)^4.5) + $B$84)/$B$86) | F109: =((($B$71*$A109*(F$105/$G$45)/(1+$H$45)^0.5 + $C$71*$A109*(F$105/$G$45)/(1+$H$45)^1.5 + $D$71*$A109*(F$105/$G$45)/(1+$H$45)^2.5 + $E$71*$A109*(F$105/$G$45)/(1+$H$45)^3.5 + $F$71*$A109*(F$105/$G$45)/(1+$H$45)^4.5) + (($F$71*$A109*(F$105/$G$45)*(1+$H$44)/($H$45-$H$44))/(1+$H$45)^4.5) + $B$84)/$B$86)
A110: 1.2 | B110: =((($B$71*$A110*(B$105/$G$45)/(1+$H$45)^0.5 + $C$71*$A110*(B$105/$G$45)/(1+$H$45)^1.5 + $D$71*$A110*(B$105/$G$45)/(1+$H$45)^2.5 + $E$71*$A110*(B$105/$G$45)/(1+$H$45)^3.5 + $F$71*$A110*(B$105/$G$45)/(1+$H$45)^4.5) + (($F$71*$A110*(B$105/$G$45)*(1+$H$44)/($H$45-$H$44))/(1+$H$45)^4.5) + $B$84)/$B$86) | C110: =((($B$71*$A110*(C$105/$G$45)/(1+$H$45)^0.5 + $C$71*$A110*(C$105/$G$45)/(1+$H$45)^1.5 + $D$71*$A110*(C$105/$G$45)/(1+$H$45)^2.5 + $E$71*$A110*(C$105/$G$45)/(1+$H$45)^3.5 + $F$71*$A110*(C$105/$G$45)/(1+$H$45)^4.5) + (($F$71*$A110*(C$105/$G$45)*(1+$H$44)/($H$45-$H$44))/(1+$H$45)^4.5) + $B$84)/$B$86) | D110: =((($B$71*$A110*(D$105/$G$45)/(1+$H$45)^0.5 + $C$71*$A110*(D$105/$G$45)/(1+$H$45)^1.5 + $D$71*$A110*(D$105/$G$45)/(1+$H$45)^2.5 + $E$71*$A110*(D$105/$G$45)/(1+$H$45)^3.5 + $F$71*$A110*(D$105/$G$45)/(1+$H$45)^4.5) + (($F$71*$A110*(D$105/$G$45)*(1+$H$44)/($H$45-$H$44))/(1+$H$45)^4.5) + $B$84)/$B$86) | E110: =((($B$71*$A110*(E$105/$G$45)/(1+$H$45)^0.5 + $C$71*$A110*(E$105/$G$45)/(1+$H$45)^1.5 + $D$71*$A110*(E$105/$G$45)/(1+$H$45)^2.5 + $E$71*$A110*(E$105/$G$45)/(1+$H$45)^3.5 + $F$71*$A110*(E$105/$G$45)/(1+$H$45)^4.5) + (($F$71*$A110*(E$105/$G$45)*(1+$H$44)/($H$45-$H$44))/(1+$H$45)^4.5) + $B$84)/$B$86) | F110: =((($B$71*$A110*(F$105/$G$45)/(1+$H$45)^0.5 + $C$71*$A110*(F$105/$G$45)/(1+$H$45)^1.5 + $D$71*$A110*(F$105/$G$45)/(1+$H$45)^2.5 + $E$71*$A110*(F$105/$G$45)/(1+$H$45)^3.5 + $F$71*$A110*(F$105/$G$45)/(1+$H$45)^4.5) + (($F$71*$A110*(F$105/$G$45)*(1+$H$44)/($H$45-$H$44))/(1+$H$45)^4.5) + $B$84)/$B$86)
A114: TABLE 3: IMPLIED ESTIMATE ($) - EQUITY BETA vs. RISK-FREE RATE (Rf)
A115: Beta \ Risk-Free Rate | B115: 0.0365 | C115: 0.0415 | D115: 0.0465 | E115: 0.0515 | F115: 0.0565
A116: 1.42 | B116: =((($B$71/(1+((B$115+$A116*$B$17)*('WACC Build'!$C$24) + ('WACC Build'!$B$13)*('WACC Build'!$C$25)))^0.5 + $C$71/(1+((B$115+$A116*$B$17)*('WACC Build'!$C$24) + ('WACC Build'!$B$13)*('WACC Build'!$C$25)))^1.5 + $D$71/(1+((B$115+$A116*$B$17)*('WACC Build'!$C$24) + ('WACC Build'!$B$13)*('WACC Build'!$C$25)))^2.5 + $E$71/(1+((B$115+$A116*$B$17)*('WACC Build'!$C$24) + ('WACC Build'!$B$13)*('WACC Build'!$C$25)))^3.5 + $F$71/(1+((B$115+$A116*$B$17)*('WACC Build'!$C$24) + ('WACC Build'!$B$13)*('WACC Build'!$C$25)))^4.5) + (($F$71*(1+$H$44)/(((B$115+$A116*$B$17)*('WACC Build'!$C$24) + ('WACC Build'!$B$13)*('WACC Build'!$C$25))-$H$44))/(1+((B$115+$A116*$B$17)*('WACC Build'!$C$24) + ('WACC Build'!$B$13)*('WACC Build'!$C$25)))^4.5) + $B$84)/$B$86) | C116: =((($B$71/(1+((C$115+$A116*$B$17)*('WACC Build'!$C$24) + ('WACC Build'!$B$13)*('WACC Build'!$C$25)))^0.5 + $C$71/(1+((C$115+$A116*$B$17)*('WACC Build'!$C$24) + ('WACC Build'!$B$13)*('WACC Build'!$C$25)))^1.5 + $D$71/(1+((C$115+$A116*$B$17)*('WACC Build'!$C$24) + ('WACC Build'!$B$13)*('WACC Build'!$C$25)))^2.5 + $E$71/(1+((C$115+$A116*$B$17)*('WACC Build'!$C$24) + ('WACC Build'!$B$13)*('WACC Build'!$C$25)))^3.5 + $F$71/(1+((C$115+$A116*$B$17)*('WACC Build'!$C$24) + ('WACC Build'!$B$13)*('WACC Build'!$C$25)))^4.5) + (($F$71*(1+$H$44)/(((C$115+$A116*$B$17)*('WACC Build'!$C$24) + ('WACC Build'!$B$13)*('WACC Build'!$C$25))-$H$44))/(1+((C$115+$A116*$B$17)*('WACC Build'!$C$24) + ('WACC Build'!$B$13)*('WACC Build'!$C$25)))^4.5) + $B$84)/$B$86) | D116: =((($B$71/(1+((D$115+$A116*$B$17)*('WACC Build'!$C$24) + ('WACC Build'!$B$13)*('WACC Build'!$C$25)))^0.5 + $C$71/(1+((D$115+$A116*$B$17)*('WACC Build'!$C$24) + ('WACC Build'!$B$13)*('WACC Build'!$C$25)))^1.5 + $D$71/(1+((D$115+$A116*$B$17)*('WACC Build'!$C$24) + ('WACC Build'!$B$13)*('WACC Build'!$C$25)))^2.5 + $E$71/(1+((D$115+$A116*$B$17)*('WACC Build'!$C$24) + ('WACC Build'!$B$13)*('WACC Build'!$C$25)))^3.5 + $F$71/(1+((D$115+$A116*$B$17)*('WACC Build'!$C$24) + ('WACC Build'!$B$13)*('WACC Build'!$C$25)))^4.5) + (($F$71*(1+$H$44)/(((D$115+$A116*$B$17)*('WACC Build'!$C$24) + ('WACC Build'!$B$13)*('WACC Build'!$C$25))-$H$44))/(1+((D$115+$A116*$B$17)*('WACC Build'!$C$24) + ('WACC Build'!$B$13)*('WACC Build'!$C$25)))^4.5) + $B$84)/$B$86) | E116: =((($B$71/(1+((E$115+$A116*$B$17)*('WACC Build'!$C$24) + ('WACC Build'!$B$13)*('WACC Build'!$C$25)))^0.5 + $C$71/(1+((E$115+$A116*$B$17)*('WACC Build'!$C$24) + ('WACC Build'!$B$13)*('WACC Build'!$C$25)))^1.5 + $D$71/(1+((E$115+$A116*$B$17)*('WACC Build'!$C$24) + ('WACC Build'!$B$13)*('WACC Build'!$C$25)))^2.5 + $E$71/(1+((E$115+$A116*$B$17)*('WACC Build'!$C$24) + ('WACC Build'!$B$13)*('WACC Build'!$C$25)))^3.5 + $F$71/(1+((E$115+$A116*$B$17)*('WACC Build'!$C$24) + ('WACC Build'!$B$13)*('WACC Build'!$C$25)))^4.5) + (($F$71*(1+$H$44)/(((E$115+$A116*$B$17)*('WACC Build'!$C$24) + ('WACC Build'!$B$13)*('WACC Build'!$C$25))-$H$44))/(1+((E$115+$A116*$B$17)*('WACC Build'!$C$24) + ('WACC Build'!$B$13)*('WACC Build'!$C$25)))^4.5) + $B$84)/$B$86) | F116: =((($B$71/(1+((F$115+$A116*$B$17)*('WACC Build'!$C$24) + ('WACC Build'!$B$13)*('WACC Build'!$C$25)))^0.5 + $C$71/(1+((F$115+$A116*$B$17)*('WACC Build'!$C$24) + ('WACC Build'!$B$13)*('WACC Build'!$C$25)))^1.5 + $D$71/(1+((F$115+$A116*$B$17)*('WACC Build'!$C$24) + ('WACC Build'!$B$13)*('WACC Build'!$C$25)))^2.5 + $E$71/(1+((F$115+$A116*$B$17)*('WACC Build'!$C$24) + ('WACC Build'!$B$13)*('WACC Build'!$C$25)))^3.5 + $F$71/(1+((F$115+$A116*$B$17)*('WACC Build'!$C$24) + ('WACC Build'!$B$13)*('WACC Build'!$C$25)))^4.5) + (($F$71*(1+$H$44)/(((F$115+$A116*$B$17)*('WACC Build'!$C$24) + ('WACC Build'!$B$13)*('WACC Build'!$C$25))-$H$44))/(1+((F$115+$A116*$B$17)*('WACC Build'!$C$24) + ('WACC Build'!$B$13)*('WACC Build'!$C$25)))^4.5) + $B$84)/$B$86)
A117: 1.62 | B117: =((($B$71/(1+((B$115+$A117*$B$17)*('WACC Build'!$C$24) + ('WACC Build'!$B$13)*('WACC Build'!$C$25)))^0.5 + $C$71/(1+((B$115+$A117*$B$17)*('WACC Build'!$C$24) + ('WACC Build'!$B$13)*('WACC Build'!$C$25)))^1.5 + $D$71/(1+((B$115+$A117*$B$17)*('WACC Build'!$C$24) + ('WACC Build'!$B$13)*('WACC Build'!$C$25)))^2.5 + $E$71/(1+((B$115+$A117*$B$17)*('WACC Build'!$C$24) + ('WACC Build'!$B$13)*('WACC Build'!$C$25)))^3.5 + $F$71/(1+((B$115+$A117*$B$17)*('WACC Build'!$C$24) + ('WACC Build'!$B$13)*('WACC Build'!$C$25)))^4.5) + (($F$71*(1+$H$44)/(((B$115+$A117*$B$17)*('WACC Build'!$C$24) + ('WACC Build'!$B$13)*('WACC Build'!$C$25))-$H$44))/(1+((B$115+$A117*$B$17)*('WACC Build'!$C$24) + ('WACC Build'!$B$13)*('WACC Build'!$C$25)))^4.5) + $B$84)/$B$86) | C117: =((($B$71/(1+((C$115+$A117*$B$17)*('WACC Build'!$C$24) + ('WACC Build'!$B$13)*('WACC Build'!$C$25)))^0.5 + $C$71/(1+((C$115+$A117*$B$17)*('WACC Build'!$C$24) + ('WACC Build'!$B$13)*('WACC Build'!$C$25)))^1.5 + $D$71/(1+((C$115+$A117*$B$17)*('WACC Build'!$C$24) + ('WACC Build'!$B$13)*('WACC Build'!$C$25)))^2.5 + $E$71/(1+((C$115+$A117*$B$17)*('WACC Build'!$C$24) + ('WACC Build'!$B$13)*('WACC Build'!$C$25)))^3.5 + $F$71/(1+((C$115+$A117*$B$17)*('WACC Build'!$C$24) + ('WACC Build'!$B$13)*('WACC Build'!$C$25)))^4.5) + (($F$71*(1+$H$44)/(((C$115+$A117*$B$17)*('WACC Build'!$C$24) + ('WACC Build'!$B$13)*('WACC Build'!$C$25))-$H$44))/(1+((C$115+$A117*$B$17)*('WACC Build'!$C$24) + ('WACC Build'!$B$13)*('WACC Build'!$C$25)))^4.5) + $B$84)/$B$86) | D117: =((($B$71/(1+((D$115+$A117*$B$17)*('WACC Build'!$C$24) + ('WACC Build'!$B$13)*('WACC Build'!$C$25)))^0.5 + $C$71/(1+((D$115+$A117*$B$17)*('WACC Build'!$C$24) + ('WACC Build'!$B$13)*('WACC Build'!$C$25)))^1.5 + $D$71/(1+((D$115+$A117*$B$17)*('WACC Build'!$C$24) + ('WACC Build'!$B$13)*('WACC Build'!$C$25)))^2.5 + $E$71/(1+((D$115+$A117*$B$17)*('WACC Build'!$C$24) + ('WACC Build'!$B$13)*('WACC Build'!$C$25)))^3.5 + $F$71/(1+((D$115+$A117*$B$17)*('WACC Build'!$C$24) + ('WACC Build'!$B$13)*('WACC Build'!$C$25)))^4.5) + (($F$71*(1+$H$44)/(((D$115+$A117*$B$17)*('WACC Build'!$C$24) + ('WACC Build'!$B$13)*('WACC Build'!$C$25))-$H$44))/(1+((D$115+$A117*$B$17)*('WACC Build'!$C$24) + ('WACC Build'!$B$13)*('WACC Build'!$C$25)))^4.5) + $B$84)/$B$86) | E117: =((($B$71/(1+((E$115+$A117*$B$17)*('WACC Build'!$C$24) + ('WACC Build'!$B$13)*('WACC Build'!$C$25)))^0.5 + $C$71/(1+((E$115+$A117*$B$17)*('WACC Build'!$C$24) + ('WACC Build'!$B$13)*('WACC Build'!$C$25)))^1.5 + $D$71/(1+((E$115+$A117*$B$17)*('WACC Build'!$C$24) + ('WACC Build'!$B$13)*('WACC Build'!$C$25)))^2.5 + $E$71/(1+((E$115+$A117*$B$17)*('WACC Build'!$C$24) + ('WACC Build'!$B$13)*('WACC Build'!$C$25)))^3.5 + $F$71/(1+((E$115+$A117*$B$17)*('WACC Build'!$C$24) + ('WACC Build'!$B$13)*('WACC Build'!$C$25)))^4.5) + (($F$71*(1+$H$44)/(((E$115+$A117*$B$17)*('WACC Build'!$C$24) + ('WACC Build'!$B$13)*('WACC Build'!$C$25))-$H$44))/(1+((E$115+$A117*$B$17)*('WACC Build'!$C$24) + ('WACC Build'!$B$13)*('WACC Build'!$C$25)))^4.5) + $B$84)/$B$86) | F117: =((($B$71/(1+((F$115+$A117*$B$17)*('WACC Build'!$C$24) + ('WACC Build'!$B$13)*('WACC Build'!$C$25)))^0.5 + $C$71/(1+((F$115+$A117*$B$17)*('WACC Build'!$C$24) + ('WACC Build'!$B$13)*('WACC Build'!$C$25)))^1.5 + $D$71/(1+((F$115+$A117*$B$17)*('WACC Build'!$C$24) + ('WACC Build'!$B$13)*('WACC Build'!$C$25)))^2.5 + $E$71/(1+((F$115+$A117*$B$17)*('WACC Build'!$C$24) + ('WACC Build'!$B$13)*('WACC Build'!$C$25)))^3.5 + $F$71/(1+((F$115+$A117*$B$17)*('WACC Build'!$C$24) + ('WACC Build'!$B$13)*('WACC Build'!$C$25)))^4.5) + (($F$71*(1+$H$44)/(((F$115+$A117*$B$17)*('WACC Build'!$C$24) + ('WACC Build'!$B$13)*('WACC Build'!$C$25))-$H$44))/(1+((F$115+$A117*$B$17)*('WACC Build'!$C$24) + ('WACC Build'!$B$13)*('WACC Build'!$C$25)))^4.5) + $B$84)/$B$86)
A118: 1.82 | B118: =((($B$71/(1+((B$115+$A118*$B$17)*('WACC Build'!$C$24) + ('WACC Build'!$B$13)*('WACC Build'!$C$25)))^0.5 + $C$71/(1+((B$115+$A118*$B$17)*('WACC Build'!$C$24) + ('WACC Build'!$B$13)*('WACC Build'!$C$25)))^1.5 + $D$71/(1+((B$115+$A118*$B$17)*('WACC Build'!$C$24) + ('WACC Build'!$B$13)*('WACC Build'!$C$25)))^2.5 + $E$71/(1+((B$115+$A118*$B$17)*('WACC Build'!$C$24) + ('WACC Build'!$B$13)*('WACC Build'!$C$25)))^3.5 + $F$71/(1+((B$115+$A118*$B$17)*('WACC Build'!$C$24) + ('WACC Build'!$B$13)*('WACC Build'!$C$25)))^4.5) + (($F$71*(1+$H$44)/(((B$115+$A118*$B$17)*('WACC Build'!$C$24) + ('WACC Build'!$B$13)*('WACC Build'!$C$25))-$H$44))/(1+((B$115+$A118*$B$17)*('WACC Build'!$C$24) + ('WACC Build'!$B$13)*('WACC Build'!$C$25)))^4.5) + $B$84)/$B$86) | C118: =((($B$71/(1+((C$115+$A118*$B$17)*('WACC Build'!$C$24) + ('WACC Build'!$B$13)*('WACC Build'!$C$25)))^0.5 + $C$71/(1+((C$115+$A118*$B$17)*('WACC Build'!$C$24) + ('WACC Build'!$B$13)*('WACC Build'!$C$25)))^1.5 + $D$71/(1+((C$115+$A118*$B$17)*('WACC Build'!$C$24) + ('WACC Build'!$B$13)*('WACC Build'!$C$25)))^2.5 + $E$71/(1+((C$115+$A118*$B$17)*('WACC Build'!$C$24) + ('WACC Build'!$B$13)*('WACC Build'!$C$25)))^3.5 + $F$71/(1+((C$115+$A118*$B$17)*('WACC Build'!$C$24) + ('WACC Build'!$B$13)*('WACC Build'!$C$25)))^4.5) + (($F$71*(1+$H$44)/(((C$115+$A118*$B$17)*('WACC Build'!$C$24) + ('WACC Build'!$B$13)*('WACC Build'!$C$25))-$H$44))/(1+((C$115+$A118*$B$17)*('WACC Build'!$C$24) + ('WACC Build'!$B$13)*('WACC Build'!$C$25)))^4.5) + $B$84)/$B$86) | D118: =((($B$71/(1+((D$115+$A118*$B$17)*('WACC Build'!$C$24) + ('WACC Build'!$B$13)*('WACC Build'!$C$25)))^0.5 + $C$71/(1+((D$115+$A118*$B$17)*('WACC Build'!$C$24) + ('WACC Build'!$B$13)*('WACC Build'!$C$25)))^1.5 + $D$71/(1+((D$115+$A118*$B$17)*('WACC Build'!$C$24) + ('WACC Build'!$B$13)*('WACC Build'!$C$25)))^2.5 + $E$71/(1+((D$115+$A118*$B$17)*('WACC Build'!$C$24) + ('WACC Build'!$B$13)*('WACC Build'!$C$25)))^3.5 + $F$71/(1+((D$115+$A118*$B$17)*('WACC Build'!$C$24) + ('WACC Build'!$B$13)*('WACC Build'!$C$25)))^4.5) + (($F$71*(1+$H$44)/(((D$115+$A118*$B$17)*('WACC Build'!$C$24) + ('WACC Build'!$B$13)*('WACC Build'!$C$25))-$H$44))/(1+((D$115+$A118*$B$17)*('WACC Build'!$C$24) + ('WACC Build'!$B$13)*('WACC Build'!$C$25)))^4.5) + $B$84)/$B$86) | E118: =((($B$71/(1+((E$115+$A118*$B$17)*('WACC Build'!$C$24) + ('WACC Build'!$B$13)*('WACC Build'!$C$25)))^0.5 + $C$71/(1+((E$115+$A118*$B$17)*('WACC Build'!$C$24) + ('WACC Build'!$B$13)*('WACC Build'!$C$25)))^1.5 + $D$71/(1+((E$115+$A118*$B$17)*('WACC Build'!$C$24) + ('WACC Build'!$B$13)*('WACC Build'!$C$25)))^2.5 + $E$71/(1+((E$115+$A118*$B$17)*('WACC Build'!$C$24) + ('WACC Build'!$B$13)*('WACC Build'!$C$25)))^3.5 + $F$71/(1+((E$115+$A118*$B$17)*('WACC Build'!$C$24) + ('WACC Build'!$B$13)*('WACC Build'!$C$25)))^4.5) + (($F$71*(1+$H$44)/(((E$115+$A118*$B$17)*('WACC Build'!$C$24) + ('WACC Build'!$B$13)*('WACC Build'!$C$25))-$H$44))/(1+((E$115+$A118*$B$17)*('WACC Build'!$C$24) + ('WACC Build'!$B$13)*('WACC Build'!$C$25)))^4.5) + $B$84)/$B$86) | F118: =((($B$71/(1+((F$115+$A118*$B$17)*('WACC Build'!$C$24) + ('WACC Build'!$B$13)*('WACC Build'!$C$25)))^0.5 + $C$71/(1+((F$115+$A118*$B$17)*('WACC Build'!$C$24) + ('WACC Build'!$B$13)*('WACC Build'!$C$25)))^1.5 + $D$71/(1+((F$115+$A118*$B$17)*('WACC Build'!$C$24) + ('WACC Build'!$B$13)*('WACC Build'!$C$25)))^2.5 + $E$71/(1+((F$115+$A118*$B$17)*('WACC Build'!$C$24) + ('WACC Build'!$B$13)*('WACC Build'!$C$25)))^3.5 + $F$71/(1+((F$115+$A118*$B$17)*('WACC Build'!$C$24) + ('WACC Build'!$B$13)*('WACC Build'!$C$25)))^4.5) + (($F$71*(1+$H$44)/(((F$115+$A118*$B$17)*('WACC Build'!$C$24) + ('WACC Build'!$B$13)*('WACC Build'!$C$25))-$H$44))/(1+((F$115+$A118*$B$17)*('WACC Build'!$C$24) + ('WACC Build'!$B$13)*('WACC Build'!$C$25)))^4.5) + $B$84)/$B$86)
A119: 2.02 | B119: =((($B$71/(1+((B$115+$A119*$B$17)*('WACC Build'!$C$24) + ('WACC Build'!$B$13)*('WACC Build'!$C$25)))^0.5 + $C$71/(1+((B$115+$A119*$B$17)*('WACC Build'!$C$24) + ('WACC Build'!$B$13)*('WACC Build'!$C$25)))^1.5 + $D$71/(1+((B$115+$A119*$B$17)*('WACC Build'!$C$24) + ('WACC Build'!$B$13)*('WACC Build'!$C$25)))^2.5 + $E$71/(1+((B$115+$A119*$B$17)*('WACC Build'!$C$24) + ('WACC Build'!$B$13)*('WACC Build'!$C$25)))^3.5 + $F$71/(1+((B$115+$A119*$B$17)*('WACC Build'!$C$24) + ('WACC Build'!$B$13)*('WACC Build'!$C$25)))^4.5) + (($F$71*(1+$H$44)/(((B$115+$A119*$B$17)*('WACC Build'!$C$24) + ('WACC Build'!$B$13)*('WACC Build'!$C$25))-$H$44))/(1+((B$115+$A119*$B$17)*('WACC Build'!$C$24) + ('WACC Build'!$B$13)*('WACC Build'!$C$25)))^4.5) + $B$84)/$B$86) | C119: =((($B$71/(1+((C$115+$A119*$B$17)*('WACC Build'!$C$24) + ('WACC Build'!$B$13)*('WACC Build'!$C$25)))^0.5 + $C$71/(1+((C$115+$A119*$B$17)*('WACC Build'!$C$24) + ('WACC Build'!$B$13)*('WACC Build'!$C$25)))^1.5 + $D$71/(1+((C$115+$A119*$B$17)*('WACC Build'!$C$24) + ('WACC Build'!$B$13)*('WACC Build'!$C$25)))^2.5 + $E$71/(1+((C$115+$A119*$B$17)*('WACC Build'!$C$24) + ('WACC Build'!$B$13)*('WACC Build'!$C$25)))^3.5 + $F$71/(1+((C$115+$A119*$B$17)*('WACC Build'!$C$24) + ('WACC Build'!$B$13)*('WACC Build'!$C$25)))^4.5) + (($F$71*(1+$H$44)/(((C$115+$A119*$B$17)*('WACC Build'!$C$24) + ('WACC Build'!$B$13)*('WACC Build'!$C$25))-$H$44))/(1+((C$115+$A119*$B$17)*('WACC Build'!$C$24) + ('WACC Build'!$B$13)*('WACC Build'!$C$25)))^4.5) + $B$84)/$B$86) | D119: =((($B$71/(1+((D$115+$A119*$B$17)*('WACC Build'!$C$24) + ('WACC Build'!$B$13)*('WACC Build'!$C$25)))^0.5 + $C$71/(1+((D$115+$A119*$B$17)*('WACC Build'!$C$24) + ('WACC Build'!$B$13)*('WACC Build'!$C$25)))^1.5 + $D$71/(1+((D$115+$A119*$B$17)*('WACC Build'!$C$24) + ('WACC Build'!$B$13)*('WACC Build'!$C$25)))^2.5 + $E$71/(1+((D$115+$A119*$B$17)*('WACC Build'!$C$24) + ('WACC Build'!$B$13)*('WACC Build'!$C$25)))^3.5 + $F$71/(1+((D$115+$A119*$B$17)*('WACC Build'!$C$24) + ('WACC Build'!$B$13)*('WACC Build'!$C$25)))^4.5) + (($F$71*(1+$H$44)/(((D$115+$A119*$B$17)*('WACC Build'!$C$24) + ('WACC Build'!$B$13)*('WACC Build'!$C$25))-$H$44))/(1+((D$115+$A119*$B$17)*('WACC Build'!$C$24) + ('WACC Build'!$B$13)*('WACC Build'!$C$25)))^4.5) + $B$84)/$B$86) | E119: =((($B$71/(1+((E$115+$A119*$B$17)*('WACC Build'!$C$24) + ('WACC Build'!$B$13)*('WACC Build'!$C$25)))^0.5 + $C$71/(1+((E$115+$A119*$B$17)*('WACC Build'!$C$24) + ('WACC Build'!$B$13)*('WACC Build'!$C$25)))^1.5 + $D$71/(1+((E$115+$A119*$B$17)*('WACC Build'!$C$24) + ('WACC Build'!$B$13)*('WACC Build'!$C$25)))^2.5 + $E$71/(1+((E$115+$A119*$B$17)*('WACC Build'!$C$24) + ('WACC Build'!$B$13)*('WACC Build'!$C$25)))^3.5 + $F$71/(1+((E$115+$A119*$B$17)*('WACC Build'!$C$24) + ('WACC Build'!$B$13)*('WACC Build'!$C$25)))^4.5) + (($F$71*(1+$H$44)/(((E$115+$A119*$B$17)*('WACC Build'!$C$24) + ('WACC Build'!$B$13)*('WACC Build'!$C$25))-$H$44))/(1+((E$115+$A119*$B$17)*('WACC Build'!$C$24) + ('WACC Build'!$B$13)*('WACC Build'!$C$25)))^4.5) + $B$84)/$B$86) | F119: =((($B$71/(1+((F$115+$A119*$B$17)*('WACC Build'!$C$24) + ('WACC Build'!$B$13)*('WACC Build'!$C$25)))^0.5 + $C$71/(1+((F$115+$A119*$B$17)*('WACC Build'!$C$24) + ('WACC Build'!$B$13)*('WACC Build'!$C$25)))^1.5 + $D$71/(1+((F$115+$A119*$B$17)*('WACC Build'!$C$24) + ('WACC Build'!$B$13)*('WACC Build'!$C$25)))^2.5 + $E$71/(1+((F$115+$A119*$B$17)*('WACC Build'!$C$24) + ('WACC Build'!$B$13)*('WACC Build'!$C$25)))^3.5 + $F$71/(1+((F$115+$A119*$B$17)*('WACC Build'!$C$24) + ('WACC Build'!$B$13)*('WACC Build'!$C$25)))^4.5) + (($F$71*(1+$H$44)/(((F$115+$A119*$B$17)*('WACC Build'!$C$24) + ('WACC Build'!$B$13)*('WACC Build'!$C$25))-$H$44))/(1+((F$115+$A119*$B$17)*('WACC Build'!$C$24) + ('WACC Build'!$B$13)*('WACC Build'!$C$25)))^4.5) + $B$84)/$B$86)
A120: 2.22 | B120: =((($B$71/(1+((B$115+$A120*$B$17)*('WACC Build'!$C$24) + ('WACC Build'!$B$13)*('WACC Build'!$C$25)))^0.5 + $C$71/(1+((B$115+$A120*$B$17)*('WACC Build'!$C$24) + ('WACC Build'!$B$13)*('WACC Build'!$C$25)))^1.5 + $D$71/(1+((B$115+$A120*$B$17)*('WACC Build'!$C$24) + ('WACC Build'!$B$13)*('WACC Build'!$C$25)))^2.5 + $E$71/(1+((B$115+$A120*$B$17)*('WACC Build'!$C$24) + ('WACC Build'!$B$13)*('WACC Build'!$C$25)))^3.5 + $F$71/(1+((B$115+$A120*$B$17)*('WACC Build'!$C$24) + ('WACC Build'!$B$13)*('WACC Build'!$C$25)))^4.5) + (($F$71*(1+$H$44)/(((B$115+$A120*$B$17)*('WACC Build'!$C$24) + ('WACC Build'!$B$13)*('WACC Build'!$C$25))-$H$44))/(1+((B$115+$A120*$B$17)*('WACC Build'!$C$24) + ('WACC Build'!$B$13)*('WACC Build'!$C$25)))^4.5) + $B$84)/$B$86) | C120: =((($B$71/(1+((C$115+$A120*$B$17)*('WACC Build'!$C$24) + ('WACC Build'!$B$13)*('WACC Build'!$C$25)))^0.5 + $C$71/(1+((C$115+$A120*$B$17)*('WACC Build'!$C$24) + ('WACC Build'!$B$13)*('WACC Build'!$C$25)))^1.5 + $D$71/(1+((C$115+$A120*$B$17)*('WACC Build'!$C$24) + ('WACC Build'!$B$13)*('WACC Build'!$C$25)))^2.5 + $E$71/(1+((C$115+$A120*$B$17)*('WACC Build'!$C$24) + ('WACC Build'!$B$13)*('WACC Build'!$C$25)))^3.5 + $F$71/(1+((C$115+$A120*$B$17)*('WACC Build'!$C$24) + ('WACC Build'!$B$13)*('WACC Build'!$C$25)))^4.5) + (($F$71*(1+$H$44)/(((C$115+$A120*$B$17)*('WACC Build'!$C$24) + ('WACC Build'!$B$13)*('WACC Build'!$C$25))-$H$44))/(1+((C$115+$A120*$B$17)*('WACC Build'!$C$24) + ('WACC Build'!$B$13)*('WACC Build'!$C$25)))^4.5) + $B$84)/$B$86) | D120: =((($B$71/(1+((D$115+$A120*$B$17)*('WACC Build'!$C$24) + ('WACC Build'!$B$13)*('WACC Build'!$C$25)))^0.5 + $C$71/(1+((D$115+$A120*$B$17)*('WACC Build'!$C$24) + ('WACC Build'!$B$13)*('WACC Build'!$C$25)))^1.5 + $D$71/(1+((D$115+$A120*$B$17)*('WACC Build'!$C$24) + ('WACC Build'!$B$13)*('WACC Build'!$C$25)))^2.5 + $E$71/(1+((D$115+$A120*$B$17)*('WACC Build'!$C$24) + ('WACC Build'!$B$13)*('WACC Build'!$C$25)))^3.5 + $F$71/(1+((D$115+$A120*$B$17)*('WACC Build'!$C$24) + ('WACC Build'!$B$13)*('WACC Build'!$C$25)))^4.5) + (($F$71*(1+$H$44)/(((D$115+$A120*$B$17)*('WACC Build'!$C$24) + ('WACC Build'!$B$13)*('WACC Build'!$C$25))-$H$44))/(1+((D$115+$A120*$B$17)*('WACC Build'!$C$24) + ('WACC Build'!$B$13)*('WACC Build'!$C$25)))^4.5) + $B$84)/$B$86) | E120: =((($B$71/(1+((E$115+$A120*$B$17)*('WACC Build'!$C$24) + ('WACC Build'!$B$13)*('WACC Build'!$C$25)))^0.5 + $C$71/(1+((E$115+$A120*$B$17)*('WACC Build'!$C$24) + ('WACC Build'!$B$13)*('WACC Build'!$C$25)))^1.5 + $D$71/(1+((E$115+$A120*$B$17)*('WACC Build'!$C$24) + ('WACC Build'!$B$13)*('WACC Build'!$C$25)))^2.5 + $E$71/(1+((E$115+$A120*$B$17)*('WACC Build'!$C$24) + ('WACC Build'!$B$13)*('WACC Build'!$C$25)))^3.5 + $F$71/(1+((E$115+$A120*$B$17)*('WACC Build'!$C$24) + ('WACC Build'!$B$13)*('WACC Build'!$C$25)))^4.5) + (($F$71*(1+$H$44)/(((E$115+$A120*$B$17)*('WACC Build'!$C$24) + ('WACC Build'!$B$13)*('WACC Build'!$C$25))-$H$44))/(1+((E$115+$A120*$B$17)*('WACC Build'!$C$24) + ('WACC Build'!$B$13)*('WACC Build'!$C$25)))^4.5) + $B$84)/$B$86) | F120: =((($B$71/(1+((F$115+$A120*$B$17)*('WACC Build'!$C$24) + ('WACC Build'!$B$13)*('WACC Build'!$C$25)))^0.5 + $C$71/(1+((F$115+$A120*$B$17)*('WACC Build'!$C$24) + ('WACC Build'!$B$13)*('WACC Build'!$C$25)))^1.5 + $D$71/(1+((F$115+$A120*$B$17)*('WACC Build'!$C$24) + ('WACC Build'!$B$13)*('WACC Build'!$C$25)))^2.5 + $E$71/(1+((F$115+$A120*$B$17)*('WACC Build'!$C$24) + ('WACC Build'!$B$13)*('WACC Build'!$C$25)))^3.5 + $F$71/(1+((F$115+$A120*$B$17)*('WACC Build'!$C$24) + ('WACC Build'!$B$13)*('WACC Build'!$C$25)))^4.5) + (($F$71*(1+$H$44)/(((F$115+$A120*$B$17)*('WACC Build'!$C$24) + ('WACC Build'!$B$13)*('WACC Build'!$C$25))-$H$44))/(1+((F$115+$A120*$B$17)*('WACC Build'!$C$24) + ('WACC Build'!$B$13)*('WACC Build'!$C$25)))^4.5) + $B$84)/$B$86)

Sheet WACC Build
A1: Tesla, Inc. (NASDAQ: TSLA)
A2: Weighted Average Cost of Capital (WACC) Schedule | CAPM Methodology & Capital Structure
A4: I. COST OF EQUITY (CAPM METHODOLOGY)
A5: Risk-Free Rate (10-Yr US Treasury Yield) | B5: 0.0465
A6: Equity Beta (5-Year Monthly vs S&P 500) | B6: 1.82
A7: Market Equity Risk Premium (ERP) | B7: 0.055
A8: Cost of Equity (Ke = Rf + Beta * ERP) | B8: =B5+B6*B7
A10: II. COST OF DEBT & CAPITAL STRUCTURE WEIGHTS
A11: Pre-Tax Cost of Debt (Kd) | B11: 0.055
A12: Effective Corporate Tax Rate (t) | B12: 0.21
A13: After-Tax Cost of Debt (Kd * (1 - t)) | B13: =B11*(1-B12)
A14: Current Share Price ($) | B14: ='DCF Valuation'!B7
A15: Diluted Shares Outstanding (M) | B15: ='DCF Valuation'!B8
A16: Market Capitalization ($M) | B16: =B14*B15
A17: Total Debt (Current + Noncurrent + Leases) ($M) | B17: 8376
A18: Cash, Cash Equivalents & ST Investments ($M) | B18: 44059
A19: Net Debt ($M) | B19: =B17-B18
A20: Enterprise Value ($M) | B20: =B16+B19
A22: III. WACC CALCULATION SUMMARY
A23: Component | B23: Market Value ($M) | C23: Capital Weight (%) | D23: Cost of Capital (%) | E23: Weighted Contribution (%)
A24: Common Equity (Market Cap) | B24: =B16 | C24: =B24/$B$20 | D24: =B8 | E24: =C24*D24
A25: Net Debt (Debt Weight Adjustment) | B25: =B19 | C25: =B25/$B$20 | D25: =B13 | E25: =C25*D25
A26: Total Capitalization / Base WACC | B26: =B20 | C26: =SUM(C24:C25) | D26: - | E26: =SUM(E24:E25)
