Workbook

Sheet DCF
A1: THE REALREAL, INC. (NASDAQ: REAL) - DISCOUNTED CASH FLOW VALUATION MODEL
A2: Ticker: REAL | Valuation Date: August 19, 2026 | FYE: Dec 31 | Units: USD Millions ($M) except per share
A4: SCENARIO SELECTOR
A5: Case Selector [1 = Bear, 2 = Base, 3 = Bull]: | B5: 2
A6: Active Selected Scenario: | B6: =IF(B5=1,"Bear Case",IF(B5=2,"Base Case","Bull Case"))
A8: MARKET DATA & VALUATION PARAMETERS
A9: Current Stock Price ($) | B9: 11.2
A10: Diluted Shares Outstanding (M) | B10: 121.67
A11: Market Capitalization ($M) | B11: =B9*B10
A12: Total Debt ($M) | B12: =WACC!$B$19
A13: Cash & Cash Equivalents ($M) | B13: =WACC!$B$20
A14: Net Debt ($M) [Total Debt - Cash] | B14: =B12-B13
A15: Baseline WACC (Discount Rate) | B15: =WACC!$B$30
A16: Terminal Growth Rate (g) | B16: 0.025
A18: BEAR CASE ASSUMPTIONS (Scenario 1 - Macro Slowdown & High Friction)
A19: Assumption | B19: FY2026E | C19: FY2027E | D19: FY2028E | E19: FY2029E | F19: FY2030E
A20: Revenue Growth Rate (%) | B20: 0.1 | C20: 0.07 | D20: 0.05 | E20: 0.04 | F20: 0.03
A21: Gross Margin (%) | B21: 0.745 | C21: 0.745 | D21: 0.742 | E21: 0.74 | F21: 0.74
A22: EBIT Margin (%) | B22: 0.025 | C22: 0.03 | D22: 0.038 | E22: 0.045 | F22: 0.05
A23: D&A (% of Revenue) | B23: 0.045 | C23: 0.042 | D23: 0.04 | E23: 0.038 | F23: 0.038
A24: CapEx (% of Revenue) | B24: 0.046 | C24: 0.044 | D24: 0.042 | E24: 0.04 | F24: 0.038
A25: NWC Change (% of Δ Revenue) | B25: 0.025 | C25: 0.025 | D25: 0.025 | E25: 0.025 | F25: 0.025
A27: BASE CASE ASSUMPTIONS (Scenario 2 - Consensus & Management Guidance)
A28: Assumption | B28: FY2026E | C28: FY2027E | D28: FY2028E | E28: FY2029E | F28: FY2030E
A29: Revenue Growth Rate (%) | B29: 0.14374 | C29: 0.12 | D29: 0.1 | E29: 0.08 | F29: 0.06
A30: Gross Margin (%) | B30: 0.755 | C30: 0.76 | D30: 0.765 | E30: 0.77 | F30: 0.775
A31: EBIT Margin (%) | B31: 0.04227 | C31: 0.065 | D31: 0.085 | E31: 0.1 | F31: 0.11
A32: D&A (% of Revenue) | B32: 0.0429 | C32: 0.04 | D32: 0.038 | E32: 0.036 | F32: 0.035
A33: CapEx (% of Revenue) | B33: 0.04416 | C33: 0.042 | D33: 0.04 | E33: 0.038 | F33: 0.035
A34: NWC Change (% of Δ Revenue) | B34: 0.02 | C34: 0.02 | D34: 0.02 | E34: 0.02 | F34: 0.02
A36: BULL CASE ASSUMPTIONS (Scenario 3 - AI Automation & Luxury Penetration Acceleration)
A37: Assumption | B37: FY2026E | C37: FY2027E | D37: FY2028E | E37: FY2029E | F37: FY2030E
A38: Revenue Growth Rate (%) | B38: 0.17 | C38: 0.15 | D38: 0.13 | E38: 0.11 | F38: 0.09
A39: Gross Margin (%) | B39: 0.76 | C39: 0.765 | D39: 0.77 | E39: 0.775 | F39: 0.785
A40: EBIT Margin (%) | B40: 0.05 | C40: 0.08 | D40: 0.105 | E40: 0.12 | F40: 0.135
A41: D&A (% of Revenue) | B41: 0.042 | C41: 0.038 | D41: 0.035 | E41: 0.033 | F41: 0.032
A42: CapEx (% of Revenue) | B42: 0.042 | C42: 0.038 | D42: 0.035 | E42: 0.033 | F42: 0.032
A43: NWC Change (% of Δ Revenue) | B43: 0.015 | C43: 0.015 | D43: 0.015 | E43: 0.015 | F43: 0.015
A45: ACTIVE CONSOLIDATED ASSUMPTIONS (DYNAMICALLY PULLED VIA CHOOSE)
A46: Assumption | B46: FY2026E | C46: FY2027E | D46: FY2028E | E46: FY2029E | F46: FY2030E
A47: Active Revenue Growth Rate (%) | B47: =CHOOSE($B$5, B20, B29, B38) | C47: =CHOOSE($B$5, C20, C29, C38) | D47: =CHOOSE($B$5, D20, D29, D38) | E47: =CHOOSE($B$5, E20, E29, E38) | F47: =CHOOSE($B$5, F20, F29, F38)
A48: Active Gross Margin (%) | B48: =CHOOSE($B$5, B21, B30, B39) | C48: =CHOOSE($B$5, C21, C30, C39) | D48: =CHOOSE($B$5, D21, D30, D39) | E48: =CHOOSE($B$5, E21, E30, E39) | F48: =CHOOSE($B$5, F21, F30, F39)
A49: Active EBIT Margin (%) | B49: =CHOOSE($B$5, B22, B31, B40) | C49: =CHOOSE($B$5, C22, C31, C40) | D49: =CHOOSE($B$5, D22, D31, D40) | E49: =CHOOSE($B$5, E22, E31, E40) | F49: =CHOOSE($B$5, F22, F31, F40)
A50: Active D&A (% of Revenue) | B50: =CHOOSE($B$5, B23, B32, B41) | C50: =CHOOSE($B$5, C23, C32, C41) | D50: =CHOOSE($B$5, D23, D32, D41) | E50: =CHOOSE($B$5, E23, E32, E41) | F50: =CHOOSE($B$5, F23, F32, F41)
A51: Active CapEx (% of Revenue) | B51: =CHOOSE($B$5, B24, B33, B42) | C51: =CHOOSE($B$5, C24, C33, C42) | D51: =CHOOSE($B$5, D24, D33, D42) | E51: =CHOOSE($B$5, E24, E33, E42) | F51: =CHOOSE($B$5, F24, F33, F42)
A52: Active NWC Change (% of Δ Rev) | B52: =CHOOSE($B$5, B25, B34, B43) | C52: =CHOOSE($B$5, C25, C34, C43) | D52: =CHOOSE($B$5, D25, D34, D43) | E52: =CHOOSE($B$5, E25, E34, E43) | F52: =CHOOSE($B$5, F25, F34, F43)
A53: Effective Marginal Tax Rate (%) | B53: 0.25 | C53: =B53 | D53: =B53 | E53: =B53 | F53: =B53
A55: HISTORICAL & PROJECTED INCOME STATEMENT ($M)
A56: Line Item ($M) | B56: FY2023A | C56: FY2024A | D56: FY2025A | E56: FY2026E | F56: FY2027E | G56: FY2028E | H56: FY2029E | I56: FY2030E
A57: Total Revenue ($M) | B57: 549.2 | C57: 600.5 | D57: 692.9 | E57: =D57*(1+$B$47) | F57: =E57*(1+$C$47) | G57: =F57*(1+$D$47) | H57: =G57*(1+$E$47) | I57: =H57*(1+$F$47)
A58: YoY Revenue Growth (%) | B58: - | C58: =C57/B57-1 | D58: =D57/C57-1 | E58: =E57/D57-1 | F58: =F57/E57-1 | G58: =G57/F57-1 | H58: =H57/G57-1 | I58: =I57/H57-1
A59: Gross Profit ($M) | B59: 362.8 | C59: 447.5 | D59: 516.8 | E59: =E57*$B$48 | F59: =F57*$C$48 | G59: =G57*$D$48 | H59: =H57*$E$48 | I59: =I57*$F$48
A60: Gross Margin (%) | B60: =B59/B57 | C60: =C59/C57 | D60: =D59/D57 | E60: =E59/E57 | F60: =F59/F57 | G60: =G59/G57 | H60: =H59/H57 | I60: =I59/I57
A61: Total Operating Expenses ($M) | B61: 529.1 | C61: 504 | D61: 540.7 | E61: =E59-E63 | F61: =F59-F63 | G61: =G59-G63 | H61: =H59-H63 | I61: =I59-I63
A62: OpEx % of Revenue (%) | B62: =B61/B57 | C62: =C61/C57 | D62: =D61/D57 | E62: =E61/E57 | F62: =F61/F57 | G62: =G61/G57 | H62: =H61/H57 | I62: =I61/I57
A63: Operating Income / (Loss) (EBIT) ($M) | B63: -166.3 | C63: -56.5 | D63: -23.9 | E63: =E57*$B$49 | F63: =F57*$C$49 | G63: =G57*$D$49 | H63: =H57*$E$49 | I63: =I57*$F$49
A64: EBIT Margin (%) | B64: =B63/B57 | C64: =C63/C57 | D64: =D63/D57 | E64: =E63/E57 | F64: =F63/F57 | G64: =G63/G57 | H64: =H63/H57 | I64: =I63/I57
A65: (-) Normalized Income Tax Expense ($M) | B65: 0 | C65: 0 | D65: 0 | E65: =MAX(0, E63)*$B$53 | F65: =MAX(0, F63)*$B$53 | G65: =MAX(0, G63)*$B$53 | H65: =MAX(0, H63)*$B$53 | I65: =MAX(0, I63)*$B$53
A66: Net Operating Profit After Tax (NOPAT) ($M) | B66: =B63-B65 | C66: =C63-C65 | D66: =D63-D65 | E66: =E63-E65 | F66: =F63-F65 | G66: =G63-G65 | H66: =H63-H65 | I66: =I63-I65
A68: UNLEVERED FREE CASH FLOW (UFCF) BUILD ($M)
A69: Line Item ($M) | B69: FY2023A | C69: FY2024A | D69: FY2025A | E69: FY2026E | F69: FY2027E | G69: FY2028E | H69: FY2029E | I69: FY2030E
A70: Net Operating Profit After Tax (NOPAT) ($M) | B70: =B66 | C70: =C66 | D70: =D66 | E70: =E66 | F70: =F66 | G70: =G66 | H70: =H66 | I70: =I66
A71: (+) Depreciation & Amortization (D&A) ($M) | B71: 38.2 | C71: 33.1 | D71: 33 | E71: =E57*$B$50 | F71: =F57*$C$50 | G71: =G57*$D$50 | H71: =H57*$E$50 | I71: =I57*$F$50
A72: D&A % of Revenue (%) | B72: =B71/B57 | C72: =C71/C57 | D72: =D71/D57 | E72: =E71/E57 | F72: =F71/F57 | G72: =G71/G57 | H72: =H71/H57 | I72: =I71/I57
A73: (-) Capital Expenditures (CapEx) ($M) | B73: 24.8 | C73: 26 | D73: 31.5 | E73: =E57*$B$51 | F73: =F57*$C$51 | G73: =G57*$D$51 | H73: =H57*$E$51 | I73: =I57*$F$51
A74: CapEx % of Revenue (%) | B74: =B73/B57 | C74: =C73/C57 | D74: =D73/D57 | E74: =E73/E57 | F74: =F73/F57 | G74: =G73/G57 | H74: =H73/H57 | I74: =I73/I57
A75: (-) Change in Net Working Capital (Δ NWC) ($M) | B75: 0 | C75: 0 | D75: 0 | E75: =(E57-D57)*$B$52 | F75: =(F57-E57)*$C$52 | G75: =(G57-F57)*$D$52 | H75: =(H57-G57)*$E$52 | I75: =(I57-H57)*$F$52
A76: Δ NWC % of Δ Revenue (%) | B76: - | C76: - | D76: - | E76: =E75/(E57-D57) | F76: =F75/(F57-E57) | G76: =G75/(G57-F57) | H76: =H75/(H57-G57) | I76: =I75/(I57-H57)
A77: UNLEVERED FREE CASH FLOW (UFCF) ($M) | B77: -72.5 | C77: 27 | D77: 37 | E77: =E70+E71-E73-E75 | F77: =F70+F71-F73-F75 | G77: =G70+G71-G73-G75 | H77: =H70+H71-H73-H75 | I77: =I70+I71-I73-I75
A79: VALUATION & DISCOUNTING SCHEDULE (MID-YEAR CONVENTION) ($M)
A80: Line Item ($M) | B80: FY2023A | C80: FY2024A | D80: FY2025A | E80: FY2026E | F80: FY2027E | G80: FY2028E | H80: FY2029E | I80: FY2030E
A81: Unlevered Free Cash Flow ($M) | B81: - | C81: - | D81: - | E81: =E77 | F81: =F77 | G81: =G77 | H81: =H77 | I81: =I77
A82: Discount Period (Mid-Year Convention, t) | B82: - | C82: - | D82: - | E82: 0.5 | F82: 1.5 | G82: 2.5 | H82: 3.5 | I82: 4.5
A83: Discount Factor [1 / (1 + WACC)^t] | B83: - | C83: - | D83: - | E83: =1/(1+$B$15)^E82 | F83: =1/(1+$B$15)^F82 | G83: =1/(1+$B$15)^G82 | H83: =1/(1+$B$15)^H82 | I83: =1/(1+$B$15)^I82
A84: Present Value (PV) of Projected FCF ($M) | B84: - | C84: - | D84: - | E84: =E81*E83 | F84: =F81*F83 | G84: =G81*G83 | H84: =H81*H83 | I84: =I81*I83
A86: TERMINAL VALUE & VALUATION SUMMARY BRIDGE ($M)
A87: Terminal Growth Rate (g) | B87: =B16
A88: Normalized Terminal FCF [FY30 FCF * (1 + g)] ($M) | B88: =I81*(1+B87)
A89: Terminal Value at Year 5 [FCF_n+1 / (WACC - g)] ($M) | B89: =B88/($B$15-B87)
A90: PV of Terminal Value ($M) [TV / (1 + WACC)^4.5] | B90: =B89/(1+$B$15)^4.5
A91: Terminal Value as % of Enterprise Value | B91: =B90/B94
A93: Cumulative PV of Explicit Cash Flows (FY26E-FY30E) ($M) | B93: =SUM(E84:I84)
A94: ENTERPRISE VALUE (EV) ($M) | B94: =B93+B90
A95: (-) Total Debt ($M) | B95: =B12
A96: (+) Cash & Cash Equivalents ($M) | B96: =B13
A97: (-) Net Debt ($M) [Debt - Cash] | B97: =B95-B96
A98: IMPLIED EQUITY VALUE ($M) | B98: =B94-B97
A99: Diluted Shares Outstanding (M) | B99: =B10
A100: IMPLIED SHARE PRICE ($ / Share) | B100: =B98/B99
A101: Current Stock Price ($ / Share) | B101: =B9
A102: Implied Upside / (Downside) (%) | B102: =B100/B101-1
A104: SENSITIVITY ANALYSIS 1: IMPLIED SHARE PRICE ($) - WACC VS. TERMINAL GROWTH RATE (g)
A105: WACC \ Terminal g | B105: 0.015 | C105: 0.02 | D105: 0.025 | E105: 0.03 | F105: 0.035
A106: 0.12 | B106: =(($E$81/(1+$A106)^0.5+$F$81/(1+$A106)^1.5+$G$81/(1+$A106)^2.5+$H$81/(1+$A106)^3.5+$I$81/(1+$A106)^4.5)+(($I$81*(1+B$105)/($A106-B$105))/(1+$A106)^4.5)-$B$14)/$B$10 | C106: =(($E$81/(1+$A106)^0.5+$F$81/(1+$A106)^1.5+$G$81/(1+$A106)^2.5+$H$81/(1+$A106)^3.5+$I$81/(1+$A106)^4.5)+(($I$81*(1+C$105)/($A106-C$105))/(1+$A106)^4.5)-$B$14)/$B$10 | D106: =(($E$81/(1+$A106)^0.5+$F$81/(1+$A106)^1.5+$G$81/(1+$A106)^2.5+$H$81/(1+$A106)^3.5+$I$81/(1+$A106)^4.5)+(($I$81*(1+D$105)/($A106-D$105))/(1+$A106)^4.5)-$B$14)/$B$10 | E106: =(($E$81/(1+$A106)^0.5+$F$81/(1+$A106)^1.5+$G$81/(1+$A106)^2.5+$H$81/(1+$A106)^3.5+$I$81/(1+$A106)^4.5)+(($I$81*(1+E$105)/($A106-E$105))/(1+$A106)^4.5)-$B$14)/$B$10 | F106: =(($E$81/(1+$A106)^0.5+$F$81/(1+$A106)^1.5+$G$81/(1+$A106)^2.5+$H$81/(1+$A106)^3.5+$I$81/(1+$A106)^4.5)+(($I$81*(1+F$105)/($A106-F$105))/(1+$A106)^4.5)-$B$14)/$B$10
A107: 0.13 | B107: =(($E$81/(1+$A107)^0.5+$F$81/(1+$A107)^1.5+$G$81/(1+$A107)^2.5+$H$81/(1+$A107)^3.5+$I$81/(1+$A107)^4.5)+(($I$81*(1+B$105)/($A107-B$105))/(1+$A107)^4.5)-$B$14)/$B$10 | C107: =(($E$81/(1+$A107)^0.5+$F$81/(1+$A107)^1.5+$G$81/(1+$A107)^2.5+$H$81/(1+$A107)^3.5+$I$81/(1+$A107)^4.5)+(($I$81*(1+C$105)/($A107-C$105))/(1+$A107)^4.5)-$B$14)/$B$10 | D107: =(($E$81/(1+$A107)^0.5+$F$81/(1+$A107)^1.5+$G$81/(1+$A107)^2.5+$H$81/(1+$A107)^3.5+$I$81/(1+$A107)^4.5)+(($I$81*(1+D$105)/($A107-D$105))/(1+$A107)^4.5)-$B$14)/$B$10 | E107: =(($E$81/(1+$A107)^0.5+$F$81/(1+$A107)^1.5+$G$81/(1+$A107)^2.5+$H$81/(1+$A107)^3.5+$I$81/(1+$A107)^4.5)+(($I$81*(1+E$105)/($A107-E$105))/(1+$A107)^4.5)-$B$14)/$B$10 | F107: =(($E$81/(1+$A107)^0.5+$F$81/(1+$A107)^1.5+$G$81/(1+$A107)^2.5+$H$81/(1+$A107)^3.5+$I$81/(1+$A107)^4.5)+(($I$81*(1+F$105)/($A107-F$105))/(1+$A107)^4.5)-$B$14)/$B$10
A108: =$B$15 | B108: =(($E$81/(1+$A108)^0.5+$F$81/(1+$A108)^1.5+$G$81/(1+$A108)^2.5+$H$81/(1+$A108)^3.5+$I$81/(1+$A108)^4.5)+(($I$81*(1+B$105)/($A108-B$105))/(1+$A108)^4.5)-$B$14)/$B$10 | C108: =(($E$81/(1+$A108)^0.5+$F$81/(1+$A108)^1.5+$G$81/(1+$A108)^2.5+$H$81/(1+$A108)^3.5+$I$81/(1+$A108)^4.5)+(($I$81*(1+C$105)/($A108-C$105))/(1+$A108)^4.5)-$B$14)/$B$10 | D108: =(($E$81/(1+$A108)^0.5+$F$81/(1+$A108)^1.5+$G$81/(1+$A108)^2.5+$H$81/(1+$A108)^3.5+$I$81/(1+$A108)^4.5)+(($I$81*(1+D$105)/($A108-D$105))/(1+$A108)^4.5)-$B$14)/$B$10 | E108: =(($E$81/(1+$A108)^0.5+$F$81/(1+$A108)^1.5+$G$81/(1+$A108)^2.5+$H$81/(1+$A108)^3.5+$I$81/(1+$A108)^4.5)+(($I$81*(1+E$105)/($A108-E$105))/(1+$A108)^4.5)-$B$14)/$B$10 | F108: =(($E$81/(1+$A108)^0.5+$F$81/(1+$A108)^1.5+$G$81/(1+$A108)^2.5+$H$81/(1+$A108)^3.5+$I$81/(1+$A108)^4.5)+(($I$81*(1+F$105)/($A108-F$105))/(1+$A108)^4.5)-$B$14)/$B$10
A109: 0.15 | B109: =(($E$81/(1+$A109)^0.5+$F$81/(1+$A109)^1.5+$G$81/(1+$A109)^2.5+$H$81/(1+$A109)^3.5+$I$81/(1+$A109)^4.5)+(($I$81*(1+B$105)/($A109-B$105))/(1+$A109)^4.5)-$B$14)/$B$10 | C109: =(($E$81/(1+$A109)^0.5+$F$81/(1+$A109)^1.5+$G$81/(1+$A109)^2.5+$H$81/(1+$A109)^3.5+$I$81/(1+$A109)^4.5)+(($I$81*(1+C$105)/($A109-C$105))/(1+$A109)^4.5)-$B$14)/$B$10 | D109: =(($E$81/(1+$A109)^0.5+$F$81/(1+$A109)^1.5+$G$81/(1+$A109)^2.5+$H$81/(1+$A109)^3.5+$I$81/(1+$A109)^4.5)+(($I$81*(1+D$105)/($A109-D$105))/(1+$A109)^4.5)-$B$14)/$B$10 | E109: =(($E$81/(1+$A109)^0.5+$F$81/(1+$A109)^1.5+$G$81/(1+$A109)^2.5+$H$81/(1+$A109)^3.5+$I$81/(1+$A109)^4.5)+(($I$81*(1+E$105)/($A109-E$105))/(1+$A109)^4.5)-$B$14)/$B$10 | F109: =(($E$81/(1+$A109)^0.5+$F$81/(1+$A109)^1.5+$G$81/(1+$A109)^2.5+$H$81/(1+$A109)^3.5+$I$81/(1+$A109)^4.5)+(($I$81*(1+F$105)/($A109-F$105))/(1+$A109)^4.5)-$B$14)/$B$10
A110: 0.16 | B110: =(($E$81/(1+$A110)^0.5+$F$81/(1+$A110)^1.5+$G$81/(1+$A110)^2.5+$H$81/(1+$A110)^3.5+$I$81/(1+$A110)^4.5)+(($I$81*(1+B$105)/($A110-B$105))/(1+$A110)^4.5)-$B$14)/$B$10 | C110: =(($E$81/(1+$A110)^0.5+$F$81/(1+$A110)^1.5+$G$81/(1+$A110)^2.5+$H$81/(1+$A110)^3.5+$I$81/(1+$A110)^4.5)+(($I$81*(1+C$105)/($A110-C$105))/(1+$A110)^4.5)-$B$14)/$B$10 | D110: =(($E$81/(1+$A110)^0.5+$F$81/(1+$A110)^1.5+$G$81/(1+$A110)^2.5+$H$81/(1+$A110)^3.5+$I$81/(1+$A110)^4.5)+(($I$81*(1+D$105)/($A110-D$105))/(1+$A110)^4.5)-$B$14)/$B$10 | E110: =(($E$81/(1+$A110)^0.5+$F$81/(1+$A110)^1.5+$G$81/(1+$A110)^2.5+$H$81/(1+$A110)^3.5+$I$81/(1+$A110)^4.5)+(($I$81*(1+E$105)/($A110-E$105))/(1+$A110)^4.5)-$B$14)/$B$10 | F110: =(($E$81/(1+$A110)^0.5+$F$81/(1+$A110)^1.5+$G$81/(1+$A110)^2.5+$H$81/(1+$A110)^3.5+$I$81/(1+$A110)^4.5)+(($I$81*(1+F$105)/($A110-F$105))/(1+$A110)^4.5)-$B$14)/$B$10
A112: SENSITIVITY ANALYSIS 2: IMPLIED SHARE PRICE ($) - REVENUE GROWTH DELTA VS. TARGET EBIT MARGIN
A113: Rev Growth Δ \ Target EBIT % | B113: 0.07 | C113: 0.09 | D113: 0.11 | E113: 0.13 | F113: 0.15
...

Sheet WACC
A1: THE REALREAL, INC. (NASDAQ: REAL) - COST OF CAPITAL (WACC)
A2: Valuation Date: August 19, 2026 | Currency: USD ($M) | Investment Banking Standard Model
A4: COST OF EQUITY CALCULATION (CAPM)
A5: Risk-Free Rate (Rf) [10-Year US Treasury] | B5: 0.0469
A6: Beta (β) [Adjusted Forward 5Y Monthly Beta] | B6: 2
A7: Equity Risk Premium (ERP) | B7: 0.055
A8: Cost of Equity (Ke) | B8: =B5+B6*B7
A10: COST OF DEBT CALCULATION
A11: Pre-Tax Cost of Debt (Kd) | B11: 0.075
A12: Marginal Tax Rate (t) | B12: =DCF!$B$53
A13: After-Tax Cost of Debt [Kd * (1 - t)] | B13: =B11*(1-B12)
A15: CAPITAL STRUCTURE & ENTERPRISE VALUE ($M)
A16: Current Stock Price ($) | B16: =DCF!$B$9
A17: Diluted Shares Outstanding (M) | B17: =DCF!$B$10
A18: Market Capitalization (Equity Value) | B18: =B16*B17
A19: Total Debt ($M) | B19: 375.8
A20: Cash & Cash Equivalents ($M) | B20: 119.1
A21: Net Debt ($M) [Total Debt - Cash] | B21: =B19-B20
A22: Enterprise Value ($M) [Market Cap + Net Debt] | B22: =B18+B21
A24: WEIGHTED AVERAGE COST OF CAPITAL (WACC) BREAKDOWN
A25: Capital Component | B25: Amount ($M) | C25: Capital Weight (%) | D25: Cost of Capital (%) | E25: Weighted Cost (%)
A26: Equity | B26: =B18 | C26: =B26/$B$22 | D26: =B8 | E26: =C26*D26
A27: Net Debt | B27: =B21 | C27: =B27/$B$22 | D27: =B13 | E27: =C27*D27
A28: Total Capitalization | B28: =SUM(B26:B27) | C28: =SUM(C26:C27) | D28: - | E28: =SUM(E26:E27)
A30: WEIGHTED AVERAGE COST OF CAPITAL (WACC) | B30: =E28
