Workbook

Sheet DCF
A1: Vital Farms, Inc. (VITL) – DCF Valuation Model
A2: NASDAQ: VITL | Model Date: August 20, 2026 | Fiscal Year End: December
A4: Scenario Selector (1=Bear / 2=Base / 3=Bull):
A5: Selected Case: | B5: 2
B6: =IF(B5=1,"Bear Case",IF(B5=2,"Base Case","Bull Case"))
A8: MARKET DATA & KEY INPUTS
A9: Item | B9: Value
A10: Current Stock Price | B10: 10.87
A11: Diluted Shares Outstanding (M) | B11: 42.9
A12: Market Capitalization ($M) | B12: =B10*B11
A13: Net Debt ($M) [Debt – Cash] | B13: 8.8
A15: BEAR CASE ASSUMPTIONS
A16: Assumption | G16: FY2026E | H16: FY2027E | I16: FY2028E | J16: FY2029E | K16: FY2030E
A17: Revenue Growth (%) | G17: 0.03 | H17: 0.08 | I17: 0.1 | J17: 0.1 | K17: 0.09
A18: Gross Margin (%) | G18: 0.26 | H18: 0.3 | I18: 0.32 | J18: 0.33 | K18: 0.34
A19: EBIT Margin (%) | G19: -0.02 | H19: 0.02 | I19: 0.05 | J19: 0.07 | K19: 0.08
A20: Tax Rate (%) | G20: 0.24
A21: D&A (% of Revenue) | G21: 0.04 | H21: 0.038 | I21: 0.035 | J21: 0.033 | K21: 0.03
A22: CapEx (% of Revenue) | G22: 0.095 | H22: 0.085 | I22: 0.07 | J22: 0.06 | K22: 0.05
A23: NWC Change (% of Δ Revenue) | G23: 0.03 | H23: 0.03 | I23: 0.03 | J23: 0.02 | K23: 0.02
A24: Terminal Growth Rate (%) | G24: 0.025
A25: WACC (%) | G25: 0.115
A27: BASE CASE ASSUMPTIONS
A28: Assumption | G28: FY2026E | H28: FY2027E | I28: FY2028E | J28: FY2029E | K28: FY2030E
A29: Revenue Growth (%) | G29: 0.035 | H29: 0.15 | I29: 0.18 | J29: 0.16 | K29: 0.13
A30: Gross Margin (%) | G30: 0.28 | H30: 0.34 | I30: 0.36 | J30: 0.37 | K30: 0.38
A31: EBIT Margin (%) | G31: 0 | H31: 0.06 | I31: 0.09 | J31: 0.11 | K31: 0.13
A32: Tax Rate (%) | G32: 0.24
A33: D&A (% of Revenue) | G33: 0.038 | H33: 0.035 | I33: 0.032 | J33: 0.03 | K33: 0.028
A34: CapEx (% of Revenue) | G34: 0.092 | H34: 0.075 | I34: 0.06 | J34: 0.05 | K34: 0.045
A35: NWC Change (% of Δ Revenue) | G35: 0.025 | H35: 0.025 | I35: 0.02 | J35: 0.02 | K35: 0.015
A36: Terminal Growth Rate (%) | G36: 0.03
A37: WACC (%) | G37: 0.105
A39: BULL CASE ASSUMPTIONS
A40: Assumption | G40: FY2026E | H40: FY2027E | I40: FY2028E | J40: FY2029E | K40: FY2030E
A41: Revenue Growth (%) | G41: 0.04 | H41: 0.2 | I41: 0.22 | J41: 0.2 | K41: 0.16
A42: Gross Margin (%) | G42: 0.3 | H42: 0.36 | I42: 0.38 | J42: 0.39 | K42: 0.4
A43: EBIT Margin (%) | G43: 0.02 | H43: 0.09 | I43: 0.13 | J43: 0.15 | K43: 0.17
A44: Tax Rate (%) | G44: 0.24
A45: D&A (% of Revenue) | G45: 0.036 | H45: 0.032 | I45: 0.03 | J45: 0.028 | K45: 0.026
A46: CapEx (% of Revenue) | G46: 0.09 | H46: 0.068 | I46: 0.055 | J46: 0.047 | K46: 0.042
A47: NWC Change (% of Δ Revenue) | G47: 0.02 | H47: 0.02 | I47: 0.018 | J47: 0.015 | K47: 0.012
A48: Terminal Growth Rate (%) | G48: 0.035
A49: WACC (%) | G49: 0.095
A51: SELECTED CASE ASSUMPTIONS (auto-updates with Scenario Selector above)
A52: Revenue Growth — Selected (%) | G52: =INDEX(G17:G41,1,$B$5) | H52: =INDEX(H17:H41,1,$B$5) | I52: =INDEX(I17:I41,1,$B$5) | J52: =INDEX(J17:J41,1,$B$5) | K52: =INDEX(K17:K41,1,$B$5)
A53: Gross Margin — Selected (%) | G53: =INDEX(G18:G42,1,$B$5) | H53: =INDEX(H18:H42,1,$B$5) | I53: =INDEX(I18:I42,1,$B$5) | J53: =INDEX(J18:J42,1,$B$5) | K53: =INDEX(K18:K42,1,$B$5)
A54: EBIT Margin — Selected (%) | G54: =INDEX(G19:G43,1,$B$5) | H54: =INDEX(H19:H43,1,$B$5) | I54: =INDEX(I19:I43,1,$B$5) | J54: =INDEX(J19:J43,1,$B$5) | K54: =INDEX(K19:K43,1,$B$5)
A55: Tax Rate — Selected (%) | G55: =INDEX(G20:G44,1,$B$5)
A56: D&A % Rev — Selected | G56: =INDEX(G21:G45,1,$B$5) | H56: =INDEX(H21:H45,1,$B$5) | I56: =INDEX(I21:I45,1,$B$5) | J56: =INDEX(J21:J45,1,$B$5) | K56: =INDEX(K21:K45,1,$B$5)
A57: CapEx % Rev — Selected | G57: =INDEX(G22:G46,1,$B$5) | H57: =INDEX(H22:H46,1,$B$5) | I57: =INDEX(I22:I46,1,$B$5) | J57: =INDEX(J22:J46,1,$B$5) | K57: =INDEX(K22:K46,1,$B$5)
A58: NWC Δ% — Selected | G58: =INDEX(G23:G47,1,$B$5) | H58: =INDEX(H23:H47,1,$B$5) | I58: =INDEX(I23:I47,1,$B$5) | J58: =INDEX(J23:J47,1,$B$5) | K58: =INDEX(K23:K47,1,$B$5)
A59: Terminal Growth Rate — Selected (%) | G59: =INDEX(G24:G48,1,$B$5)
A60: WACC — Selected | G60: =INDEX(G25:G49,1,$B$5)
A62: INCOME STATEMENT ($M)
B63: FY2021A | C63: FY2022A | D63: FY2023A | E63: FY2024A | F63: FY2025A | G63: FY2026E | H63: FY2027E | I63: FY2028E | J63: FY2029E | K63: FY2030E
A64: Net Revenue ($M) | B64: 260.9 | C64: 362.1 | D64: 471.9 | E64: 606.3 | F64: 759.4 | G64: =F64*(1+G52) | H64: =G64*(1+H52) | I64: =H64*(1+I52) | J64: =I64*(1+J52) | K64: =J64*(1+K52)
A65: % Growth | B65: — | C65: =C64/B64-1 | D65: =D64/C64-1 | E65: =E64/D64-1 | F65: =F64/E64-1 | G65: =G64/F64-1 | H65: =H64/G64-1 | I65: =I64/H64-1 | J65: =J64/I64-1 | K65: =K64/J64-1
A67: Gross Profit ($M) | B67: 82.9 | C67: 110.5 | D67: 162.3 | E67: 229.9 | F67: 285.7 | G67: =G64*G53 | H67: =H64*H53 | I67: =I64*I53 | J67: =J64*J53 | K67: =K64*K53
A68: % Gross Margin | B68: =B67/B64 | C68: =C67/C64 | D68: =D67/D64 | E68: =E67/E64 | F68: =F67/F64 | G68: =G67/G64 | H68: =H67/H64 | I68: =I67/I64 | ... K68: =K67/K64
A70: SG&A / Operating Expenses ($M) | B70: 82.85 | C70: 106.15 | D70: 129.07 | E70: 166.37 | F70: 197.31 | G70: =G67-G73 | H70: =H67-H73 | I70: =I67-I73 | J70: =J67-J73 | K70: =K67-K73
A71: % Revenue | B71: =B70/B64 | C71: =C70/C64 | D71: =D70/D64 | E71: =E70/E64 | F71: =F70/F64 | G71: =G70/G64 | H71: =H70/H64 | I71: =I70/I64 | ... K71: =K70/K64
A73: EBIT ($M) | B73: 0.05 | C73: 4.3 | D73: 33.25 | E73: 63.55 | F73: 88.37 | G73: =G64*G54 | H73: =H64*H54 | I73: =I64*I54 | J73: =J64*J54 | K73: =K64*K54
A74: % EBIT Margin | B74: =IF(B64=0,0,B73/B64) | C74: =IF(C64=0,0,C73/C64) | D74: =IF(D64=0,0,D73/D64) | E74: =IF(E64=0,0,E73/E64) | F74: =IF(F64=0,0,F73/F64) | G74: =IF(G64=0,0,G73/G64) | H74: =IF(H64=0,0,H73/H64) | I74: =IF(I64=0,0,I73/I64) | ... K74: =IF(K64=0,0,K73/K64)
A76: Income Tax ($M) | B76: 0 | C76: 1.6 | D76: 6.64 | E76: 14.15 | F76: 24.98 | G76: =MAX(0,G73*$G$55) | H76: =MAX(0,H73*$G$55) | I76: =MAX(0,I73*$G$55) | J76: =MAX(0,J73*$G$55) | K76: =MAX(0,K73*$G$55)
A77: Effective Tax Rate | B77: =IF(B73=0,0,B76/B73) | C77: =IF(C73=0,0,C76/C73) | D77: =IF(D73=0,0,D76/D73) | E77: =IF(E73=0,0,E76/E73) | F77: =IF(F73=0,0,F76/F73) | G77: =IF(G73=0,0,G76/G73) | H77: =IF(H73=0,0,H76/H73) | I77: =IF(I73=0,0,I76/I73) | ... K77: =IF(K73=0,0,K76/K73)
A79: NOPAT ($M) | B79: 0.05 | C79: 2.7 | D79: 26.61 | E79: 49.4 | F79: 63.39 | G79: =G73-G76 | H79: =H73-H76 | I79: =I73-I76 | J79: =J73-J76 | K79: =K73-K76
A81: FREE CASH FLOW BUILD ($M)
B82: FY2021A | C82: FY2022A | D82: FY2023A | E82: FY2024A | F82: FY2025A | G82: FY2026E | H82: FY2027E | I82: FY2028E | J82: FY2029E | K82: FY2030E
A83: NOPAT ($M) | B83: =B79 | C83: =C79 | D83: =D79 | E83: =E79 | F83: =F79 | G83: =G79 | H83: =H79 | I83: =I79 | ... K83: =K79
A84: (+) D&A ($M) | B84: 3.54 | C84: 5.44 | D84: 7.93 | E84: 13.09 | F84: 14.51 | G84: =G64*G56 | H84: =H64*H56 | I84: =I64*I56 | J84: =J64*J56 | K84: =K64*K56
A85: D&A % Revenue | B85: =B84/B64 | C85: =C84/C64 | D85: =D84/D64 | E85: =E84/E64 | F85: =F84/F64 | G85: =G84/G64 | H85: =H84/H64 | I85: =I84/I64 | ... K85: =K84/K64
A86: (-) CapEx ($M) | B86: 16.71 | C86: 10.56 | D86: 11.54 | E86: 28.65 | F86: 81.95 | G86: =G64*G57 | H86: =H64*H57 | I86: =I64*I57 | J86: =J64*J57 | K86: =K64*K57
A87: CapEx % Revenue | B87: =B86/B64 | C87: =C86/C64 | D87: =D86/D64 | E87: =E86/E64 | F87: =F86/F64 | G87: =G86/G64 | H87: =H86/H64 | I87: =I86/I64 | ... K87: =K86/K64
A88: (-) Δ NWC ($M) | B88: -8.21 | C88: 24.18 | D88: -2.49 | E88: 16.22 | F88: 76.31 | G88: =(G64-F64)*G58 | H88: =(H64-G64)*H58 | I88: =(I64-H64)*I58 | J88: =(J64-I64)*J58 | K88: =(K64-J64)*K58
A89: NWC Δ% of Revenue Change | G89: =IF(G64-F64=0,0,G88/(G64-F64)) | H89: =IF(H64-G64=0,0,H88/(H64-G64)) | I89: =IF(I64-H64=0,0,I88/(I64-H64)) | J89: =IF(J64-I64=0,0,J88/(J64-I64)) | K89: =IF(K64-J64=0,0,K88/(K64-J64))
A91: Unlevered Free Cash Flow ($M) | B91: 1.18 | C91: -18.36 | D91: 30.8 | E91: 39.23 | F91: -22.78 | G91: =G83+G84-G86-G88 | H91: =H83+H84-H86-H88 | I91: =I83+I84-I86-I88 | J91: =J83+J84-J86-J88 | K91: =K83+K84-K86-K88
A93: DCF DISCOUNTING (Mid-Year Convention)
G94: FY2026E | H94: FY2027E | I94: FY2028E | J94: FY2029E | K94: FY2030E
A95: Discount Period (mid-year) | G95: 0.5 | H95: 1.5 | I95: 2.5 | J95: 3.5 | K95: 4.5
A96: Discount Factor | G96: =1/(1+WACC!$B$27)^G95 | H96: =1/(1+WACC!$B$27)^H95 | I96: =1/(1+WACC!$B$27)^I95 | J96: =1/(1+WACC!$B$27)^J95 | K96: =1/(1+WACC!$B$27)^K95
A97: PV of FCF ($M) | G97: =G91*G96 | H97: =H91*H96 | I97: =I91*I96 | J97: =J91*J96 | K97: =K91*K96
A99: TERMINAL VALUE (Perpetuity Growth Method)
A100: Terminal Year FCF ($M) | K100: =K91*(1+$G$59)
A101: Terminal Value ($M) | K101: =K100/(WACC!$B$27-$G$59)
A102: PV of Terminal Value ($M) | K102: =K101/(1+WACC!$B$27)^4.5
A104: VALUATION SUMMARY
A105: Sum of PV of Projected FCFs ($M) | B105: =SUM(G97:K97)
A106: PV of Terminal Value ($M) | B106: =K102
A107: Enterprise Value ($M) | B107: =B105+B106
A108: (-) Net Debt ($M) [+ if net debt, – if net cash] | B108: =B13
A109: Equity Value ($M) | B109: =B107-B108
A111: Diluted Shares Outstanding (M) | B111: =B11
A112: IMPLIED SHARE PRICE | B112: =IF(B111=0,0,B109/B111)
A113: Current Stock Price | B113: =B10
A114: Implied Upside / (Downside) | B114: =B112/B113-1
A117: SENSITIVITY 1 — Implied Price: WACC vs Terminal Growth Rate
A118: WACC \ Term.Growth | B118: 0.02 | C118: 0.025 | D118: 0.03 | E118: 0.035 | F118: 0.04
A119: 0.085 | B119: =IF(B11=0,0,(G91/(1+0.085)^0.5+H91/(1+0.085)^1.5+I91/(1+0.085)^2.5+J91/(1+0.085)^3.5+K91/(1+0.085)^4.5+(K91*(1+0.02)/(0.085-0.02))/(1+0.085)^4.5-B13)/B11) | C119: =IF(B11=0,0,(G91/(1+0.085)^0.5+H91/(1+0.085)^1.5+I91/(1+0.085)^2.5+J91/(1+0.085)^3.5+K91/(1+0.085)^4.5+(K91*(1+0.025)/(0.085-0.025))/(1+0.085)^4.5-B13)/B11) | D119: =IF(B11=0,0,(G91/(1+0.085)^0.5+H91/(1+0.085)^1.5+I91/(1+0.085)^2.5+J91/(1+0.085)^3.5+K91/(1+0.085)^4.5+(K91*(1+0.03)/(0.085-0.03))/(1+0.085)^4.5-B13)/B11) | E119: =IF(B11=0,0,(G91/(1+0.085)^0.5+H91/(1+0.085)^1.5+I91/(1+0.085)^2.5+J91/(1+0.085)^3.5+K91/(1+0.085)^4.5+(K91*(1+0.035)/(0.085-0.035))/(1+0.085)^4.5-B13)/B11) | F119: =IF(B11=0,0,(G91/(1+0.085)^0.5+H91/(1+0.085)^1.5+I91/(1+0.085)^2.5+J91/(1+0.085)^3.5+K91/(1+0.085)^4.5+(K91*(1+0.04)/(0.085-0.04))/(1+0.085)^4.5-B13)/B11)
A120: 0.095 | B120: =IF(B11=0,0,(G91/(1+0.095)^0.5+H91/(1+0.095)^1.5+I91/(1+0.095)^2.5+J91/(1+0.095)^3.5+K91/(1+0.095)^4.5+(K91*(1+0.02)/(0.095-0.02))/(1+0.095)^4.5-B13)/B11) | C120: =IF(B11=0,0,(G91/(1+0.095)^0.5+H91/(1+0.095)^1.5+I91/(1+0.095)^2.5+J91/(1+0.095)^3.5+K91/(1+0.095)^4.5+(K91*(1+0.025)/(0.095-0.025))/(1+0.095)^4.5-B13)/B11) | D120: =IF(B11=0,0,(G91/(1+0.095)^0.5+H91/(1+0.095)^1.5+I91/(1+0.095)^2.5+J91/(1+0.095)^3.5+K91/(1+0.095)^4.5+(K91*(1+0.03)/(0.095-0.03))/(1+0.095)^4.5-B13)/B11) | E120: =IF(B11=0,0,(G91/(1+0.095)^0.5+H91/(1+0.095)^1.5+I91/(1+0.095)^2.5+J91/(1+0.095)^3.5+K91/(1+0.095)^4.5+(K91*(1+0.035)/(0.095-0.035))/(1+0.095)^4.5-B13)/B11) | F120: =IF(B11=0,0,(G91/(1+0.095)^0.5+H91/(1+0.095)^1.5+I91/(1+0.095)^2.5+J91/(1+0.095)^3.5+K91/(1+0.095)^4.5+(K91*(1+0.04)/(0.095-0.04))/(1+0.095)^4.5-B13)/B11)
...

Sheet WACC
A1: Vital Farms (VITL) — WACC Calculation
A2: Date: August 20, 2026 | CAPM Methodology
A4: COST OF EQUITY — CAPM
A5: Item | B5: Value | C5: Notes
A6: Risk-Free Rate (10Y US Treasury) | B6: 0.0468 | C6: FRED DGS10 — Aug 17 2026
A7: Beta (5-Year) | B7: 1.3756 | C7: GuruFocus, Aug 19 2026
A8: Equity Risk Premium (ERP) | B8: 0.055 | C8: Damodaran, 2026 US ERP
A9: Cost of Equity (CAPM) | B9: =B6+B7*B8 | C9: =Rf + β × ERP
A11: COST OF DEBT
A12: Item | B12: Value
A13: Pre-Tax Cost of Debt | B13: 0.085 | C13: SOFR + spread estimate on new term loan
A14: Tax Rate (for debt shield) | B14: =DCF!$G$55 | C14: Linked from DCF sheet
A15: After-Tax Cost of Debt | B15: =B13*(1-B14)
A17: CAPITAL STRUCTURE
A18: Item | B18: Value
A19: Pre-Tax Cost of Debt (ref) | B19: =B13
A20: Current Stock Price | B20: =DCF!$B$10
A21: Diluted Shares (M) | B21: =DCF!$B$11
A22: Market Capitalization ($M) | B22: =B20*B21
A23: Net Debt ($M) | B23: =DCF!$B$13
A24: Enterprise Value ($M) | B24: =B22+B23
A25: Equity Weight | B25: =IF(B24=0,1,B22/B24)
A26: Debt Weight | B26: =IF(B24=0,0,B23/B24)
A27: WEIGHTED AVG COST OF CAPITAL (WACC) | B27: =D30+D31
A28: WACC CALCULATION
B29: Weight | C29: Cost | D29: Contribution
A30: Equity | B30: =B25 | C30: =B9 | D30: =B30*C30
A31: Debt | B31: =B26 | C31: =B15 | D31: =B31*C31
